Workbook

Sheet Executive Dashboard
A1: PRIME BISTRO — EXECUTIVE DASHBOARD
A2: F&B Controlling System | Live — updates automatically as data is entered
A4: 1. MONTHLY SALES & PROFIT SNAPSHOT
A6: FOOD SALES (ETB) | D6: BEVERAGE SALES (ETB) | G6: GROSS SALES (ETB) | J6: NET SALES (ETB)
A7: ='Daily Flash Cost'!AG4 -> 224090 | D7: ='Daily Flash Cost'!AG5 -> 82140 | G7: ='Daily Flash Cost'!AG6 -> 306230 | J7: ='Daily Flash Cost'!AG9 -> 305330
A9: TOTAL ACTUAL COST (ETB) | D9: GROSS PROFIT (ETB) | G9: OVERALL F&B COST % | J9: GROSS PROFIT %
A10: ='Daily Flash Cost'!AG15 -> 107557.6 | D10: ='Daily Flash Cost'!AG20 -> 211104.09 | G10: ='Daily Flash Cost'!AG23 -> 0.35123144 | J10: =IFERROR('Daily Flash Cost'!AG20/'Daily Flash Cost'!AG9,0) -> 0.69139649
A12: FOOD COST % | D12: BEVERAGE COST % | G12: AVG. DAILY NET SALES (ETB) | J12: DAYS OF DATA (Month)
A13: ='Daily Flash Cost'!AG21 -> 0.33492513 | D13: ='Daily Flash Cost'!AG22 -> 0.39571744 | G13: =IFERROR('Daily Flash Cost'!AG9/COUNTIF('Daily Flash Cost'!B3:AF3,"<>"),0) -> 9849.3548 | J13: =COUNT('Daily Flash Cost'!B4:AF4) -> 31
A16: 2. LOSS & VARIANCE CONTROL
A18: TOTAL WASTAGE VALUE (ETB) | D18: STAFF MEAL COST (ETB) | G18: VOID + COMP SALES (ETB) | J18: INVENTORY VARIANCE COST (ETB)
A19: =SUM(Wastage!$I:$I) -> 219.5 | D19: =SUM('Daily Staff Meal'!$H:$H) -> 1188 | G19: =SUM('Daily Void'!$J:$J)+SUM(Complementary!$J:$J) -> 900 | J19: =SUM('Inventory Variance'!$I:$I) -> -14739.195
A21: RECIPE VARIANCE COST (ETB) | D21: ITEMS TO INVESTIGATE (Variance) | G21: WASTAGE EVENTS LOGGED | J21: VOID EVENTS LOGGED
A22: =SUM('Theoretical Consumption'!$M:$M) -> 21671.133 | D22: =COUNTIF('Inventory Variance'!$K:$K,"INVESTIGATE") -> 33 | G22: =COUNTA(Wastage!$C$5:$C$64) -> 4 | J22: =COUNTA('Daily Void'!$E$5:$E$44) -> 2
A25: 3. MAIN STORE INVENTORY HEALTH (Par Level Monitoring)
A27: TOTAL STORE VALUE (ETB) | D27: ITEMS BELOW MIN PAR | G27: ITEMS OVERSTOCKED | J27: ITEMS WITHIN PAR (OK)
A28: =SUM('Store Inventory'!G4:G41) -> 230960 | D28: =COUNTIF('Store Inventory'!J4:J41,"REORDER NOW") -> 8 | G28: =COUNTIF('Store Inventory'!J4:J41,"OVERSTOCK") -> 21 | J28: =COUNTIF('Store Inventory'!J4:J41,"OK") -> 6
A30: TOP REORDER ALERTS (Main Store)
A31: Item | B31: Category | C31: Available Qty | D31: Min Par | E31: Status
A32: =IFERROR(INDEX('Store Inventory'!$B$4:$B$41,MATCH(1,'Store Inventory'!$L$4:$L$41,0)),"—") -> Black Tea Bags | B32: =IFERROR(INDEX('Store Inventory'!$C$4:$C$41,MATCH(1,'Store Inventory'!$L$4:$L$41,0)),"") -> Coffee & Tea | C32: =IFERROR(INDEX('Store Inventory'!$E$4:$E$41,MATCH(1,'Store Inventory'!$L$4:$L$41,0)),"") -> 0 | D32: =IFERROR(INDEX('Store Inventory'!$H$4:$H$41,MATCH(1,'Store Inventory'!$L$4:$L$41,0)),"") -> 20 | E32: =IF(A32="—","","REORDER NOW") -> REORDER NOW
A33: =IFERROR(INDEX('Store Inventory'!$B$4:$B$41,MATCH(2,'Store Inventory'!$L$4:$L$41,0)),"—") -> Green Tea Bags | B33: =IFERROR(INDEX('Store Inventory'!$C$4:$C$41,MATCH(2,'Store Inventory'!$L$4:$L$41,0)),"") -> Coffee & Tea | C33: =IFERROR(INDEX('Store Inventory'!$E$4:$E$41,MATCH(2,'Store Inventory'!$L$4:$L$41,0)),"") -> 0 | D33: =IFERROR(INDEX('Store Inventory'!$H$4:$H$41,MATCH(2,'Store Inventory'!$L$4:$L$41,0)),"") -> 20 | E33: =IF(A33="—","","REORDER NOW") -> REORDER NOW
A34: =IFERROR(INDEX('Store Inventory'!$B$4:$B$41,MATCH(3,'Store Inventory'!$L$4:$L$41,0)),"—") -> Cocoa Powder | B34: =IFERROR(INDEX('Store Inventory'!$C$4:$C$41,MATCH(3,'Store Inventory'!$L$4:$L$41,0)),"") -> Coffee & Tea | C34: =IFERROR(INDEX('Store Inventory'!$E$4:$E$41,MATCH(3,'Store Inventory'!$L$4:$L$41,0)),"") -> 0 | D34: =IFERROR(INDEX('Store Inventory'!$H$4:$H$41,MATCH(3,'Store Inventory'!$L$4:$L$41,0)),"") -> 10 | E34: =IF(A34="—","","REORDER NOW") -> REORDER NOW
A35: =IFERROR(INDEX('Store Inventory'!$B$4:$B$41,MATCH(4,'Store Inventory'!$L$4:$L$41,0)),"—") -> Fresh Mint Leaves | B35: =IFERROR(INDEX('Store Inventory'!$C$4:$C$41,MATCH(4,'Store Inventory'!$L$4:$L$41,0)),"") -> Bar Garnish | C35: =IFERROR(INDEX('Store Inventory'!$E$4:$E$41,MATCH(4,'Store Inventory'!$L$4:$L$41,0)),"") -> 0 | D35: =IFERROR(INDEX('Store Inventory'!$H$4:$H$41,MATCH(4,'Store Inventory'!$L$4:$L$41,0)),"") -> 10 | E35: =IF(A35="—","","REORDER NOW") -> REORDER NOW
A36: =IFERROR(INDEX('Store Inventory'!$B$4:$B$41,MATCH(5,'Store Inventory'!$L$4:$L$41,0)),"—") -> Paper Napkins | B36: =IFERROR(INDEX('Store Inventory'!$C$4:$C$41,MATCH(5,'Store Inventory'!$L$4:$L$41,0)),"") -> Consumables | C36: =IFERROR(INDEX('Store Inventory'!$E$4:$E$41,MATCH(5,'Store Inventory'!$L$4:$L$41,0)),"") -> 0 | D36: =IFERROR(INDEX('Store Inventory'!$H$4:$H$41,MATCH(5,'Store Inventory'!$L$4:$L$41,0)),"") -> 100 | E36: =IF(A36="—","","REORDER NOW") -> REORDER NOW
A38: 4. MENU PORTFOLIO OVERVIEW
A40: TOTAL ACTIVE MENU ITEMS | D40: STARS | G40: PLOWHORSES | J40: PUZZLES + DOGS
A41: 26 | D41: =COUNTIF('Menu Engineering'!$J$4:$J$29,"STAR") -> 3 | G41: =COUNTIF('Menu Engineering'!$J$4:$J$29,"PLOWHORSE") -> 6 | J41: =COUNTIF('Menu Engineering'!$J$4:$J$29,"PUZZLE")+COUNTIF('Menu Engineering'!$J$4:$J$29,"DOG") -> 17
A43: TOP 5 BEST SELLERS (by Qty Sold) | G43: TOP 5 REVENUE DRIVERS (by Monthly Sales)
A44: Menu Item | B44: Category | C44: Qty Sold | G44: Menu Item | H44: Category | I44: Revenue (ETB)
A45: =IFERROR(INDEX('Menu Engineering'!$B$4:$B$29,MATCH(1,'Menu Engineering'!$M$4:$M$29,0)),"—") -> Cappuccino | B45: =IFERROR(INDEX('Menu Engineering'!$C$4:$C$29,MATCH(1,'Menu Engineering'!$M$4:$M$29,0)),"") -> Beverage | C45: =IFERROR(INDEX('Menu Engineering'!$D$4:$D$29,MATCH(1,'Menu Engineering'!$M$4:$M$29,0)),"") -> 157 | G45: =IFERROR(INDEX('Menu Engineering'!$B$4:$B$29,MATCH(1,'Menu Engineering'!$N$4:$N$29,0)),"—") -> Margherita Pizza | H45: =IFERROR(INDEX('Menu Engineering'!$C$4:$C$29,MATCH(1,'Menu Engineering'!$N$4:$N$29,0)),"") -> Food | I45: =IFERROR(INDEX('Menu Engineering'!$L$4:$L$29,MATCH(1,'Menu Engineering'!$N$4:$N$29,0)),"") -> 31160
A46: =IFERROR(INDEX('Menu Engineering'!$B$4:$B$29,MATCH(2,'Menu Engineering'!$M$4:$M$29,0)),"—") -> Americano | B46: =IFERROR(INDEX('Menu Engineering'!$C$4:$C$29,MATCH(2,'Menu Engineering'!$M$4:$M$29,0)),"") -> Beverage | C46: =IFERROR(INDEX('Menu Engineering'!$D$4:$D$29,MATCH(2,'Menu Engineering'!$M$4:$M$29,0)),"") -> 137 | G46: =IFERROR(INDEX('Menu Engineering'!$B$4:$B$29,MATCH(2,'Menu Engineering'!$N$4:$N$29,0)),"—") -> Classic Beef Burger | H46: =IFERROR(INDEX('Menu Engineering'!$C$4:$C$29,MATCH(2,'Menu Engineering'!$N$4:$N$29,0)),"") -> Food | I46: =IFERROR(INDEX('Menu Engineering'!$L$4:$L$29,MATCH(2,'Menu Engineering'!$N$4:$N$29,0)),"") -> 29120
A47: =IFERROR(INDEX('Menu Engineering'!$B$4:$B$29,MATCH(3,'Menu Engineering'!$M$4:$M$29,0)),"—") -> Coca-Cola | B47: =IFERROR(INDEX('Menu Engineering'!$C$4:$C$29,MATCH(3,'Menu Engineering'!$M$4:$M$29,0)),"") -> Beverage | C47: =IFERROR(INDEX('Menu Engineering'!$D$4:$D$29,MATCH(3,'Menu Engineering'!$M$4:$M$29,0)),"") -> 103 | G47: =IFERROR(INDEX('Menu Engineering'!$B$4:$B$29,MATCH(3,'Menu Engineering'!$N$4:$N$29,0)),"—") -> Spaghetti Bolognese | H47: =IFERROR(INDEX('Menu Engineering'!$C$4:$C$29,MATCH(3,'Menu Engineering'!$N$4:$N$29,0)),"") -> Food | I47: =IFERROR(INDEX('Menu Engineering'!$L$4:$L$29,MATCH(3,'Menu Engineering'!$N$4:$N$29,0)),"") -> 23100
A48: =IFERROR(INDEX('Menu Engineering'!$B$4:$B$29,MATCH(4,'Menu Engineering'!$M$4:$M$29,0)),"—") -> Classic Beef Burger | B48: =IFERROR(INDEX('Menu Engineering'!$C$4:$C$29,MATCH(4,'Menu Engineering'!$M$4:$M$29,0)),"") -> Food | C48: =IFERROR(INDEX('Menu Engineering'!$D$4:$D$29,MATCH(4,'Menu Engineering'!$M$4:$M$29,0)),"") -> 91 | G48: =IFERROR(INDEX('Menu Engineering'!$B$4:$B$29,MATCH(4,'Menu Engineering'!$N$4:$N$29,0)),"—") -> Cappuccino | H48: =IFERROR(INDEX('Menu Engineering'!$C$4:$C$29,MATCH(4,'Menu Engineering'!$N$4:$N$29,0)),"") -> Beverage | I48: =IFERROR(INDEX('Menu Engineering'!$L$4:$L$29,MATCH(4,'Menu Engineering'!$N$4:$N$29,0)),"") -> 17270
A49: =IFERROR(INDEX('Menu Engineering'!$B$4:$B$29,MATCH(5,'Menu Engineering'!$M$4:$M$29,0)),"—") -> Butter Croissant | B49: =IFERROR(INDEX('Menu Engineering'!$C$4:$C$29,MATCH(5,'Menu Engineering'!$M$4:$M$29,0)),"") -> Food | C49: =IFERROR(INDEX('Menu Engineering'!$D$4:$D$29,MATCH(5,'Menu Engineering'!$M$4:$M$29,0)),"") -> 85 | G49: =IFERROR(INDEX('Menu Engineering'!$B$4:$B$29,MATCH(5,'Menu Engineering'!$N$4:$N$29,0)),"—") -> Double Beef Burger | H49: =IFERROR(INDEX('Menu Engineering'!$C$4:$C$29,MATCH(5,'Menu Engineering'!$N$4:$N$29,0)),"") -> Food | I49: =IFERROR(INDEX('Menu Engineering'!$L$4:$L$29,MATCH(5,'Menu Engineering'!$N$4:$N$29,0)),"") -> 17220
A51: 5. NOTES
A53: All figures on this dashboard are live formulas pulling from Daily Sales, Daily Flash Cost, Store Inventory, Wastage, Daily Void, Complementary, Daily Staff Meal, Inventory Variance, Theoretical Consumption and Menu Engineering. Enter your outlet's real daily data in those sheets and every number here recalculates automatically — nothing on this page needs to be typed in directly.

Sheet Overview
A1: PRIME BISTRO — F&B CONTROLLING SYSTEM
A2: System Guide & Overview
B4: 1. PURPOSE OF THIS SYSTEM
B5: This workbook is the complete F&B costing and control system for Prime Bistro, rebuilt for a SINGLE OUTLET. It exists to answer, every day, three questions: what did we sell, what did it cost us, and where is money being lost — so food cost can be actively managed rather than discovered a month later.
B7: 2. HOW THE SINGLE-STORE, SINGLE-OUTLET MODEL WORKS
B8: All ingredients are purchased into and valued in one Main Store (moving-average costing). The Main Store issues stock to the outlet's Kitchen & Bar, which is where daily consumption, sales, and wastage are tracked.
B10: 3. THE FLOW OF THE SYSTEM (follow the sheets in this order)
B11: Item Master | C11: Master list of every raw ingredient (Food / Beverage / Others) with standard cost, used to build recipes.
B12: Menu Master | C12: Every sellable menu item (Food, Beverage, To-Go). This is what recipes and daily sales are built from.
B13: Recipe Master | C13: Ingredient breakdown + standard cost for every menu item — the basis of theoretical food cost.
B14: Sub-Recipe | C14: Homemade components (buns, dressings, sauces, dough) costed separately, then used inside Recipe Master.
B15: Purchase Register | C15: What was bought, from whom, at what cost — feeds the Main Store.
B16: Store Receiving | C16: Goods received into the Main Store, building up available stock and average cost.
B17: Store Inventory | C17: The Main Store balance — with Min/Max Par Level and an automatic Reorder Status flag.
B18: Store Issue | C18: Stock issued from the Main Store to the outlet's Kitchen & Bar.
B19: Kitchen & Bar Receiving | C19: Confirms what the outlet actually received from the Main Store.
B20: Daily Inventory / Semi-Finished Inventory | C20: Daily stock counts at the outlet, for raw items and homemade prep items.
B21: Wastage / Daily Void / Complementary / Staff Meal | C21: Every way food leaves the building without being paid for in full.
B22: Daily Sales | C22: Every menu item sold, day by day for the month — the engine of the whole system.
... B26: Executive Dashboard | C26: One-page view of every major KPI above, updating live as data is entered.
B28: 4. HOW ITEM MASTER, MENU MASTER, RECIPE MASTER AND SUB-RECIPE FIT TOGETHER
B29: Item Master is built to serve Menu Master: every raw ingredient in Item Master exists because it is needed by a recipe on Menu Master. A Sub-Recipe is any homemade component — burger buns, sandwich bread, pizza dough, bolognese/alfredo/pizza sauce, caesar dressing, mojito syrup — costed once as its own small recipe with a batch yield, then pulled into Recipe Master as a single costed ingredient line. Whenever a new menu item is added: add its raw ingredients to Item Master (if not already there), cost any new homemade component in Sub-Recipe, then build its line in Recipe Master — the rest of the system (Daily Sales standard cost, Flash Cost, Menu Engineering, Theoretical Consumption) picks it up automatically.
B31: 5. MAIN STORE PAR LEVELS
B32: Every item in Store Inventory carries a Min Par Level and Max Par Level. A Reorder Status column flags each item automatically as REORDER NOW (below minimum), OVERSTOCK (above maximum) or OK — colour-coded so the purchaser can act at a glance instead of reading raw numbers.
B34: 6. COLOUR KEY USED THROUGHOUT THE SYSTEM
B35: Blue text = a cell you type into (inputs, prices, par levels, quantities, dates). Black text = an automatic formula — never overtype these. Green text = a live link pulled from another sheet. Shaded rows = subtotal / total rows. Yellow-tinted cells = key assumptions.
B37: 7. TRIAL DATA IN THIS FILE
B38: Every transactional sheet (Purchase Register, Store Receiving, Store Issue, Daily Sales, Wastage, Void, Complementary, Staff Meal, Daily Inventory) has been pre-filled with realistic sample data for the first few days/events of the month so you can see the whole system working end-to-end — every report, variance and the Executive Dashboard are already live. Simply clear the blue input cells and replace them with your own outlet's real numbers; every formula will recalculate automatically.

Sheet Item Master
A1: ITEM MASTER
A2: Master list of every raw ingredient — standard cost feeds every recipe
A3: ITEM CODE | B3: ITEM NAME | C3: CATEGORY | D3: UOM | E3: STANDARD COST (ETB)
A4: FOOD
A5: FD001 | B5: Beef Mince (80% Lean) | C5: Meat & Poultry | D5: Kg | E5: 550
A6: FD002 | B6: Chicken Breast (Boneless) | C6: Meat & Poultry | D6: Kg | E6: 480
A7: FD003 | B7: Bacon Strips | C7: Meat & Poultry | D7: Kg | E7: 650
A8: FD004 | B8: Fresh Lettuce | C8: Fresh Produce | D8: Kg | E8: 60
A9: FD005 | B9: Fresh Tomato | C9: Fresh Produce | D9: Kg | E9: 55
A10: FD006 | B10: Onion | C10: Fresh Produce | D10: Kg | E10: 40
A11: FD007 | B11: Cheddar Cheese Slice | C11: Dairy | D11: Pcs | E11: 12
A12: FD008 | B12: All-Purpose Flour | C12: Bakery & Dry Goods | D12: Kg | E12: 55
A13: FD009 | B13: Butter (Unsalted) | C13: Dairy | D13: Kg | E13: 480
A14: FD010 | B14: Fresh Eggs | C14: Dairy | D14: Pcs | E14: 8
A15: FD011 | B15: Spaghetti Pasta | C15: Bakery & Dry Goods | D15: Kg | E15: 120
A16: FD012 | B16: Tortilla Wrap | C16: Bakery & Dry Goods | D16: Pcs | E16: 15
... A19: FD015 | B19: Mozzarella Cheese | C19: Dairy | D19: Kg | E19: 620
A20: BEVERAGE
A21: BV001 | B21: Coffee Beans (Roasted) | C21: Coffee & Tea | D21: Kg | E21: 900
A22: BV002 | B22: Black Tea Bags | C22: Coffee & Tea | D22: Pcs | E22: 3
A23: BV003 | B23: Green Tea Bags | C23: Coffee & Tea | D23: Pcs | E23: 4
A24: BV004 | B24: Fresh Milk | C24: Dairy & Bar | D24: Ltr | E24: 65
A25: BV005 | B25: Cocoa Powder | C25: Coffee & Tea | D25: Kg | E25: 350
A26: BV006 | B26: White Rum | C26: Bar & Spirits | D26: Ltr | E26: 950
A27: BV007 | B27: Fresh Mint Leaves | C27: Bar Garnish | D27: Kg | E27: 150
A28: BV008 | B28: Fresh Lime | C28: Bar Garnish | D28: Kg | E28: 100
A29: BV009 | B29: Fresh Avocado | C29: Fresh Produce | D29: Kg | E29: 90
A30: BV010 | B30: Soda Water | C30: Bar & Mixers | D30: Ltr | E30: 45
A31: BV011 | B31: Coca-Cola (330ml Bottle) | C31: Soft Drinks | D31: Bottle | E31: 35
A32: OTHERS
A33: OT001 | B33: Burger Takeaway Box | C33: Packaging | D33: Pcs | E33: 8
A34: OT002 | B34: Pizza Takeaway Box | C34: Packaging | D34: Pcs | E34: 15
A35: OT003 | B35: Paper Napkins | C35: Consumables | D35: Pcs | E35: 1
A36: OT004 | B36: Disposable Straws | C36: Consumables | D36: Pcs | E36: 1
A37: OT005 | B37: White Sugar | C37: Pantry & Dry Goods | D37: Kg | E37: 60
A38: OT006 | B38: Iodized Salt | C38: Pantry & Dry Goods | D38: Kg | E38: 25
A39: OT007 | B39: Cooking / Vegetable Oil | C39: Pantry & Dry Goods | D39: Ltr | E39: 150
A40: OT008 | B40: Instant Dry Yeast | C40: Pantry & Dry Goods | D40: Kg | E40: 400
A41: OT009 | B41: Black Pepper (Ground) | C41: Pantry & Dry Goods | D41: Kg | E41: 500

Sheet Menu Master
A1: MENU MASTER
A2: Every sellable menu item — the basis of Recipe Master & Daily Sales
A3: MENU CODE | B3: MENU ITEM | C3: CATEGORY | D3: SUB-CATEGORY | E3: UOM | F3: STATUS
A4: A. Food Menu
A5: Burgers
A6: FM001 | B6: Classic Beef Burger | C6: Food | D6: Burger | E6: Plate | F6: Active
A7: FM002 | B7: Double Beef Burger | C7: Food | D7: Burger | E7: Plate | F7: Active
A8: Wraps
A9: FM003 | B9: Chicken Caesar Wrap | C9: Food | D9: Wrap | E9: Plate | F9: Active
A10: FM004 | B10: Crispy Chicken Wrap | C10: Food | D10: Wrap | E10: Plate | F10: Active
A11: Sandwiches
A12: FM005 | B12: Club Sandwich | C12: Food | D12: Sandwich | E12: Plate | F12: Active
A13: FM006 | B13: Chicken Sandwich | C13: Food | D13: Sandwich | E13: Plate | F13: Active
A14: Pasta
A15: FM007 | B15: Spaghetti Bolognese | C15: Food | D15: Pasta | E15: Plate | F15: Active
A16: FM008 | B16: Spaghetti Alfredo | C16: Food | D16: Pasta | E16: Plate | F16: Active
A17: Breakfast
A18: FM009 | B18: American Breakfast | C18: Food | D18: Breakfast | E18: Plate | F18: Active
A19: FM010 | B19: Continental Breakfast | C19: Food | D19: Breakfast | E19: Plate | F19: Active
A20: Bakery & Pastries
A21: FM011 | B21: Butter Croissant | C21: Food | D21: Bakery & Pastries | E21: Plate | F21: Active
A22: FM012 | B22: Danish Pastry | C22: Food | D22: Bakery & Pastries | E22: Plate | F22: Active
A23: Salads
A24: FM013 | B24: Chicken Caesar Salad | C24: Food | D24: Salad | E24: Plate | F24: Active
A25: FM014 | B25: Avocado Salad | C25: Food | D25: Salad | E25: Plate | F25: Active
A26: Pizza
A27: FM015 | B27: Margherita Pizza | C27: Food | D27: Pizza | E27: Plate | F27: Active
A28: B. Beverage Menu
A29: Coffee
A30: BM001 | B30: Americano | C30: Beverage | D30: Coffee | E30: Cup | F30: Active
A31: BM002 | B31: Cappuccino | C31: Beverage | D31: Coffee | E31: Cup | F31: Active
A32: Tea
A33: BM003 | B33: English Breakfast Tea | C33: Beverage | D33: Tea | E33: Cup | F33: Active
A34: BM004 | B34: Green Tea | C34: Beverage | D34: Tea | E34: Cup | F34: Active
A35: Hot Drinks
A36: BM005 | B36: Hot Chocolate | C36: Beverage | D36: Hot Drink | E36: Cup | F36: Active
A37: Mojitos
A38: BM006 | B38: Classic Mojito | C38: Beverage | D38: Mojito | E38: Glass | F38: Active
A39: BM007 | B39: Strawberry Mojito | C39: Beverage | D39: Mojito | E39: Glass | F39: Active
A40: Fresh Juices
A41: BM008 | B41: Fresh Avocado Juice | C41: Beverage | D41: Juice | E41: Glass | F41: Active
A42: Soft Drinks & Water
A43: BM009 | B43: Coca-Cola | C43: Beverage | D43: Soft Drinks | E43: Bottle | F43: Active
A44: C. Other Menu Items (To-Go Materials)
A45: OM001 | B45: Burger Takeaway Box | C45: To-Go Material | D45: Packaging | E45: Each | F45: Active
A46: OM002 | B46: Pizza Takeaway Box | C46: To-Go Material | D46: Packaging | E46: Each | F46: Active
A48: Summary
A49: Category | B49: Number of Items
A50: Food Menu | B50: =COUNTIF(C4:C48,"Food") -> 15
A51: Beverage Menu | B51: =COUNTIF(C4:C48,"Beverage") -> 9
A52: Other (To-Go Materials) | B52: =COUNTIF(C4:C48,"To-Go Material") -> 2
A53: Total Menu Items | B53: =SUM(B50:B52) -> 26

Sheet Recipe Master
A1: RECIPE MASTER
A2: Ingredient breakdown & standard cost for every menu item — theoretical food cost engine
A3: RECIPE CODE | B3: MENU CODE | C3: MENU ITEM | D3: ITEM CODE | E3: INGREDIENT | F3: UOM | G3: QTY | H3: ITEM COST (ETB) | I3: MONTHLY QTY SOLD (link) | J3: THEORETICAL QTY THIS LINE
A4: RC-FM001 | B4: FM001 | C4: Classic Beef Burger | D4: FD001 | E4: Beef Mince (80% Lean) | F4: Kg | G4: 0.15 | H4: =G4*IFERROR(INDEX('Item Master'!$E$4:$E$41,MATCH(D4,'Item Master'!$A$4:$A$41,0)),INDEX('Sub-Recipe'!$K$4:$K$200,MATCH(D4,'Sub-Recipe'!$A$4:$A$200,0))) -> 82.5 | I4: =IFERROR(INDEX('Daily Sales'!$AK$5:$AK$30,MATCH($B4,'Daily Sales'!$A$5:$A$30,0)),0) -> 91 | J4: =G4*I4 -> 13.65
A5: RC-FM001 | B5: FM001 | C5: Classic Beef Burger | D5: SR001 | E5: TOTAL - Burger Bun (Homemade) (Sub-Recipe) | F5: Pcs | G5: 1 | H5: =G5*IFERROR(INDEX('Item Master'!$E$4:$E$41,MATCH(D5,'Item Master'!$A$4:$A$41,0)),INDEX('Sub-Recipe'!$K$4:$K$200,MATCH(D5,'Sub-Recipe'!$A$4:$A$200,0))) -> 0 | I5: =IFERROR(INDEX('Daily Sales'!$AK$5:$AK$30,MATCH($B5,'Daily Sales'!$A$5:$A$30,0)),0) -> 91 | J5: =G5*I5 -> 91
A6: RC-FM001 | B6: FM001 | C6: Classic Beef Burger | D6: FD004 | E6: Fresh Lettuce | F6: Kg | G6: 0.02 | H6: =G6*IFERROR(INDEX('Item Master'!$E$4:$E$41,MATCH(D6,'Item Master'!$A$4:$A$41,0)),INDEX('Sub-Recipe'!$K$4:$K$200,MATCH(D6,'Sub-Recipe'!$A$4:$A$200,0))) -> 1.2 | I6: =IFERROR(INDEX('Daily Sales'!$AK$5:$AK$30,MATCH($B6,'Daily Sales'!$A$5:$A$30,0)),0) -> 91 | J6: =G6*I6 -> 1.82
A7: RC-FM001 | B7: FM001 | C7: Classic Beef Burger | D7: FD005 | E7: Fresh Tomato | F7: Kg | G7: 0.03 | H7: =G7*IFERROR(INDEX('Item Master'!$E$4:$E$41,MATCH(D7,'Item Master'!$A$4:$A$41,0)),INDEX('Sub-Recipe'!$K$4:$K$200,MATCH(D7,'Sub-Recipe'!$A$4:$A$200,0))) -> 1.65 | I7: =IFERROR(INDEX('Daily Sales'!$AK$5:$AK$30,MATCH($B7,'Daily Sales'!$A$5:$A$30,0)),0) -> 91 | J7: =G7*I7 -> 2.73
A8: RC-FM001 | B8: FM001 | C8: Classic Beef Burger | D8: FD006 | E8: Onion | F8: Kg | G8: 0.02 | H8: =G8*IFERROR(INDEX('Item Master'!$E$4:$E$41,MATCH(D8,'Item Master'!$A$4:$A$41,0)),INDEX('Sub-Recipe'!$K$4:$K$200,MATCH(D8,'Sub-Recipe'!$A$4:$A$200,0))) -> 0.8 | I8: =IFERROR(INDEX('Daily Sales'!$AK$5:$AK$30,MATCH($B8,'Daily Sales'!$A$5:$A$30,0)),0) -> 91 | J8: =G8*I8 -> 1.82
A9: RC-FM001 | B9: FM001 | C9: Classic Beef Burger | D9: FD007 | E9: Cheddar Cheese Slice | F9: Pcs | G9: 1 | H9: =G9*IFERROR(INDEX('Item Master'!$E$4:$E$41,MATCH(D9,'Item Master'!$A$4:$A$41,0)),INDEX('Sub-Recipe'!$K$4:$K$200,MATCH(D9,'Sub-Recipe'!$A$4:$A$200,0))) -> 12 | I9: =IFERROR(INDEX('Daily Sales'!$AK$5:$AK$30,MATCH($B9,'Daily Sales'!$A$5:$A$30,0)),0) -> 91 | J9: =G9*I9 -> 91
A10: RC-FM001 | B10: FM001 | C10: Classic Beef Burger | D10: FD013 | E10: Mayonnaise | F10: Kg | G10: 0.02 | H10: =G10*IFERROR(INDEX('Item Master'!$E$4:$E$41,MATCH(D10,'Item Master'!$A$4:$A$41,0)),INDEX('Sub-Recipe'!$K$4:$K$200,MATCH(D10,'Sub-Recipe'!$A$4:$A$200,0))) -> 4.4 | I10: =IFERROR(INDEX('Daily Sales'!$AK$5:$AK$30,MATCH($B10,'Daily Sales'!$A$5:$A$30,0)),0) -> 91 | J10: =G10*I10 -> 1.82
A11: RC-FM001 | B11: FM001 | C11: Classic Beef Burger | D11: FD014 | E11: Tomato Ketchup | F11: Kg | G11: 0.02 | H11: =G11*IFERROR(INDEX('Item Master'!$E$4:$E$41,MATCH(D11,'Item Master'!$A$4:$A$41,0)),INDEX('Sub-Recipe'!$K$4:$K$200,MATCH(D11,'Sub-Recipe'!$A$4:$A$200,0))) -> 3.6 | I11: =IFERROR(INDEX('Daily Sales'!$AK$5:$AK$30,MATCH($B11,'Daily Sales'!$A$5:$A$30,0)),0) -> 91 | J11: =G11*I11 -> 1.82
A12: RC-FM001 | B12: FM001 | C12: TOTAL STANDARD RECIPE COST - Classic Beef Burger | D12: TOTAL | H12: =SUM(H4:H11) -> 106.15
A14: RC-FM002 | B14: FM002 | C14: Double Beef Burger | D14: FD001 | E14: Beef Mince (80% Lean) | F14: Kg | G14: 0.3 | H14: =G14*IFERROR(INDEX('Item Master'!$E$4:$E$41,MATCH(D14,'Item Master'!$A$4:$A$41,0)),INDEX('Sub-Recipe'!$K$4:$K$200,MATCH(D14,'Sub-Recipe'!$A$4:$A$200,0))) -> 165 | I14: =IFERROR(INDEX('Daily Sales'!$AK$5:$AK$30,MATCH($B14,'Daily Sales'!$A$5:$A$30,0)),0) -> 41 | J14: =G14*I14 -> 12.3
A15: RC-FM002 | B15: FM002 | C15: Double Beef Burger | D15: SR001 | E15: TOTAL - Burger Bun (Homemade) (Sub-Recipe) | F15: Pcs | G15: 1 | H15: =G15*IFERROR(INDEX('Item Master'!$E$4:$E$41,MATCH(D15,'Item Master'!$A$4:$A$41,0)),INDEX('Sub-Recipe'!$K$4:$K$200,MATCH(D15,'Sub-Recipe'!$A$4:$A$200,0))) -> 0 | I15: =IFERROR(INDEX('Daily Sales'!$AK$5:$AK$30,MATCH($B15,'Daily Sales'!$A$5:$A$30,0)),0) -> 41 | J15: =G15*I15 -> 41
A16: RC-FM002 | B16: FM002 | C16: Double Beef Burger | D16: FD004 | E16: Fresh Lettuce | F16: Kg | G16: 0.02 | H16: =G16*IFERROR(INDEX('Item Master'!$E$4:$E$41,MATCH(D16,'Item Master'!$A$4:$A$41,0)),INDEX('Sub-Recipe'!$K$4:$K$200,MATCH(D16,'Sub-Recipe'!$A$4:$A$200,0))) -> 1.2 | I16: =IFERROR(INDEX('Daily Sales'!$AK$5:$AK$30,MATCH($B16,'Daily Sales'!$A$5:$A$30,0)),0) -> 41 | J16: =G16*I16 -> 0.82
A17: RC-FM002 | B17: FM002 | C17: Double Beef Burger | D17: FD005 | E17: Fresh Tomato | F17: Kg | G17: 0.03 | H17: =G17*IFERROR(INDEX('Item Master'!$E$4:$E$41,MATCH(D17,'Item Master'!$A$4:$A$41,0)),INDEX('Sub-Recipe'!$K$4:$K$200,MATCH(D17,'Sub-Recipe'!$A$4:$A$200,0))) -> 1.65 | I17: =IFERROR(INDEX('Daily Sales'!$AK$5:$AK$30,MATCH($B17,'Daily Sales'!$A$5:$A$30,0)),0) -> 41 | J17: =G17*I17 -> 1.23
A18: RC-FM002 | B18: FM002 | C18: Double Beef Burger | D18: FD006 | E18: Onion | F18: Kg | G18: 0.02 | H18: =G18*IFERROR(INDEX('Item Master'!$E$4:$E$41,MATCH(D18,'Item Master'!$A$4:$A$41,0)),INDEX('Sub-Recipe'!$K$4:$K$200,MATCH(D18,'Sub-Recipe'!$A$4:$A$200,0))) -> 0.8 | I18: =IFERROR(INDEX('Daily Sales'!$AK$5:$AK$30,MATCH($B18,'Daily Sales'!$A$5:$A$30,0)),0) -> 41 | J18: =G18*I18 -> 0.82
A19: RC-FM002 | B19: FM002 | C19: Double Beef Burger | D19: FD007 | E19: Cheddar Cheese Slice | F19: Pcs | G19: 2 | H19: =G19*IFERROR(INDEX('Item Master'!$E$4:$E$41,MATCH(D19,'Item Master'!$A$4:$A$41,0)),INDEX('Sub-Recipe'!$K$4:$K$200,MATCH(D19,'Sub-Recipe'!$A$4:$A$200,0))) -> 24 | I19: =IFERROR(INDEX('Daily Sales'!$AK$5:$AK$30,MATCH($B19,'Daily Sales'!$A$5:$A$30,0)),0) -> 41 | J19: =G19*I19 -> 82
A20: RC-FM002 | B20: FM002 | C20: Double Beef Burger | D20: FD013 | E20: Mayonnaise | F20: Kg | G20: 0.02 | H20: =G20*IFERROR(INDEX('Item Master'!$E$4:$E$41,MATCH(D20,'Item Master'!$A$4:$A$41,0)),INDEX('Sub-Recipe'!$K$4:$K$200,MATCH(D20,'Sub-Recipe'!$A$4:$A$200,0))) -> 4.4 | I20: =IFERROR(INDEX('Daily Sales'!$AK$5:$AK$30,MATCH($B20,'Daily Sales'!$A$5:$A$30,0)),0) -> 41 | J20: =G20*I20 -> 0.82
A21: RC-FM002 | B21: FM002 | C21: Double Beef Burger | D21: FD014 | E21: Tomato Ketchup | F21: Kg | G21: 0.02 | H21: =G21*IFERROR(INDEX('Item Master'!$E$4:$E$41,MATCH(D21,'Item Master'!$A$4:$A$41,0)),INDEX('Sub-Recipe'!$K$4:$K$200,MATCH(D21,'Sub-Recipe'!$A$4:$A$200,0))) -> 3.6 | I21: =IFERROR(INDEX('Daily Sales'!$AK$5:$AK$30,MATCH($B21,'Daily Sales'!$A$5:$A$30,0)),0) -> 41 | J21: =G21*I21 -> 0.82
A22: RC-FM002 | B22: FM002 | C22: TOTAL STANDARD RECIPE COST - Double Beef Burger | D22: TOTAL | H22: =SUM(H14:H21) -> 200.65
A24: RC-FM003 | B24: FM003 | C24: Chicken Caesar Wrap | D24: FD002 | E24: Chicken Breast (Boneless) | F24: Kg | G24: 0.15 | H24: =G24*IFERROR(INDEX('Item Master'!$E$4:$E$41,MATCH(D24,'Item Master'!$A$4:$A$41,0)),INDEX('Sub-Recipe'!$K$4:$K$200,MATCH(D24,'Sub-Recipe'!$A$4:$A$200,0))) -> 72 | I24: =IFERROR(INDEX('Daily Sales'!$AK$5:$AK$30,MATCH($B24,'Daily Sales'!$A$5:$A$30,0)),0) -> 51 | J24: =G24*I24 -> 7.65
A25: RC-FM003 | B25: FM003 | C25: Chicken Caesar Wrap | D25: FD012 | E25: Tortilla Wrap | F25: Pcs | G25: 1 | H25: =G25*IFERROR(INDEX('Item Master'!$E$4:$E$41,MATCH(D25,'Item Master'!$A$4:$A$41,0)),INDEX('Sub-Recipe'!$K$4:$K$200,MATCH(D25,'Sub-Recipe'!$A$4:$A$200,0))) -> 15 | I25: =IFERROR(INDEX('Daily Sales'!$AK$5:$AK$30,MATCH($B25,'Daily Sales'!$A$5:$A$30,0)),0) -> 51 | J25: =G25*I25 -> 51
A26: RC-FM003 | B26: FM003 | C26: Chicken Caesar Wrap | D26: FD004 | E26: Fresh Lettuce | F26: Kg | G26: 0.03 | H26: =G26*IFERROR(INDEX('Item Master'!$E$4:$E$41,MATCH(D26,'Item Master'!$A$4:$A$41,0)),INDEX('Sub-Recipe'!$K$4:$K$200,MATCH(D26,'Sub-Recipe'!$A$4:$A$200,0))) -> 1.8 | I26: =IFERROR(INDEX('Daily Sales'!$AK$5:$AK$30,MATCH($B26,'Daily Sales'!$A$5:$A$30,0)),0) -> 51 | J26: =G26*I26 -> 1.53
A27: RC-FM003 | B27: FM003 | C27: Chicken Caesar Wrap | D27: SR008 | E27: TOTAL - Caesar Dressing (Homemade) (Sub-Recipe) | F27: Portions (100g) | G27: 1 | H27: =G27*IFERROR(INDEX('Item Master'!$E$4:$E$41,MATCH(D27,'Item Master'!$A$4:$A$41,0)),INDEX('Sub-Recipe'!$K$4:$K$200,MATCH(D27,'Sub-Recipe'!$A$4:$A$200,0))) -> 0 | I27: =IFERROR(INDEX('Daily Sales'!$AK$5:$AK$30,MATCH($B27,'Daily Sales'!$A$5:$A$30,0)),0) -> 51 | J27: =G27*I27 -> 51
A28: RC-FM003 | B28: FM003 | C28: Chicken Caesar Wrap | D28: FD015 | E28: Mozzarella Cheese | F28: Kg | G28: 0.03 | H28: =G28*IFERROR(INDEX('Item Master'!$E$4:$E$41,MATCH(D28,'Item Master'!$A$4:$A$41,0)),INDEX('Sub-Recipe'!$K$4:$K$200,MATCH(D28,'Sub-Recipe'!$A$4:$A$200,0))) -> 18.6 | I28: =IFERROR(INDEX('Daily Sales'!$AK$5:$AK$30,MATCH($B28,'Daily Sales'!$A$5:$A$30,0)),0) -> 51 | J28: =G28*I28 -> 1.53
A29: RC-FM003 | B29: FM003 | C29: TOTAL STANDARD RECIPE COST - Chicken Caesar Wrap | D29: TOTAL | H29: =SUM(H24:H28) -> 107.4
A31: RC-FM004 | B31: FM004 | C31: Crispy Chicken Wrap | D31: FD002 | E31: Chicken Breast (Boneless) | F31: Kg | G31: 0.15 | H31: =G31*IFERROR(INDEX('Item Master'!$E$4:$E$41,MATCH(D31,'Item Master'!$A$4:$A$41,0)),INDEX('Sub-Recipe'!$K$4:$K$200,MATCH(D31,'Sub-Recipe'!$A$4:$A$200,0))) -> 72 | I31: =IFERROR(INDEX('Daily Sales'!$AK$5:$AK$30,MATCH($B31,'Daily Sales'!$A$5:$A$30,0)),0) -> 58 | J31: =G31*I31 -> 8.7
A32: RC-FM004 | B32: FM004 | C32: Crispy Chicken Wrap | D32: FD012 | E32: Tortilla Wrap | F32: Pcs | G32: 1 | H32: =G32*IFERROR(INDEX('Item Master'!$E$4:$E$41,MATCH(D32,'Item Master'!$A$4:$A$41,0)),INDEX('Sub-Recipe'!$K$4:$K$200,MATCH(D32,'Sub-Recipe'!$A$4:$A$200,0))) -> 15 | I32: =IFERROR(INDEX('Daily Sales'!$AK$5:$AK$30,MATCH($B32,'Daily Sales'!$A$5:$A$30,0)),0) -> 58 | J32: =G32*I32 -> 58
A33: RC-FM004 | B33: FM004 | C33: Crispy Chicken Wrap | D33: FD004 | E33: Fresh Lettuce | F33: Kg | G33: 0.03 | H33: =G33*IFERROR(INDEX('Item Master'!$E$4:$E$41,MATCH(D33,'Item Master'!$A$4:$A$41,0)),INDEX('Sub-Recipe'!$K$4:$K$200,MATCH(D33,'Sub-Recipe'!$A$4:$A$200,0))) -> 1.8 | I33: =IFERROR(INDEX('Daily Sales'!$AK$5:$AK$30,MATCH($B33,'Daily Sales'!$A$5:$A$30,0)),0) -> 58 | J33: =G33*I33 -> 1.74
A34: RC-FM004 | B34: FM004 | C34: Crispy Chicken Wrap | D34: FD013 | E34: Mayonnaise | F34: Kg | G34: 0.03 | H34: =G34*IFERROR(INDEX('Item Master'!$E$4:$E$41,MATCH(D34,'Item Master'!$A$4:$A$41,0)),INDEX('Sub-Recipe'!$K$4:$K$200,MATCH(D34,'Sub-Recipe'!$A$4:$A$200,0))) -> 6.6 | I34: =IFERROR(INDEX('Daily Sales'!$AK$5:$AK$30,MATCH($B34,'Daily Sales'!$A$5:$A$30,0)),0) -> 58 | J34: =G34*I34 -> 1.74
A35: RC-FM004 | B35: FM004 | C35: Crispy Chicken Wrap | D35: FD006 | E35: Onion | F35: Kg | G35: 0.02 | H35: =G35*IFERROR(INDEX('Item Master'!$E$4:$E$41,MATCH(D35,'Item Master'!$A$4:$A$41,0)),INDEX('Sub-Recipe'!$K$4:$K$200,MATCH(D35,'Sub-Recipe'!$A$4:$A$200,0))) -> 0.8 | I35: =IFERROR(INDEX('Daily Sales'!$AK$5:$AK$30,MATCH($B35,'Daily Sales'!$A$5:$A$30,0)),0) -> 58 | J35: =G35*I35 -> 1.16
A36: RC-FM004 | B36: FM004 | C36: Crispy Chicken Wrap | D36: OT007 | E36: Cooking / Vegetable Oil | F36: Ltr | G36: 0.05 | H36: =G36*IFERROR(INDEX('Item Master'!$E$4:$E$41,MATCH(D36,'Item Master'!$A$4:$A$41,0)),INDEX('Sub-Recipe'!$K$4:$K$200,MATCH(D36,'Sub-Recipe'!$A$4:$A$200,0))) -> 7.5 | I36: =IFERROR(INDEX('Daily Sales'!$AK$5:$AK$30,MATCH($B36,'Daily Sales'!$A$5:$A$30,0)),0) -> 58 | J36: =G36*I36 -> 2.9
A37: RC-FM004 | B37: FM004 | C37: TOTAL STANDARD RECIPE COST - Crispy Chicken Wrap | D37: TOTAL | H37: =SUM(H31:H36) -> 103.7
A39: RC-FM005 | B39: FM005 | C39: Club Sandwich | D39: SR002 | E39: TOTAL - Sandwich Bread Loaf (Homemade) (Sub-Recipe) | F39: Slices | G39: 3 | H39: =G39*IFERROR(INDEX('Item Master'!$E$4:$E$41,MATCH(D39,'Item Master'!$A$4:$A$41,0)),INDEX('Sub-Recipe'!$K$4:$K$200,MATCH(D39,'Sub-Recipe'!$A$4:$A$200,0))) -> 0 | I39: =IFERROR(INDEX('Daily Sales'!$AK$5:$AK$30,MATCH($B39,'Daily Sales'!$A$5:$A$30,0)),0) -> 50 | J39: =G39*I39 -> 150
A40: RC-FM005 | B40: FM005 | C40: Club Sandwich | D40: FD002 | E40: Chicken Breast (Boneless) | F40: Kg | G40: 0.1 | H40: =G40*IFERROR(INDEX('Item Master'!$E$4:$E$41,MATCH(D40,'Item Master'!$A$4:$A$41,0)),INDEX('Sub-Recipe'!$K$4:$K$200,MATCH(D40,'Sub-Recipe'!$A$4:$A$200,0))) -> 48 | I40: =IFERROR(INDEX('Daily Sales'!$AK$5:$AK$30,MATCH($B40,'Daily Sales'!$A$5:$A$30,0)),0) -> 50 | J40: =G40*I40 -> 5
A41: RC-FM005 | B41: FM005 | C41: Club Sandwich | D41: FD003 | E41: Bacon Strips | F41: Kg | G41: 0.05 | H41: =G41*IFERROR(INDEX('Item Master'!$E$4:$E$41,MATCH(D41,'Item Master'!$A$4:$A$41,0)),INDEX('Sub-Recipe'!$K$4:$K$200,MATCH(D41,'Sub-Recipe'!$A$4:$A$200,0))) -> 32.5 | I41: =IFERROR(INDEX('Daily Sales'!$AK$5:$AK$30,MATCH($B41,'Daily Sales'!$A$5:$A$30,0)),0) -> 50 | J41: =G41*I41 -> 2.5
A42: RC-FM005 | B42: FM005 | C42: Club Sandwich | D42: FD004 | E42: Fresh Lettuce | F42: Kg | G42: 0.02 | H42: =G42*IFERROR(INDEX('Item Master'!$E$4:$E$41,MATCH(D42,'Item Master'!$A$4:$A$41,0)),INDEX('Sub-Recipe'!$K$4:$K$200,MATCH(D42,'Sub-Recipe'!$A$4:$A$200,0))) -> 1.2 | I42: =IFERROR(INDEX('Daily Sales'!$AK$5:$AK$30,MATCH($B42,'Daily Sales'!$A$5:$A$30,0)),0) -> 50 | J42: =G42*I42 -> 1
A43: RC-FM005 | B43: FM005 | C43: Club Sandwich | D43: FD005 | E43: Fresh Tomato | F43: Kg | G43: 0.03 | H43: =G43*IFERROR(INDEX('Item Master'!$E$4:$E$41,MATCH(D43,'Item Master'!$A$4:$A$41,0)),INDEX('Sub-Recipe'!$K$4:$K$200,MATCH(D43,'Sub-Recipe'!$A$4:$A$200,0))) -> 1.65 | I43: =IFERROR(INDEX('Daily Sales'!$AK$5:$AK$30,MATCH($B43,'Daily Sales'!$A$5:$A$30,0)),0) -> 50 | J43: =G43*I43 -> 1.5
A44: RC-FM005 | B44: FM005 | C44: Club Sandwich | D44: FD007 | E44: Cheddar Cheese Slice | F44: Pcs | G44: 1 | H44: =G44*IFERROR(INDEX('Item Master'!$E$4:$E$41,MATCH(D44,'Item Master'!$A$4:$A$41,0)),INDEX('Sub-Recipe'!$K$4:$K$200,MATCH(D44,'Sub-Recipe'!$A$4:$A$200,0))) -> 12 | I44: =IFERROR(INDEX('Daily Sales'!$AK$5:$AK$30,MATCH($B44,'Daily Sales'!$A$5:$A$30,0)),0) -> 50 | J44: =G44*I44 -> 50
A45: RC-FM005 | B45: FM005 | C45: Club Sandwich | D45: FD013 | E45: Mayonnaise | F45: Kg | G45: 0.02 | H45: =G45*IFERROR(INDEX('Item Master'!$E$4:$E$41,MATCH(D45,'Item Master'!$A$4:$A$41,0)),INDEX('Sub-Recipe'!$K$4:$K$200,MATCH(D45,'Sub-Recipe'!$A$4:$A$200,0))) -> 4.4 | I45: =IFERROR(INDEX('Daily Sales'!$AK$5:$AK$30,MATCH($B45,'Daily Sales'!$A$5:$A$30,0)),0) -> 50 | J45: =G45*I45 -> 1
A46: RC-FM005 | B46: FM005 | C46: TOTAL STANDARD RECIPE COST - Club Sandwich | D46: TOTAL | H46: =SUM(H39:H45) -> 99.75
A48: RC-FM006 | B48: FM006 | C48: Chicken Sandwich | D48: SR002 | E48: TOTAL - Sandwich Bread Loaf (Homemade) (Sub-Recipe) | F48: Slices | G48: 2 | H48: =G48*IFERROR(INDEX('Item Master'!$E$4:$E$41,MATCH(D48,'Item Master'!$A$4:$A$41,0)),INDEX('Sub-Recipe'!$K$4:$K$200,MATCH(D48,'Sub-Recipe'!$A$4:$A$200,0))) -> 0 | I48: =IFERROR(INDEX('Daily Sales'!$AK$5:$AK$30,MATCH($B48,'Daily Sales'!$A$5:$A$30,0)),0) -> 51 | J48: =G48*I48 -> 102
A49: RC-FM006 | B49: FM006 | C49: Chicken Sandwich | D49: FD002 | E49: Chicken Breast (Boneless) | F49: Kg | G49: 0.12 | H49: =G49*IFERROR(INDEX('Item Master'!$E$4:$E$41,MATCH(D49,'Item Master'!$A$4:$A$41,0)),INDEX('Sub-Recipe'!$K$4:$K$200,MATCH(D49,'Sub-Recipe'!$A$4:$A$200,0))) -> 57.6 | I49: =IFERROR(INDEX('Daily Sales'!$AK$5:$AK$30,MATCH($B49,'Daily Sales'!$A$5:$A$30,0)),0) -> 51 | J49: =G49*I49 -> 6.12
A50: RC-FM006 | B50: FM006 | C50: Chicken Sandwich | D50: FD004 | E50: Fresh Lettuce | F50: Kg | G50: 0.02 | H50: =G50*IFERROR(INDEX('Item Master'!$E$4:$E$41,MATCH(D50,'Item Master'!$A$4:$A$41,0)),INDEX('Sub-Recipe'!$K$4:$K$200,MATCH(D50,'Sub-Recipe'!$A$4:$A$200,0))) -> 1.2 | I50: =IFERROR(INDEX('Daily Sales'!$AK$5:$AK$30,MATCH($B50,'Daily Sales'!$A$5:$A$30,0)),0) -> 51 | J50: =G50*I50 -> 1.02
A51: RC-FM006 | B51: FM006 | C51: Chicken Sandwich | D51: FD005 | E51: Fresh Tomato | F51: Kg | G51: 0.02 | H51: =G51*IFERROR(INDEX('Item Master'!$E$4:$E$41,MATCH(D51,'Item Master'!$A$4:$A$41,0)),INDEX('Sub-Recipe'!$K$4:$K$200,MATCH(D51,'Sub-Recipe'!$A$4:$A$200,0))) -> 1.1 | I51: =IFERROR(INDEX('Daily Sales'!$AK$5:$AK$30,MATCH($B51,'Daily Sales'!$A$5:$A$30,0)),0) -> 51 | J51: =G51*I51 -> 1.02
A52: RC-FM006 | B52: FM006 | C52: Chicken Sandwich | D52: FD013 | E52: Mayonnaise | F52: Kg | G52: 0.02 | H52: =G52*IFERROR(INDEX('Item Master'!$E$4:$E$41,MATCH(D52,'Item Master'!$A$4:$A$41,0)),INDEX('Sub-Recipe'!$K$4:$K$200,MATCH(D52,'Sub-Recipe'!$A$4:$A$200,0))) -> 4.4 | I52: =IFERROR(INDEX('Daily Sales'!$AK$5:$AK$30,MATCH($B52,'Daily Sales'!$A$5:$A$30,0)),0) -> 51 | J52: =G52*I52 -> 1.02
A53: RC-FM006 | B53: FM006 | C53: TOTAL STANDARD RECIPE COST - Chicken Sandwich | D53: TOTAL | H53: =SUM(H48:H52) -> 64.3
A55: RC-FM007 | B55: FM007 | C55: Spaghetti Bolognese | D55: FD011 | E55: Spaghetti Pasta | F55: Kg | G55: 0.2 | H55: =G55*IFERROR(INDEX('Item Master'!$E$4:$E$41,MATCH(D55,'Item Master'!$A$4:$A$41,0)),INDEX('Sub-Recipe'!$K$4:$K$200,MATCH(D55,'Sub-Recipe'!$A$4:$A$200,0))) -> 24 | I55: =IFERROR(INDEX('Daily Sales'!$AK$5:$AK$30,MATCH($B55,'Daily Sales'!$A$5:$A$30,0)),0) -> 66 | J55: =G55*I55 -> 13.2
A56: RC-FM007 | B56: FM007 | C56: Spaghetti Bolognese | D56: SR006 | E56: TOTAL - Bolognese Sauce (Homemade) (Sub-Recipe) | F56: Portions (250g) | G56: 1 | H56: =G56*IFERROR(INDEX('Item Master'!$E$4:$E$41,MATCH(D56,'Item Master'!$A$4:$A$41,0)),INDEX('Sub-Recipe'!$K$4:$K$200,MATCH(D56,'Sub-Recipe'!$A$4:$A$200,0))) -> 0 | I56: =IFERROR(INDEX('Daily Sales'!$AK$5:$AK$30,MATCH($B56,'Daily Sales'!$A$5:$A$30,0)),0) -> 66 | J56: =G56*I56 -> 66
A57: RC-FM007 | B57: FM007 | C57: Spaghetti Bolognese | D57: FD015 | E57: Mozzarella Cheese | F57: Kg | G57: 0.02 | H57: =G57*IFERROR(INDEX('Item Master'!$E$4:$E$41,MATCH(D57,'Item Master'!$A$4:$A$41,0)),INDEX('Sub-Recipe'!$K$4:$K$200,MATCH(D57,'Sub-Recipe'!$A$4:$A$200,0))) -> 12.4 | I57: =IFERROR(INDEX('Daily Sales'!$AK$5:$AK$30,MATCH($B57,'Daily Sales'!$A$5:$A$30,0)),0) -> 66 | J57: =G57*I57 -> 1.32
A58: RC-FM007 | B58: FM007 | C58: TOTAL STANDARD RECIPE COST - Spaghetti Bolognese | D58: TOTAL | H58: =SUM(H55:H57) -> 36.4
A60: RC-FM008 | B60: FM008 | C60: Spaghetti Alfredo | D60: FD011 | E60: Spaghetti Pasta | F60: Kg | G60: 0.2 | H60: =G60*IFERROR(INDEX('Item Master'!$E$4:$E$41,MATCH(D60,'Item Master'!$A$4:$A$41,0)),INDEX('Sub-Recipe'!$K$4:$K$200,MATCH(D60,'Sub-Recipe'!$A$4:$A$200,0))) -> 24 | I60: =IFERROR(INDEX('Daily Sales'!$AK$5:$AK$30,MATCH($B60,'Daily Sales'!$A$5:$A$30,0)),0) -> 48 | J60: =G60*I60 -> 9.6
A61: RC-FM008 | B61: FM008 | C61: Spaghetti Alfredo | D61: SR007 | E61: TOTAL - Alfredo Sauce (Homemade) (Sub-Recipe) | F61: Portions (125g) | G61: 1 | H61: =G61*IFERROR(INDEX('Item Master'!$E$4:$E$41,MATCH(D61,'Item Master'!$A$4:$A$41,0)),INDEX('Sub-Recipe'!$K$4:$K$200,MATCH(D61,'Sub-Recipe'!$A$4:$A$200,0))) -> 0 | I61: =IFERROR(INDEX('Daily Sales'!$AK$5:$AK$30,MATCH($B61,'Daily Sales'!$A$5:$A$30,0)),0) -> 48 | J61: =G61*I61 -> 48
A62: RC-FM008 | B62: FM008 | C62: Spaghetti Alfredo | D62: FD002 | E62: Chicken Breast (Boneless) | F62: Kg | G62: 0.08 | H62: =G62*IFERROR(INDEX('Item Master'!$E$4:$E$41,MATCH(D62,'Item Master'!$A$4:$A$41,0)),INDEX('Sub-Recipe'!$K$4:$K$200,MATCH(D62,'Sub-Recipe'!$A$4:$A$200,0))) -> 38.4 | I62: =IFERROR(INDEX('Daily Sales'!$AK$5:$AK$30,MATCH($B62,'Daily Sales'!$A$5:$A$30,0)),0) -> 48 | J62: =G62*I62 -> 3.84
A63: RC-FM008 | B63: FM008 | C63: TOTAL STANDARD RECIPE COST - Spaghetti Alfredo | D63: TOTAL | H63: =SUM(H60:H62) -> 62.4
A65: RC-FM009 | B65: FM009 | C65: American Breakfast | D65: FD010 | E65: Fresh Eggs | F65: Pcs | G65: 2 | H65: =G65*IFERROR(INDEX('Item Master'!$E$4:$E$41,MATCH(D65,'Item Master'!$A$4:$A$41,0)),INDEX('Sub-Recipe'!$K$4:$K$200,MATCH(D65,'Sub-Recipe'!$A$4:$A$200,0))) -> 16 | I65: =IFERROR(INDEX('Daily Sales'!$AK$5:$AK$30,MATCH($B65,'Daily Sales'!$A$5:$A$30,0)),0) -> 38 | J65: =G65*I65 -> 76
A66: RC-FM009 | B66: FM009 | C66: American Breakfast | D66: FD003 | E66: Bacon Strips | F66: Kg | G66: 0.08 | H66: =G66*IFERROR(INDEX('Item Master'!$E$4:$E$41,MATCH(D66,'Item Master'!$A$4:$A$41,0)),INDEX('Sub-Recipe'!$K$4:$K$200,MATCH(D66,'Sub-Recipe'!$A$4:$A$200,0))) -> 52 | I66: =IFERROR(INDEX('Daily Sales'!$AK$5:$AK$30,MATCH($B66,'Daily Sales'!$A$5:$A$30,0)),0) -> 38 | J66: =G66*I66 -> 3.04
A67: RC-FM009 | B67: FM009 | C67: American Breakfast | D67: SR002 | E67: TOTAL - Sandwich Bread Loaf (Homemade) (Sub-Recipe) | F67: Slices | G67: 2 | H67: =G67*IFERROR(INDEX('Item Master'!$E$4:$E$41,MATCH(D67,'Item Master'!$A$4:$A$41,0)),INDEX('Sub-Recipe'!$K$4:$K$200,MATCH(D67,'Sub-Recipe'!$A$4:$A$200,0))) -> 0 | I67: =IFERROR(INDEX('Daily Sales'!$AK$5:$AK$30,MATCH($B67,'Daily Sales'!$A$5:$A$30,0)),0) -> 38 | J67: =G67*I67 -> 76
A68: RC-FM009 | B68: FM009 | C68: American Breakfast | D68: FD009 | E68: Butter (Unsalted) | F68: Kg | G68: 0.01 | H68: =G68*IFERROR(INDEX('Item Master'!$E$4:$E$41,MATCH(D68,'Item Master'!$A$4:$A$41,0)),INDEX('Sub-Recipe'!$K$4:$K$200,MATCH(D68,'Sub-Recipe'!$A$4:$A$200,0))) -> 4.8 | I68: =IFERROR(INDEX('Daily Sales'!$AK$5:$AK$30,MATCH($B68,'Daily Sales'!$A$5:$A$30,0)),0) -> 38 | J68: =G68*I68 -> 0.38
A69: RC-FM009 | B69: FM009 | C69: American Breakfast | D69: FD014 | E69: Tomato Ketchup | F69: Kg | G69: 0.01 | H69: =G69*IFERROR(INDEX('Item Master'!$E$4:$E$41,MATCH(D69,'Item Master'!$A$4:$A$41,0)),INDEX('Sub-Recipe'!$K$4:$K$200,MATCH(D69,'Sub-Recipe'!$A$4:$A$200,0))) -> 1.8 | I69: =IFERROR(INDEX('Daily Sales'!$AK$5:$AK$30,MATCH($B69,'Daily Sales'!$A$5:$A$30,0)),0) -> 38 | J69: =G69*I69 -> 0.38
A70: RC-FM009 | B70: FM009 | C70: TOTAL STANDARD RECIPE COST - American Breakfast | D70: TOTAL | H70: =SUM(H65:H69) -> 74.6
A72: RC-FM010 | B72: FM010 | C72: Continental Breakfast | D72: SR003 | E72: TOTAL - Croissant Dough (Homemade) (Sub-Recipe) | F72: Pcs | G72: 1 | H72: =G72*IFERROR(INDEX('Item Master'!$E$4:$E$41,MATCH(D72,'Item Master'!$A$4:$A$41,0)),INDEX('Sub-Recipe'!$K$4:$K$200,MATCH(D72,'Sub-Recipe'!$A$4:$A$200,0))) -> 0 | I72: =IFERROR(INDEX('Daily Sales'!$AK$5:$AK$30,MATCH($B72,'Daily Sales'!$A$5:$A$30,0)),0) -> 27 | J72: =G72*I72 -> 27
A73: RC-FM010 | B73: FM010 | C73: Continental Breakfast | D73: SR004 | E73: TOTAL - Danish Pastry Dough (Homemade) (Sub-Recipe) | F73: Pcs | G73: 1 | H73: =G73*IFERROR(INDEX('Item Master'!$E$4:$E$41,MATCH(D73,'Item Master'!$A$4:$A$41,0)),INDEX('Sub-Recipe'!$K$4:$K$200,MATCH(D73,'Sub-Recipe'!$A$4:$A$200,0))) -> 0 | I73: =IFERROR(INDEX('Daily Sales'!$AK$5:$AK$30,MATCH($B73,'Daily Sales'!$A$5:$A$30,0)),0) -> 27 | J73: =G73*I73 -> 27
A74: RC-FM010 | B74: FM010 | C74: Continental Breakfast | D74: FD009 | E74: Butter (Unsalted) | F74: Kg | G74: 0.01 | H74: =G74*IFERROR(INDEX('Item Master'!$E$4:$E$41,MATCH(D74,'Item Master'!$A$4:$A$41,0)),INDEX('Sub-Recipe'!$K$4:$K$200,MATCH(D74,'Sub-Recipe'!$A$4:$A$200,0))) -> 4.8 | I74: =IFERROR(INDEX('Daily Sales'!$AK$5:$AK$30,MATCH($B74,'Daily Sales'!$A$5:$A$30,0)),0) -> 27 | J74: =G74*I74 -> 0.27
A75: RC-FM010 | B75: FM010 | C75: Continental Breakfast | D75: FD007 | E75: Cheddar Cheese Slice | F75: Pcs | G75: 1 | H75: =G75*IFERROR(INDEX('Item Master'!$E$4:$E$41,MATCH(D75,'Item Master'!$A$4:$A$41,0)),INDEX('Sub-Recipe'!$K$4:$K$200,MATCH(D75,'Sub-Recipe'!$A$4:$A$200,0))) -> 12 | I75: =IFERROR(INDEX('Daily Sales'!$AK$5:$AK$30,MATCH($B75,'Daily Sales'!$A$5:$A$30,0)),0) -> 27 | J75: =G75*I75 -> 27
A76: RC-FM010 | B76: FM010 | C76: TOTAL STANDARD RECIPE COST - Continental Breakfast | D76: TOTAL | H76: =SUM(H72:H75) -> 16.8
A78: RC-FM011 | B78: FM011 | C78: Butter Croissant | D78: SR003 | E78: TOTAL - Croissant Dough (Homemade) (Sub-Recipe) | F78: Pcs | G78: 1 | H78: =G78*IFERROR(INDEX('Item Master'!$E$4:$E$41,MATCH(D78,'Item Master'!$A$4:$A$41,0)),INDEX('Sub-Recipe'!$K$4:$K$200,MATCH(D78,'Sub-Recipe'!$A$4:$A$200,0))) -> 0 | I78: =IFERROR(INDEX('Daily Sales'!$AK$5:$AK$30,MATCH($B78,'Daily Sales'!$A$5:$A$30,0)),0) -> 85 | J78: =G78*I78 -> 85
A79: RC-FM011 | B79: FM011 | C79: Butter Croissant | D79: FD009 | E79: Butter (Unsalted) | F79: Kg | G79: 0.02 | H79: =G79*IFERROR(INDEX('Item Master'!$E$4:$E$41,MATCH(D79,'Item Master'!$A$4:$A$41,0)),INDEX('Sub-Recipe'!$K$4:$K$200,MATCH(D79,'Sub-Recipe'!$A$4:$A$200,0))) -> 9.6 | I79: =IFERROR(INDEX('Daily Sales'!$AK$5:$AK$30,MATCH($B79,'Daily Sales'!$A$5:$A$30,0)),0) -> 85 | J79: =G79*I79 -> 1.7
A80: RC-FM011 | B80: FM011 | C80: TOTAL STANDARD RECIPE COST - Butter Croissant | D80: TOTAL | H80: =SUM(H78:H79) -> 9.6
A82: RC-FM012 | B82: FM012 | C82: Danish Pastry | D82: SR004 | E82: TOTAL - Danish Pastry Dough (Homemade) (Sub-Recipe) | F82: Pcs | G82: 1 | H82: =G82*IFERROR(INDEX('Item Master'!$E$4:$E$41,MATCH(D82,'Item Master'!$A$4:$A$41,0)),INDEX('Sub-Recipe'!$K$4:$K$200,MATCH(D82,'Sub-Recipe'!$A$4:$A$200,0))) -> 0 | I82: =IFERROR(INDEX('Daily Sales'!$AK$5:$AK$30,MATCH($B82,'Daily Sales'!$A$5:$A$30,0)),0) -> 62 | J82: =G82*I82 -> 62
A83: RC-FM012 | B83: FM012 | C83: Danish Pastry | D83: FD009 | E83: Butter (Unsalted) | F83: Kg | G83: 0.01 | H83: =G83*IFERROR(INDEX('Item Master'!$E$4:$E$41,MATCH(D83,'Item Master'!$A$4:$A$41,0)),INDEX('Sub-Recipe'!$K$4:$K$200,MATCH(D83,'Sub-Recipe'!$A$4:$A$200,0))) -> 4.8 | I83: =IFERROR(INDEX('Daily Sales'!$AK$5:$AK$30,MATCH($B83,'Daily Sales'!$A$5:$A$30,0)),0) -> 62 | J83: =G83*I83 -> 0.62
A84: RC-FM012 | B84: FM012 | C84: TOTAL STANDARD RECIPE COST - Danish Pastry | D84: TOTAL | H84: =SUM(H82:H83) -> 4.8
A86: RC-FM013 | B86: FM013 | C86: Chicken Caesar Salad | D86: FD002 | E86: Chicken Breast (Boneless) | F86: Kg | G86: 0.12 | H86: =G86*IFERROR(INDEX('Item Master'!$E$4:$E$41,MATCH(D86,'Item Master'!$A$4:$A$41,0)),INDEX('Sub-Recipe'!$K$4:$K$200,MATCH(D86,'Sub-Recipe'!$A$4:$A$200,0))) -> 57.6 | I86: =IFERROR(INDEX('Daily Sales'!$AK$5:$AK$30,MATCH($B86,'Daily Sales'!$A$5:$A$30,0)),0) -> 41 | J86: =G86*I86 -> 4.92
A87: RC-FM013 | B87: FM013 | C87: Chicken Caesar Salad | D87: FD004 | E87: Fresh Lettuce | F87: Kg | G87: 0.1 | H87: =G87*IFERROR(INDEX('Item Master'!$E$4:$E$41,MATCH(D87,'Item Master'!$A$4:$A$41,0)),INDEX('Sub-Recipe'!$K$4:$K$200,MATCH(D87,'Sub-Recipe'!$A$4:$A$200,0))) -> 6 | I87: =IFERROR(INDEX('Daily Sales'!$AK$5:$AK$30,MATCH($B87,'Daily Sales'!$A$5:$A$30,0)),0) -> 41 | J87: =G87*I87 -> 4.1
A88: RC-FM013 | B88: FM013 | C88: Chicken Caesar Salad | D88: SR008 | E88: TOTAL - Caesar Dressing (Homemade) (Sub-Recipe) | F88: Portions (100g) | G88: 1 | H88: =G88*IFERROR(INDEX('Item Master'!$E$4:$E$41,MATCH(D88,'Item Master'!$A$4:$A$41,0)),INDEX('Sub-Recipe'!$K$4:$K$200,MATCH(D88,'Sub-Recipe'!$A$4:$A$200,0))) -> 0 | I88: =IFERROR(INDEX('Daily Sales'!$AK$5:$AK$30,MATCH($B88,'Daily Sales'!$A$5:$A$30,0)),0) -> 41 | J88: =G88*I88 -> 41
A89: RC-FM013 | B89: FM013 | C89: Chicken Caesar Salad | D89: FD015 | E89: Mozzarella Cheese | F89: Kg | G89: 0.02 | H89: =G89*IFERROR(INDEX('Item Master'!$E$4:$E$41,MATCH(D89,'Item Master'!$A$4:$A$41,0)),INDEX('Sub-Recipe'!$K$4:$K$200,MATCH(D89,'Sub-Recipe'!$A$4:$A$200,0))) -> 12.4 | I89: =IFERROR(INDEX('Daily Sales'!$AK$5:$AK$30,MATCH($B89,'Daily Sales'!$A$5:$A$30,0)),0) -> 41 | J89: =G89*I89 -> 0.82
A90: RC-FM013 | B90: FM013 | C90: TOTAL STANDARD RECIPE COST - Chicken Caesar Salad | D90: TOTAL | H90: =SUM(H86:H89) -> 76
A92: RC-FM014 | B92: FM014 | C92: Avocado Salad | D92: BV009 | E92: Fresh Avocado | F92: Kg | G92: 0.15 | H92: =G92*IFERROR(INDEX('Item Master'!$E$4:$E$41,MATCH(D92,'Item Master'!$A$4:$A$41,0)),INDEX('Sub-Recipe'!$K$4:$K$200,MATCH(D92,'Sub-Recipe'!$A$4:$A$200,0))) -> 13.5 | I92: =IFERROR(INDEX('Daily Sales'!$AK$5:$AK$30,MATCH($B92,'Daily Sales'!$A$5:$A$30,0)),0) -> 33 | J92: =G92*I92 -> 4.95
A93: RC-FM014 | B93: FM014 | C93: Avocado Salad | D93: FD004 | E93: Fresh Lettuce | F93: Kg | G93: 0.1 | H93: =G93*IFERROR(INDEX('Item Master'!$E$4:$E$41,MATCH(D93,'Item Master'!$A$4:$A$41,0)),INDEX('Sub-Recipe'!$K$4:$K$200,MATCH(D93,'Sub-Recipe'!$A$4:$A$200,0))) -> 6 | I93: =IFERROR(INDEX('Daily Sales'!$AK$5:$AK$30,MATCH($B93,'Daily Sales'!$A$5:$A$30,0)),0) -> 33 | J93: =G93*I93 -> 3.3
A94: RC-FM014 | B94: FM014 | C94: Avocado Salad | D94: FD005 | E94: Fresh Tomato | F94: Kg | G94: 0.05 | H94: =G94*IFERROR(INDEX('Item Master'!$E$4:$E$41,MATCH(D94,'Item Master'!$A$4:$A$41,0)),INDEX('Sub-Recipe'!$K$4:$K$200,MATCH(D94,'Sub-Recipe'!$A$4:$A$200,0))) -> 2.75 | I94: =IFERROR(INDEX('Daily Sales'!$AK$5:$AK$30,MATCH($B94,'Daily Sales'!$A$5:$A$30,0)),0) -> 33 | J94: =G94*I94 -> 1.65
A95: RC-FM014 | B95: FM014 | C95: Avocado Salad | D95: FD006 | E95: Onion | F95: Kg | G95: 0.02 | H95: =G95*IFERROR(INDEX('Item Master'!$E$4:$E$41,MATCH(D95,'Item Master'!$A$4:$A$41,0)),INDEX('Sub-Recipe'!$K$4:$K$200,MATCH(D95,'Sub-Recipe'!$A$4:$A$200,0))) -> 0.8 | I95: =IFERROR(INDEX('Daily Sales'!$AK$5:$AK$30,MATCH($B95,'Daily Sales'!$A$5:$A$30,0)),0) -> 33 | J95: =G95*I95 -> 0.66
A96: RC-FM014 | B96: FM014 | C96: Avocado Salad | D96: OT007 | E96: Cooking / Vegetable Oil | F96: Ltr | G96: 0.02 | H96: =G96*IFERROR(INDEX('Item Master'!$E$4:$E$41,MATCH(D96,'Item Master'!$A$4:$A$41,0)),INDEX('Sub-Recipe'!$K$4:$K$200,MATCH(D96,'Sub-Recipe'!$A$4:$A$200,0))) -> 3 | I96: =IFERROR(INDEX('Daily Sales'!$AK$5:$AK$30,MATCH($B96,'Daily Sales'!$A$5:$A$30,0)),0) -> 33 | J96: =G96*I96 -> 0.66
A97: RC-FM014 | B97: FM014 | C97: TOTAL STANDARD RECIPE COST - Avocado Salad | D97: TOTAL | H97: =SUM(H92:H96) -> 26.05
A99: RC-FM015 | B99: FM015 | C99: Margherita Pizza | D99: SR005 | E99: TOTAL - Pizza Dough Base (Homemade) (Sub-Recipe) | F99: Bases | G99: 1 | H99: =G99*IFERROR(INDEX('Item Master'!$E$4:$E$41,MATCH(D99,'Item Master'!$A$4:$A$41,0)),INDEX('Sub-Recipe'!$K$4:$K$200,MATCH(D99,'Sub-Recipe'!$A$4:$A$200,0))) -> 0 | I99: =IFERROR(INDEX('Daily Sales'!$AK$5:$AK$30,MATCH($B99,'Daily Sales'!$A$5:$A$30,0)),0) -> 82 | J99: =G99*I99 -> 82
A100: RC-FM015 | B100: FM015 | C100: Margherita Pizza | D100: SR009 | E100: TOTAL - Pizza Tomato Sauce (Homemade) (Sub-Recipe) | F100: Portions (100g) | G100: 1 | H100: =G100*IFERROR(INDEX('Item Master'!$E$4:$E$41,MATCH(D100,'Item Master'!$A$4:$A$41,0)),INDEX('Sub-Recipe'!$K$4:$K$200,MATCH(D100,'Sub-Recipe'!$A$4:$A$200,0))) -> 0 | I100: =IFERROR(INDEX('Daily Sales'!$AK$5:$AK$30,MATCH($B100,'Daily Sales'!$A$5:$A$30,0)),0) -> 82 | J100: =G100*I100 -> 82
A101: RC-FM015 | B101: FM015 | C101: Margherita Pizza | D101: FD015 | E101: Mozzarella Cheese | F101: Kg | G101: 0.15 | H101: =G101*IFERROR(INDEX('Item Master'!$E$4:$E$41,MATCH(D101,'Item Master'!$A$4:$A$41,0)),INDEX('Sub-Recipe'!$K$4:$K$200,MATCH(D101,'Sub-Recipe'!$A$4:$A$200,0))) -> 93 | I101: =IFERROR(INDEX('Daily Sales'!$AK$5:$AK$30,MATCH($B101,'Daily Sales'!$A$5:$A$30,0)),0) -> 82 | J101: =G101*I101 -> 12.3
A102: RC-FM015 | B102: FM015 | C102: TOTAL STANDARD RECIPE COST - Margherita Pizza | D102: TOTAL | H102: =SUM(H99:H101) -> 93
A104: RC-BM001 | B104: BM001 | C104: Americano | D104: BV001 | E104: Coffee Beans (Roasted) | F104: Kg | G104: 0.018 | H104: =G104*IFERROR(INDEX('Item Master'!$E$4:$E$41,MATCH(D104,'Item Master'!$A$4:$A$41,0)),INDEX('Sub-Recipe'!$K$4:$K$200,MATCH(D104,'Sub-Recipe'!$A$4:$A$200,0))) -> 16.2 | I104: =IFERROR(INDEX('Daily Sales'!$AK$5:$AK$30,MATCH($B104,'Daily Sales'!$A$5:$A$30,0)),0) -> 137 | J104: =G104*I104 -> 2.466
A105: RC-BM001 | B105: BM001 | C105: TOTAL STANDARD RECIPE COST - Americano | D105: TOTAL | H105: =SUM(H104:H104) -> 16.2
A107: RC-BM002 | B107: BM002 | C107: Cappuccino | D107: BV001 | E107: Coffee Beans (Roasted) | F107: Kg | G107: 0.018 | H107: =G107*IFERROR(INDEX('Item Master'!$E$4:$E$41,MATCH(D107,'Item Master'!$A$4:$A$41,0)),INDEX('Sub-Recipe'!$K$4:$K$200,MATCH(D107,'Sub-Recipe'!$A$4:$A$200,0))) -> 16.2 | I107: =IFERROR(INDEX('Daily Sales'!$AK$5:$AK$30,MATCH($B107,'Daily Sales'!$A$5:$A$30,0)),0) -> 157 | J107: =G107*I107 -> 2.826
A108: RC-BM002 | B108: BM002 | C108: Cappuccino | D108: BV004 | E108: Fresh Milk | F108: Ltr | G108: 0.15 | H108: =G108*IFERROR(INDEX('Item Master'!$E$4:$E$41,MATCH(D108,'Item Master'!$A$4:$A$41,0)),INDEX('Sub-Recipe'!$K$4:$K$200,MATCH(D108,'Sub-Recipe'!$A$4:$A$200,0))) -> 9.75 | I108: =IFERROR(INDEX('Daily Sales'!$AK$5:$AK$30,MATCH($B108,'Daily Sales'!$A$5:$A$30,0)),0) -> 157 | J108: =G108*I108 -> 23.55
A109: RC-BM002 | B109: BM002 | C109: TOTAL STANDARD RECIPE COST - Cappuccino | D109: TOTAL | H109: =SUM(H107:H108) -> 25.95
A111: RC-BM003 | B111: BM003 | C111: English Breakfast Tea | D111: BV002 | E111: Black Tea Bags | F111: Pcs | G111: 1 | H111: =G111*IFERROR(INDEX('Item Master'!$E$4:$E$41,MATCH(D111,'Item Master'!$A$4:$A$41,0)),INDEX('Sub-Recipe'!$K$4:$K$200,MATCH(D111,'Sub-Recipe'!$A$4:$A$200,0))) -> 3 | I111: =IFERROR(INDEX('Daily Sales'!$AK$5:$AK$30,MATCH($B111,'Daily Sales'!$A$5:$A$30,0)),0) -> 74 | J111: =G111*I111 -> 74
A112: RC-BM003 | B112: BM003 | C112: English Breakfast Tea | D112: BV004 | E112: Fresh Milk | F112: Ltr | G112: 0.05 | H112: =G112*IFERROR(INDEX('Item Master'!$E$4:$E$41,MATCH(D112,'Item Master'!$A$4:$A$41,0)),INDEX('Sub-Recipe'!$K$4:$K$200,MATCH(D112,'Sub-Recipe'!$A$4:$A$200,0))) -> 3.25 | I112: =IFERROR(INDEX('Daily Sales'!$AK$5:$AK$30,MATCH($B112,'Daily Sales'!$A$5:$A$30,0)),0) -> 74 | J112: =G112*I112 -> 3.7
A113: RC-BM003 | B113: BM003 | C113: TOTAL STANDARD RECIPE COST - English Breakfast Tea | D113: TOTAL | H113: =SUM(H111:H112) -> 6.25
A115: RC-BM004 | B115: BM004 | C115: Green Tea | D115: BV003 | E115: Green Tea Bags | F115: Pcs | G115: 1 | H115: =G115*IFERROR(INDEX('Item Master'!$E$4:$E$41,MATCH(D115,'Item Master'!$A$4:$A$41,0)),INDEX('Sub-Recipe'!$K$4:$K$200,MATCH(D115,'Sub-Recipe'!$A$4:$A$200,0))) -> 4 | I115: =IFERROR(INDEX('Daily Sales'!$AK$5:$AK$30,MATCH($B115,'Daily Sales'!$A$5:$A$30,0)),0) -> 53 | J115: =G115*I115 -> 53
A116: RC-BM004 | B116: BM004 | C116: TOTAL STANDARD RECIPE COST - Green Tea | D116: TOTAL | H116: =SUM(H115:H115) -> 4
A118: RC-BM005 | B118: BM005 | C118: Hot Chocolate | D118: BV005 | E118: Cocoa Powder | F118: Kg | G118: 0.03 | H118: =G118*IFERROR(INDEX('Item Master'!$E$4:$E$41,MATCH(D118,'Item Master'!$A$4:$A$41,0)),INDEX('Sub-Recipe'!$K$4:$K$200,MATCH(D118,'Sub-Recipe'!$A$4:$A$200,0))) -> 10.5 | I118: =IFERROR(INDEX('Daily Sales'!$AK$5:$AK$30,MATCH($B118,'Daily Sales'!$A$5:$A$30,0)),0) -> 52 | J118: =G118*I118 -> 1.56
A119: RC-BM005 | B119: BM005 | C119: Hot Chocolate | D119: BV004 | E119: Fresh Milk | F119: Ltr | G119: 0.2 | H119: =G119*IFERROR(INDEX('Item Master'!$E$4:$E$41,MATCH(D119,'Item Master'!$A$4:$A$41,0)),INDEX('Sub-Recipe'!$K$4:$K$200,MATCH(D119,'Sub-Recipe'!$A$4:$A$200,0))) -> 13 | I119: =IFERROR(INDEX('Daily Sales'!$AK$5:$AK$30,MATCH($B119,'Daily Sales'!$A$5:$A$30,0)),0) -> 52 | J119: =G119*I119 -> 10.4
...

Sheet Sub-Recipe
A1: SUB-RECIPE MASTER
A2: Homemade components costed once, then pulled into Recipe Master as a single ingredient line
A3: SUB-RECIPE CODE | B3: MENU CODE(S) | C3: COMPONENT NAME | D3: ITEM CODE | E3: INGREDIENT | F3: UOM | G3: QTY | H3: ITEM COST (ETB) | I3: BATCH YIELD QTY | J3: YIELD UOM | K3: COST PER UNIT (ETB) | L3: PORTIONS CONSUMED (MONTHLY) | M3: BATCHES REQUIRED | N3: THEORETICAL RAW QTY THIS LINE
A4: SR001 | B4: FM001, FM002 | C4: Burger Bun (Homemade) | D4: FD008 | E4: All-Purpose Flour | F4: Kg | G4: 1 | H4: =G4*IFERROR(INDEX('Item Master'!$E$4:$E$41,MATCH(D4,'Item Master'!$A$4:$A$41,0)),0) -> 55 | N4: =G4*$M$10 -> 6.6
A5: SR001 | B5: FM001, FM002 | C5: Burger Bun (Homemade) | D5: OT008 | E5: Instant Dry Yeast | F5: Kg | G5: 0.02 | H5: =G5*IFERROR(INDEX('Item Master'!$E$4:$E$41,MATCH(D5,'Item Master'!$A$4:$A$41,0)),0) -> 8 | N5: =G5*$M$10 -> 0.132
A6: SR001 | B6: FM001, FM002 | C6: Burger Bun (Homemade) | D6: FD009 | E6: Butter (Unsalted) | F6: Kg | G6: 0.08 | H6: =G6*IFERROR(INDEX('Item Master'!$E$4:$E$41,MATCH(D6,'Item Master'!$A$4:$A$41,0)),0) -> 38.4 | N6: =G6*$M$10 -> 0.528
A7: SR001 | B7: FM001, FM002 | C7: Burger Bun (Homemade) | D7: OT005 | E7: White Sugar | F7: Kg | G7: 0.05 | H7: =G7*IFERROR(INDEX('Item Master'!$E$4:$E$41,MATCH(D7,'Item Master'!$A$4:$A$41,0)),0) -> 3 | N7: =G7*$M$10 -> 0.33
A8: SR001 | B8: FM001, FM002 | C8: Burger Bun (Homemade) | D8: OT006 | E8: Iodized Salt | F8: Kg | G8: 0.015 | H8: =G8*IFERROR(INDEX('Item Master'!$E$4:$E$41,MATCH(D8,'Item Master'!$A$4:$A$41,0)),0) -> 0.375 | N8: =G8*$M$10 -> 0.099
A9: SR001 | B9: FM001, FM002 | C9: Burger Bun (Homemade) | D9: FD010 | E9: Fresh Eggs | F9: Pcs | G9: 1 | H9: =G9*IFERROR(INDEX('Item Master'!$E$4:$E$41,MATCH(D9,'Item Master'!$A$4:$A$41,0)),0) -> 8 | N9: =G9*$M$10 -> 6.6
A10: SR001 | C10: TOTAL - Burger Bun (Homemade) | D10: TOTAL | H10: =SUM(H4:H9) -> 112.775 | I10: 20 | J10: Pcs | K10: =IFERROR(H10/I10,0) -> 5.63875 | L10: =SUMIF('Recipe Master'!$D$4:$D$146,A10,'Recipe Master'!$J$4:$J$146) -> 132 | M10: =IFERROR(L10/I10,0) -> 6.6
A12: SR002 | B12: FM005, FM006, FM009 | C12: Sandwich Bread Loaf (Homemade) | D12: FD008 | E12: All-Purpose Flour | F12: Kg | G12: 1 | H12: =G12*IFERROR(INDEX('Item Master'!$E$4:$E$41,MATCH(D12,'Item Master'!$A$4:$A$41,0)),0) -> 55 | N12: =G12*$M$17 -> 16.4
A13: SR002 | B13: FM005, FM006, FM009 | C13: Sandwich Bread Loaf (Homemade) | D13: OT008 | E13: Instant Dry Yeast | F13: Kg | G13: 0.02 | H13: =G13*IFERROR(INDEX('Item Master'!$E$4:$E$41,MATCH(D13,'Item Master'!$A$4:$A$41,0)),0) -> 8 | N13: =G13*$M$17 -> 0.328
A14: SR002 | B14: FM005, FM006, FM009 | C14: Sandwich Bread Loaf (Homemade) | D14: FD009 | E14: Butter (Unsalted) | F14: Kg | G14: 0.05 | H14: =G14*IFERROR(INDEX('Item Master'!$E$4:$E$41,MATCH(D14,'Item Master'!$A$4:$A$41,0)),0) -> 24 | N14: =G14*$M$17 -> 0.82
A15: SR002 | B15: FM005, FM006, FM009 | C15: Sandwich Bread Loaf (Homemade) | D15: OT006 | E15: Iodized Salt | F15: Kg | G15: 0.015 | H15: =G15*IFERROR(INDEX('Item Master'!$E$4:$E$41,MATCH(D15,'Item Master'!$A$4:$A$41,0)),0) -> 0.375 | N15: =G15*$M$17 -> 0.246
A16: SR002 | B16: FM005, FM006, FM009 | C16: Sandwich Bread Loaf (Homemade) | D16: OT005 | E16: White Sugar | F16: Kg | G16: 0.02 | H16: =G16*IFERROR(INDEX('Item Master'!$E$4:$E$41,MATCH(D16,'Item Master'!$A$4:$A$41,0)),0) -> 1.2 | N16: =G16*$M$17 -> 0.328
A17: SR002 | C17: TOTAL - Sandwich Bread Loaf (Homemade) | D17: TOTAL | H17: =SUM(H12:H16) -> 88.575 | I17: 20 | J17: Slices | K17: =IFERROR(H17/I17,0) -> 4.42875 | L17: =SUMIF('Recipe Master'!$D$4:$D$146,A17,'Recipe Master'!$J$4:$J$146) -> 328 | M17: =IFERROR(L17/I17,0) -> 16.4
A19: SR003 | B19: FM010, FM011 | C19: Croissant Dough (Homemade) | D19: FD008 | E19: All-Purpose Flour | F19: Kg | G19: 1 | H19: =G19*IFERROR(INDEX('Item Master'!$E$4:$E$41,MATCH(D19,'Item Master'!$A$4:$A$41,0)),0) -> 55 | N19: =G19*$M$24 -> 11.2
A20: SR003 | B20: FM010, FM011 | C20: Croissant Dough (Homemade) | D20: FD009 | E20: Butter (Unsalted) | F20: Kg | G20: 0.5 | H20: =G20*IFERROR(INDEX('Item Master'!$E$4:$E$41,MATCH(D20,'Item Master'!$A$4:$A$41,0)),0) -> 240 | N20: =G20*$M$24 -> 5.6
A21: SR003 | B21: FM010, FM011 | C21: Croissant Dough (Homemade) | D21: OT005 | E21: White Sugar | F21: Kg | G21: 0.05 | H21: =G21*IFERROR(INDEX('Item Master'!$E$4:$E$41,MATCH(D21,'Item Master'!$A$4:$A$41,0)),0) -> 3 | N21: =G21*$M$24 -> 0.56
A22: SR003 | B22: FM010, FM011 | C22: Croissant Dough (Homemade) | D22: OT008 | E22: Instant Dry Yeast | F22: Kg | G22: 0.02 | H22: =G22*IFERROR(INDEX('Item Master'!$E$4:$E$41,MATCH(D22,'Item Master'!$A$4:$A$41,0)),0) -> 8 | N22: =G22*$M$24 -> 0.224
A23: SR003 | B23: FM010, FM011 | C23: Croissant Dough (Homemade) | D23: FD010 | E23: Fresh Eggs | F23: Pcs | G23: 1 | H23: =G23*IFERROR(INDEX('Item Master'!$E$4:$E$41,MATCH(D23,'Item Master'!$A$4:$A$41,0)),0) -> 8 | N23: =G23*$M$24 -> 11.2
A24: SR003 | C24: TOTAL - Croissant Dough (Homemade) | D24: TOTAL | H24: =SUM(H19:H23) -> 314 | I24: 10 | J24: Pcs | K24: =IFERROR(H24/I24,0) -> 31.4 | L24: =SUMIF('Recipe Master'!$D$4:$D$146,A24,'Recipe Master'!$J$4:$J$146) -> 112 | M24: =IFERROR(L24/I24,0) -> 11.2
A26: SR004 | B26: FM010, FM012 | C26: Danish Pastry Dough (Homemade) | D26: FD008 | E26: All-Purpose Flour | F26: Kg | G26: 1 | H26: =G26*IFERROR(INDEX('Item Master'!$E$4:$E$41,MATCH(D26,'Item Master'!$A$4:$A$41,0)),0) -> 55 | N26: =G26*$M$30 -> 8.9
A27: SR004 | B27: FM010, FM012 | C27: Danish Pastry Dough (Homemade) | D27: FD009 | E27: Butter (Unsalted) | F27: Kg | G27: 0.4 | H27: =G27*IFERROR(INDEX('Item Master'!$E$4:$E$41,MATCH(D27,'Item Master'!$A$4:$A$41,0)),0) -> 192 | N27: =G27*$M$30 -> 3.56
A28: SR004 | B28: FM010, FM012 | C28: Danish Pastry Dough (Homemade) | D28: OT005 | E28: White Sugar | F28: Kg | G28: 0.1 | H28: =G28*IFERROR(INDEX('Item Master'!$E$4:$E$41,MATCH(D28,'Item Master'!$A$4:$A$41,0)),0) -> 6 | N28: =G28*$M$30 -> 0.89
A29: SR004 | B29: FM010, FM012 | C29: Danish Pastry Dough (Homemade) | D29: FD010 | E29: Fresh Eggs | F29: Pcs | G29: 2 | H29: =G29*IFERROR(INDEX('Item Master'!$E$4:$E$41,MATCH(D29,'Item Master'!$A$4:$A$41,0)),0) -> 16 | N29: =G29*$M$30 -> 17.8
A30: SR004 | C30: TOTAL - Danish Pastry Dough (Homemade) | D30: TOTAL | H30: =SUM(H26:H29) -> 269 | I30: 10 | J30: Pcs | K30: =IFERROR(H30/I30,0) -> 26.9 | L30: =SUMIF('Recipe Master'!$D$4:$D$146,A30,'Recipe Master'!$J$4:$J$146) -> 89 | M30: =IFERROR(L30/I30,0) -> 8.9
A32: SR005 | B32: FM015 | C32: Pizza Dough Base (Homemade) | D32: FD008 | E32: All-Purpose Flour | F32: Kg | G32: 1 | H32: =G32*IFERROR(INDEX('Item Master'!$E$4:$E$41,MATCH(D32,'Item Master'!$A$4:$A$41,0)),0) -> 55 | N32: =G32*$M$36 -> 16.4
A33: SR005 | B33: FM015 | C33: Pizza Dough Base (Homemade) | D33: OT008 | E33: Instant Dry Yeast | F33: Kg | G33: 0.02 | H33: =G33*IFERROR(INDEX('Item Master'!$E$4:$E$41,MATCH(D33,'Item Master'!$A$4:$A$41,0)),0) -> 8 | N33: =G33*$M$36 -> 0.328
A34: SR005 | B34: FM015 | C34: Pizza Dough Base (Homemade) | D34: OT006 | E34: Iodized Salt | F34: Kg | G34: 0.02 | H34: =G34*IFERROR(INDEX('Item Master'!$E$4:$E$41,MATCH(D34,'Item Master'!$A$4:$A$41,0)),0) -> 0.5 | N34: =G34*$M$36 -> 0.328
A35: SR005 | B35: FM015 | C35: Pizza Dough Base (Homemade) | D35: OT007 | E35: Cooking / Vegetable Oil | F35: Ltr | G35: 0.05 | H35: =G35*IFERROR(INDEX('Item Master'!$E$4:$E$41,MATCH(D35,'Item Master'!$A$4:$A$41,0)),0) -> 7.5 | N35: =G35*$M$36 -> 0.82
A36: SR005 | C36: TOTAL - Pizza Dough Base (Homemade) | D36: TOTAL | H36: =SUM(H32:H35) -> 71 | I36: 5 | J36: Bases | K36: =IFERROR(H36/I36,0) -> 14.2 | L36: =SUMIF('Recipe Master'!$D$4:$D$146,A36,'Recipe Master'!$J$4:$J$146) -> 82 | M36: =IFERROR(L36/I36,0) -> 16.4
A38: SR006 | B38: FM007 | C38: Bolognese Sauce (Homemade) | D38: FD001 | E38: Beef Mince (80% Lean) | F38: Kg | G38: 1 | H38: =G38*IFERROR(INDEX('Item Master'!$E$4:$E$41,MATCH(D38,'Item Master'!$A$4:$A$41,0)),0) -> 550 | N38: =G38*$M$43 -> 8.25
A39: SR006 | B39: FM007 | C39: Bolognese Sauce (Homemade) | D39: FD005 | E39: Fresh Tomato | F39: Kg | G39: 0.5 | H39: =G39*IFERROR(INDEX('Item Master'!$E$4:$E$41,MATCH(D39,'Item Master'!$A$4:$A$41,0)),0) -> 27.5 | N39: =G39*$M$43 -> 4.125
A40: SR006 | B40: FM007 | C40: Bolognese Sauce (Homemade) | D40: FD006 | E40: Onion | F40: Kg | G40: 0.3 | H40: =G40*IFERROR(INDEX('Item Master'!$E$4:$E$41,MATCH(D40,'Item Master'!$A$4:$A$41,0)),0) -> 12 | N40: =G40*$M$43 -> 2.475
A41: SR006 | B41: FM007 | C41: Bolognese Sauce (Homemade) | D41: OT007 | E41: Cooking / Vegetable Oil | F41: Ltr | G41: 0.05 | H41: =G41*IFERROR(INDEX('Item Master'!$E$4:$E$41,MATCH(D41,'Item Master'!$A$4:$A$41,0)),0) -> 7.5 | N41: =G41*$M$43 -> 0.4125
A42: SR006 | B42: FM007 | C42: Bolognese Sauce (Homemade) | D42: OT006 | E42: Iodized Salt | F42: Kg | G42: 0.02 | H42: =G42*IFERROR(INDEX('Item Master'!$E$4:$E$41,MATCH(D42,'Item Master'!$A$4:$A$41,0)),0) -> 0.5 | N42: =G42*$M$43 -> 0.165
A43: SR006 | C43: TOTAL - Bolognese Sauce (Homemade) | D43: TOTAL | H43: =SUM(H38:H42) -> 597.5 | I43: 8 | J43: Portions (250g) | K43: =IFERROR(H43/I43,0) -> 74.6875 | L43: =SUMIF('Recipe Master'!$D$4:$D$146,A43,'Recipe Master'!$J$4:$J$146) -> 66 | M43: =IFERROR(L43/I43,0) -> 8.25
A45: SR007 | B45: FM008 | C45: Alfredo Sauce (Homemade) | D45: FD009 | E45: Butter (Unsalted) | F45: Kg | G45: 0.3 | H45: =G45*IFERROR(INDEX('Item Master'!$E$4:$E$41,MATCH(D45,'Item Master'!$A$4:$A$41,0)),0) -> 144 | N45: =G45*$M$49 -> 1.8
A46: SR007 | B46: FM008 | C46: Alfredo Sauce (Homemade) | D46: BV004 | E46: Fresh Milk | F46: Ltr | G46: 0.5 | H46: =G46*IFERROR(INDEX('Item Master'!$E$4:$E$41,MATCH(D46,'Item Master'!$A$4:$A$41,0)),0) -> 32.5 | N46: =G46*$M$49 -> 3
A47: SR007 | B47: FM008 | C47: Alfredo Sauce (Homemade) | D47: FD015 | E47: Mozzarella Cheese | F47: Kg | G47: 0.2 | H47: =G47*IFERROR(INDEX('Item Master'!$E$4:$E$41,MATCH(D47,'Item Master'!$A$4:$A$41,0)),0) -> 124 | N47: =G47*$M$49 -> 1.2
A48: SR007 | B48: FM008 | C48: Alfredo Sauce (Homemade) | D48: OT009 | E48: Black Pepper (Ground) | F48: Kg | G48: 0.01 | H48: =G48*IFERROR(INDEX('Item Master'!$E$4:$E$41,MATCH(D48,'Item Master'!$A$4:$A$41,0)),0) -> 5 | N48: =G48*$M$49 -> 0.06
A49: SR007 | C49: TOTAL - Alfredo Sauce (Homemade) | D49: TOTAL | H49: =SUM(H45:H48) -> 305.5 | I49: 8 | J49: Portions (125g) | K49: =IFERROR(H49/I49,0) -> 38.1875 | L49: =SUMIF('Recipe Master'!$D$4:$D$146,A49,'Recipe Master'!$J$4:$J$146) -> 48 | M49: =IFERROR(L49/I49,0) -> 6
A51: SR008 | B51: FM003, FM013 | C51: Caesar Dressing (Homemade) | D51: FD013 | E51: Mayonnaise | F51: Kg | G51: 0.6 | H51: =G51*IFERROR(INDEX('Item Master'!$E$4:$E$41,MATCH(D51,'Item Master'!$A$4:$A$41,0)),0) -> 132 | N51: =G51*$M$55 -> 5.52
A52: SR008 | B52: FM003, FM013 | C52: Caesar Dressing (Homemade) | D52: FD015 | E52: Mozzarella Cheese | F52: Kg | G52: 0.1 | H52: =G52*IFERROR(INDEX('Item Master'!$E$4:$E$41,MATCH(D52,'Item Master'!$A$4:$A$41,0)),0) -> 62 | N52: =G52*$M$55 -> 0.92
A53: SR008 | B53: FM003, FM013 | C53: Caesar Dressing (Homemade) | D53: OT009 | E53: Black Pepper (Ground) | F53: Kg | G53: 0.01 | H53: =G53*IFERROR(INDEX('Item Master'!$E$4:$E$41,MATCH(D53,'Item Master'!$A$4:$A$41,0)),0) -> 5 | N53: =G53*$M$55 -> 0.092
A54: SR008 | B54: FM003, FM013 | C54: Caesar Dressing (Homemade) | D54: BV008 | E54: Fresh Lime | F54: Kg | G54: 0.1 | H54: =G54*IFERROR(INDEX('Item Master'!$E$4:$E$41,MATCH(D54,'Item Master'!$A$4:$A$41,0)),0) -> 10 | N54: =G54*$M$55 -> 0.92
A55: SR008 | C55: TOTAL - Caesar Dressing (Homemade) | D55: TOTAL | H55: =SUM(H51:H54) -> 209 | I55: 10 | J55: Portions (100g) | K55: =IFERROR(H55/I55,0) -> 20.9 | L55: =SUMIF('Recipe Master'!$D$4:$D$146,A55,'Recipe Master'!$J$4:$J$146) -> 92 | M55: =IFERROR(L55/I55,0) -> 9.2
A57: SR009 | B57: FM015 | C57: Pizza Tomato Sauce (Homemade) | D57: FD005 | E57: Fresh Tomato | F57: Kg | G57: 1 | H57: =G57*IFERROR(INDEX('Item Master'!$E$4:$E$41,MATCH(D57,'Item Master'!$A$4:$A$41,0)),0) -> 55 | N57: =G57*$M$61 -> 8.2
A58: SR009 | B58: FM015 | C58: Pizza Tomato Sauce (Homemade) | D58: FD006 | E58: Onion | F58: Kg | G58: 0.2 | H58: =G58*IFERROR(INDEX('Item Master'!$E$4:$E$41,MATCH(D58,'Item Master'!$A$4:$A$41,0)),0) -> 8 | N58: =G58*$M$61 -> 1.64
A59: SR009 | B59: FM015 | C59: Pizza Tomato Sauce (Homemade) | D59: OT007 | E59: Cooking / Vegetable Oil | F59: Ltr | G59: 0.03 | H59: =G59*IFERROR(INDEX('Item Master'!$E$4:$E$41,MATCH(D59,'Item Master'!$A$4:$A$41,0)),0) -> 4.5 | N59: =G59*$M$61 -> 0.246
A60: SR009 | B60: FM015 | C60: Pizza Tomato Sauce (Homemade) | D60: OT006 | E60: Iodized Salt | F60: Kg | G60: 0.01 | H60: =G60*IFERROR(INDEX('Item Master'!$E$4:$E$41,MATCH(D60,'Item Master'!$A$4:$A$41,0)),0) -> 0.25 | N60: =G60*$M$61 -> 0.082
A61: SR009 | C61: TOTAL - Pizza Tomato Sauce (Homemade) | D61: TOTAL | H61: =SUM(H57:H60) -> 67.75 | I61: 10 | J61: Portions (100g) | K61: =IFERROR(H61/I61,0) -> 6.775 | L61: =SUMIF('Recipe Master'!$D$4:$D$146,A61,'Recipe Master'!$J$4:$J$146) -> 82 | M61: =IFERROR(L61/I61,0) -> 8.2
A63: SR010 | B63: BM006, BM007 | C63: Mojito Syrup Base (Homemade) | D63: OT005 | E63: White Sugar | F63: Kg | G63: 0.5 | H63: =G63*IFERROR(INDEX('Item Master'!$E$4:$E$41,MATCH(D63,'Item Master'!$A$4:$A$41,0)),0) -> 30 | N63: =G63*$M$66 -> 2.625
A64: SR010 | B64: BM006, BM007 | C64: Mojito Syrup Base (Homemade) | D64: BV007 | E64: Fresh Mint Leaves | F64: Kg | G64: 0.1 | H64: =G64*IFERROR(INDEX('Item Master'!$E$4:$E$41,MATCH(D64,'Item Master'!$A$4:$A$41,0)),0) -> 15 | N64: =G64*$M$66 -> 0.525
A65: SR010 | B65: BM006, BM007 | C65: Mojito Syrup Base (Homemade) | D65: BV008 | E65: Fresh Lime | F65: Kg | G65: 0.3 | H65: =G65*IFERROR(INDEX('Item Master'!$E$4:$E$41,MATCH(D65,'Item Master'!$A$4:$A$41,0)),0) -> 30 | N65: =G65*$M$66 -> 1.575
A66: SR010 | C66: TOTAL - Mojito Syrup Base (Homemade) | D66: TOTAL | H66: =SUM(H63:H65) -> 75 | I66: 20 | J66: Servings (50ml) | K66: =IFERROR(H66/I66,0) -> 3.75 | L66: =SUMIF('Recipe Master'!$D$4:$D$146,A66,'Recipe Master'!$J$4:$J$146) -> 105 | M66: =IFERROR(L66/I66,0) -> 5.25

Sheet Purchase Register
A1: PURCHASE REGISTER
A2: What was bought, from whom, at what cost — feeds the Main Store
A3: Enter each purchase event's date in row 3 above its Qty/Cost/Total block. | F3: 46206 | I3: 46218 | L3: Insert Date | O3: Insert Date | R3: Insert Date | U3: Insert Date | X3: Insert Date | AA3: Insert Date | AD3: Insert Date
A4: ITEM CODE | B4: ITEM NAME | C4: CATEGORY | D4: UOM | E4: OPENING AVG. COST | F4: P1 Qty | G4: P1 Cost | H4: P1 Total | I4: P2 Qty | J4: P2 Cost | K4: P2 Total | L4: P3 Qty | M4: P3 Cost | N4: P3 Total | O4: P4 Qty | P4: P4 Cost | Q4: P4 Total | R4: P5 Qty | S4: P5 Cost | T4: P5 Total | U4: P6 Qty | V4: P6 Cost | W4: P6 Total | X4: P7 Qty | Y4: P7 Cost | Z4: P7 Total | AA4: P8 Qty | AB4: P8 Cost | AC4: P8 Total | AD4: P9 Qty | AE4: P9 Cost | AF4: P9 Total | AG4: TOTAL QTY | AH4: TOTAL COST | AI4: AVG. COST
A5: FOOD
A6: FD001 | B6: Beef Mince (80% Lean) | C6: Meat & Poultry | D6: Kg | E6: ='Item Master'!E5 -> 550 | F6: 45 | G6: 555 | H6: =IFERROR(F6*G6,0) -> 24975 | I6: 40 | J6: 560 | K6: =IFERROR(I6*J6,0) -> 22400 | N6: =IFERROR(L6*M6,0) -> 0 | Q6: =IFERROR(O6*P6,0) -> 0 | T6: =IFERROR(R6*S6,0) -> 0 | W6: =IFERROR(U6*V6,0) -> 0 | Z6: =IFERROR(X6*Y6,0) -> 0 | AC6: =IFERROR(AA6*AB6,0) -> 0 | AF6: =IFERROR(AD6*AE6,0) -> 0 | AG6: =F6+I6+L6+O6+R6+U6+X6+AA6+AD6 -> 85 | AH6: =H6+K6+N6+Q6+T6+W6+Z6+AC6+AF6 -> 47375 | AI6: =IFERROR(AH6/AG6,E6) -> 557.35294
A7: FD002 | B7: Chicken Breast (Boneless) | C7: Meat & Poultry | D7: Kg | E7: ='Item Master'!E6 -> 480 | F7: 40 | G7: 485 | H7: =IFERROR(F7*G7,0) -> 19400 | I7: 35 | J7: 480 | K7: =IFERROR(I7*J7,0) -> 16800 | N7: =IFERROR(L7*M7,0) -> 0 | Q7: =IFERROR(O7*P7,0) -> 0 | T7: =IFERROR(R7*S7,0) -> 0 | W7: =IFERROR(U7*V7,0) -> 0 | Z7: =IFERROR(X7*Y7,0) -> 0 | AC7: =IFERROR(AA7*AB7,0) -> 0 | AF7: =IFERROR(AD7*AE7,0) -> 0 | AG7: =F7+I7+L7+O7+R7+U7+X7+AA7+AD7 -> 75 | AH7: =H7+K7+N7+Q7+T7+W7+Z7+AC7+AF7 -> 36200 | AI7: =IFERROR(AH7/AG7,E7) -> 482.66667
A8: FD003 | B8: Bacon Strips | C8: Meat & Poultry | D8: Kg | E8: ='Item Master'!E7 -> 650 | F8: 20 | G8: 650 | H8: =IFERROR(F8*G8,0) -> 13000 | K8: =IFERROR(I8*J8,0) -> 0 | N8: =IFERROR(L8*M8,0) -> 0 | Q8: =IFERROR(O8*P8,0) -> 0 | T8: =IFERROR(R8*S8,0) -> 0 | W8: =IFERROR(U8*V8,0) -> 0 | Z8: =IFERROR(X8*Y8,0) -> 0 | AC8: =IFERROR(AA8*AB8,0) -> 0 | AF8: =IFERROR(AD8*AE8,0) -> 0 | AG8: =F8+I8+L8+O8+R8+U8+X8+AA8+AD8 -> 20 | AH8: =H8+K8+N8+Q8+T8+W8+Z8+AC8+AF8 -> 13000 | AI8: =IFERROR(AH8/AG8,E8) -> 650
A9: FD004 | B9: Fresh Lettuce | C9: Fresh Produce | D9: Kg | E9: ='Item Master'!E8 -> 60 | F9: 25 | G9: 58 | H9: =IFERROR(F9*G9,0) -> 1450 | I9: 25 | J9: 62 | K9: =IFERROR(I9*J9,0) -> 1550 | N9: =IFERROR(L9*M9,0) -> 0 | Q9: =IFERROR(O9*P9,0) -> 0 | T9: =IFERROR(R9*S9,0) -> 0 | W9: =IFERROR(U9*V9,0) -> 0 | Z9: =IFERROR(X9*Y9,0) -> 0 | AC9: =IFERROR(AA9*AB9,0) -> 0 | AF9: =IFERROR(AD9*AE9,0) -> 0 | AG9: =F9+I9+L9+O9+R9+U9+X9+AA9+AD9 -> 50 | AH9: =H9+K9+N9+Q9+T9+W9+Z9+AC9+AF9 -> 3000 | AI9: =IFERROR(AH9/AG9,E9) -> 60
A10: FD005 | B10: Fresh Tomato | C10: Fresh Produce | D10: Kg | E10: ='Item Master'!E9 -> 55 | F10: 25 | G10: 55 | H10: =IFERROR(F10*G10,0) -> 1375 | I10: 25 | J10: 57 | K10: =IFERROR(I10*J10,0) -> 1425 | N10: =IFERROR(L10*M10,0) -> 0 | Q10: =IFERROR(O10*P10,0) -> 0 | T10: =IFERROR(R10*S10,0) -> 0 | W10: =IFERROR(U10*V10,0) -> 0 | Z10: =IFERROR(X10*Y10,0) -> 0 | AC10: =IFERROR(AA10*AB10,0) -> 0 | AF10: =IFERROR(AD10*AE10,0) -> 0 | AG10: =F10+I10+L10+O10+R10+U10+X10+AA10+AD10 -> 50 | AH10: =H10+K10+N10+Q10+T10+W10+Z10+AC10+AF10 -> 2800 | AI10: =IFERROR(AH10/AG10,E10) -> 56
A11: FD006 | B11: Onion | C11: Fresh Produce | D11: Kg | E11: ='Item Master'!E10 -> 40 | F11: 25 | G11: 40 | H11: =IFERROR(F11*G11,0) -> 1000 | K11: =IFERROR(I11*J11,0) -> 0 | N11: =IFERROR(L11*M11,0) -> 0 | Q11: =IFERROR(O11*P11,0) -> 0 | T11: =IFERROR(R11*S11,0) -> 0 | W11: =IFERROR(U11*V11,0) -> 0 | Z11: =IFERROR(X11*Y11,0) -> 0 | AC11: =IFERROR(AA11*AB11,0) -> 0 | AF11: =IFERROR(AD11*AE11,0) -> 0 | AG11: =F11+I11+L11+O11+R11+U11+X11+AA11+AD11 -> 25 | AH11: =H11+K11+N11+Q11+T11+W11+Z11+AC11+AF11 -> 1000 | AI11: =IFERROR(AH11/AG11,E11) -> 40
A12: FD007 | B12: Cheddar Cheese Slice | C12: Dairy | D12: Pcs | E12: ='Item Master'!E11 -> 12 | F12: 150 | G12: 12 | H12: =IFERROR(F12*G12,0) -> 1800 | K12: =IFERROR(I12*J12,0) -> 0 | N12: =IFERROR(L12*M12,0) -> 0 | Q12: =IFERROR(O12*P12,0) -> 0 | T12: =IFERROR(R12*S12,0) -> 0 | W12: =IFERROR(U12*V12,0) -> 0 | Z12: =IFERROR(X12*Y12,0) -> 0 | AC12: =IFERROR(AA12*AB12,0) -> 0 | AF12: =IFERROR(AD12*AE12,0) -> 0 | AG12: =F12+I12+L12+O12+R12+U12+X12+AA12+AD12 -> 150 | AH12: =H12+K12+N12+Q12+T12+W12+Z12+AC12+AF12 -> 1800 | AI12: =IFERROR(AH12/AG12,E12) -> 12
A13: FD008 | B13: All-Purpose Flour | C13: Bakery & Dry Goods | D13: Kg | E13: ='Item Master'!E12 -> 55 | F13: 60 | G13: 55 | H13: =IFERROR(F13*G13,0) -> 3300 | K13: =IFERROR(I13*J13,0) -> 0 | N13: =IFERROR(L13*M13,0) -> 0 | Q13: =IFERROR(O13*P13,0) -> 0 | T13: =IFERROR(R13*S13,0) -> 0 | W13: =IFERROR(U13*V13,0) -> 0 | Z13: =IFERROR(X13*Y13,0) -> 0 | AC13: =IFERROR(AA13*AB13,0) -> 0 | AF13: =IFERROR(AD13*AE13,0) -> 0 | AG13: =F13+I13+L13+O13+R13+U13+X13+AA13+AD13 -> 60 | AH13: =H13+K13+N13+Q13+T13+W13+Z13+AC13+AF13 -> 3300 | AI13: =IFERROR(AH13/AG13,E13) -> 55
A14: FD009 | B14: Butter (Unsalted) | C14: Dairy | D14: Kg | E14: ='Item Master'!E13 -> 480 | F14: 20 | G14: 480 | H14: =IFERROR(F14*G14,0) -> 9600 | K14: =IFERROR(I14*J14,0) -> 0 | N14: =IFERROR(L14*M14,0) -> 0 | Q14: =IFERROR(O14*P14,0) -> 0 | T14: =IFERROR(R14*S14,0) -> 0 | W14: =IFERROR(U14*V14,0) -> 0 | Z14: =IFERROR(X14*Y14,0) -> 0 | AC14: =IFERROR(AA14*AB14,0) -> 0 | AF14: =IFERROR(AD14*AE14,0) -> 0 | AG14: =F14+I14+L14+O14+R14+U14+X14+AA14+AD14 -> 20 | AH14: =H14+K14+N14+Q14+T14+W14+Z14+AC14+AF14 -> 9600 | AI14: =IFERROR(AH14/AG14,E14) -> 480
A15: FD010 | B15: Fresh Eggs | C15: Dairy | D15: Pcs | E15: ='Item Master'!E14 -> 8 | F15: 150 | G15: 8 | H15: =IFERROR(F15*G15,0) -> 1200 | K15: =IFERROR(I15*J15,0) -> 0 | N15: =IFERROR(L15*M15,0) -> 0 | Q15: =IFERROR(O15*P15,0) -> 0 | T15: =IFERROR(R15*S15,0) -> 0 | W15: =IFERROR(U15*V15,0) -> 0 | Z15: =IFERROR(X15*Y15,0) -> 0 | AC15: =IFERROR(AA15*AB15,0) -> 0 | AF15: =IFERROR(AD15*AE15,0) -> 0 | AG15: =F15+I15+L15+O15+R15+U15+X15+AA15+AD15 -> 150 | AH15: =H15+K15+N15+Q15+T15+W15+Z15+AC15+AF15 -> 1200 | AI15: =IFERROR(AH15/AG15,E15) -> 8
A16: FD011 | B16: Spaghetti Pasta | C16: Bakery & Dry Goods | D16: Kg | E16: ='Item Master'!E15 -> 120 | F16: 35 | G16: 120 | H16: =IFERROR(F16*G16,0) -> 4200 | K16: =IFERROR(I16*J16,0) -> 0 | N16: =IFERROR(L16*M16,0) -> 0 | Q16: =IFERROR(O16*P16,0) -> 0 | T16: =IFERROR(R16*S16,0) -> 0 | W16: =IFERROR(U16*V16,0) -> 0 | Z16: =IFERROR(X16*Y16,0) -> 0 | AC16: =IFERROR(AA16*AB16,0) -> 0 | AF16: =IFERROR(AD16*AE16,0) -> 0 | AG16: =F16+I16+L16+O16+R16+U16+X16+AA16+AD16 -> 35 | AH16: =H16+K16+N16+Q16+T16+W16+Z16+AC16+AF16 -> 4200 | AI16: =IFERROR(AH16/AG16,E16) -> 120
A17: FD012 | B17: Tortilla Wrap | C17: Bakery & Dry Goods | D17: Pcs | E17: ='Item Master'!E16 -> 15 | F17: 90 | G17: 15 | H17: =IFERROR(F17*G17,0) -> 1350 | K17: =IFERROR(I17*J17,0) -> 0 | N17: =IFERROR(L17*M17,0) -> 0 | Q17: =IFERROR(O17*P17,0) -> 0 | T17: =IFERROR(R17*S17,0) -> 0 | W17: =IFERROR(U17*V17,0) -> 0 | Z17: =IFERROR(X17*Y17,0) -> 0 | AC17: =IFERROR(AA17*AB17,0) -> 0 | AF17: =IFERROR(AD17*AE17,0) -> 0 | AG17: =F17+I17+L17+O17+R17+U17+X17+AA17+AD17 -> 90 | AH17: =H17+K17+N17+Q17+T17+W17+Z17+AC17+AF17 -> 1350 | AI17: =IFERROR(AH17/AG17,E17) -> 15
A18: FD013 | B18: Mayonnaise | C18: Condiments & Sauces | D18: Kg | E18: ='Item Master'!E17 -> 220 | F18: 35 | G18: 220 | H18: =IFERROR(F18*G18,0) -> 7700 | K18: =IFERROR(I18*J18,0) -> 0 | N18: =IFERROR(L18*M18,0) -> 0 | Q18: =IFERROR(O18*P18,0) -> 0 | T18: =IFERROR(R18*S18,0) -> 0 | W18: =IFERROR(U18*V18,0) -> 0 | Z18: =IFERROR(X18*Y18,0) -> 0 | AC18: =IFERROR(AA18*AB18,0) -> 0 | AF18: =IFERROR(AD18*AE18,0) -> 0 | AG18: =F18+I18+L18+O18+R18+U18+X18+AA18+AD18 -> 35 | AH18: =H18+K18+N18+Q18+T18+W18+Z18+AC18+AF18 -> 7700 | AI18: =IFERROR(AH18/AG18,E18) -> 220
A19: FD014 | B19: Tomato Ketchup | C19: Condiments & Sauces | D19: Kg | E19: ='Item Master'!E18 -> 180 | F19: 35 | G19: 180 | H19: =IFERROR(F19*G19,0) -> 6300 | K19: =IFERROR(I19*J19,0) -> 0 | N19: =IFERROR(L19*M19,0) -> 0 | Q19: =IFERROR(O19*P19,0) -> 0 | T19: =IFERROR(R19*S19,0) -> 0 | W19: =IFERROR(U19*V19,0) -> 0 | Z19: =IFERROR(X19*Y19,0) -> 0 | AC19: =IFERROR(AA19*AB19,0) -> 0 | AF19: =IFERROR(AD19*AE19,0) -> 0 | AG19: =F19+I19+L19+O19+R19+U19+X19+AA19+AD19 -> 35 | AH19: =H19+K19+N19+Q19+T19+W19+Z19+AC19+AF19 -> 6300 | AI19: =IFERROR(AH19/AG19,E19) -> 180
A20: FD015 | B20: Mozzarella Cheese | C20: Dairy | D20: Kg | E20: ='Item Master'!E19 -> 620 | F20: 25 | G20: 620 | H20: =IFERROR(F20*G20,0) -> 15500 | K20: =IFERROR(I20*J20,0) -> 0 | N20: =IFERROR(L20*M20,0) -> 0 | Q20: =IFERROR(O20*P20,0) -> 0 | T20: =IFERROR(R20*S20,0) -> 0 | W20: =IFERROR(U20*V20,0) -> 0 | Z20: =IFERROR(X20*Y20,0) -> 0 | AC20: =IFERROR(AA20*AB20,0) -> 0 | AF20: =IFERROR(AD20*AE20,0) -> 0 | AG20: =F20+I20+L20+O20+R20+U20+X20+AA20+AD20 -> 25 | AH20: =H20+K20+N20+Q20+T20+W20+Z20+AC20+AF20 -> 15500 | AI20: =IFERROR(AH20/AG20,E20) -> 620
A21: BEVERAGE
A22: BV001 | B22: Coffee Beans (Roasted) | C22: Coffee & Tea | D22: Kg | E22: ='Item Master'!E21 -> 900 | F22: 25 | G22: 900 | H22: =IFERROR(F22*G22,0) -> 22500 | K22: =IFERROR(I22*J22,0) -> 0 | N22: =IFERROR(L22*M22,0) -> 0 | Q22: =IFERROR(O22*P22,0) -> 0 | T22: =IFERROR(R22*S22,0) -> 0 | W22: =IFERROR(U22*V22,0) -> 0 | Z22: =IFERROR(X22*Y22,0) -> 0 | AC22: =IFERROR(AA22*AB22,0) -> 0 | AF22: =IFERROR(AD22*AE22,0) -> 0 | AG22: =F22+I22+L22+O22+R22+U22+X22+AA22+AD22 -> 25 | AH22: =H22+K22+N22+Q22+T22+W22+Z22+AC22+AF22 -> 22500 | AI22: =IFERROR(AH22/AG22,E22) -> 900
A23: BV002 | B23: Black Tea Bags | C23: Coffee & Tea | D23: Pcs | E23: ='Item Master'!E22 -> 3 | H23: =IFERROR(F23*G23,0) -> 0 | K23: =IFERROR(I23*J23,0) -> 0 | N23: =IFERROR(L23*M23,0) -> 0 | Q23: =IFERROR(O23*P23,0) -> 0 | T23: =IFERROR(R23*S23,0) -> 0 | W23: =IFERROR(U23*V23,0) -> 0 | Z23: =IFERROR(X23*Y23,0) -> 0 | AC23: =IFERROR(AA23*AB23,0) -> 0 | AF23: =IFERROR(AD23*AE23,0) -> 0 | AG23: =F23+I23+L23+O23+R23+U23+X23+AA23+AD23 -> 0 | AH23: =H23+K23+N23+Q23+T23+W23+Z23+AC23+AF23 -> 0 | AI23: =IFERROR(AH23/AG23,E23) -> 3
A24: BV003 | B24: Green Tea Bags | C24: Coffee & Tea | D24: Pcs | E24: ='Item Master'!E23 -> 4 | H24: =IFERROR(F24*G24,0) -> 0 | K24: =IFERROR(I24*J24,0) -> 0 | N24: =IFERROR(L24*M24,0) -> 0 | Q24: =IFERROR(O24*P24,0) -> 0 | T24: =IFERROR(R24*S24,0) -> 0 | W24: =IFERROR(U24*V24,0) -> 0 | Z24: =IFERROR(X24*Y24,0) -> 0 | AC24: =IFERROR(AA24*AB24,0) -> 0 | AF24: =IFERROR(AD24*AE24,0) -> 0 | AG24: =F24+I24+L24+O24+R24+U24+X24+AA24+AD24 -> 0 | AH24: =H24+K24+N24+Q24+T24+W24+Z24+AC24+AF24 -> 0 | AI24: =IFERROR(AH24/AG24,E24) -> 4
A25: BV004 | B25: Fresh Milk | C25: Dairy & Bar | D25: Ltr | E25: ='Item Master'!E24 -> 65 | F25: 70 | G25: 65 | H25: =IFERROR(F25*G25,0) -> 4550 | I25: 60 | J25: 66 | K25: =IFERROR(I25*J25,0) -> 3960 | N25: =IFERROR(L25*M25,0) -> 0 | Q25: =IFERROR(O25*P25,0) -> 0 | T25: =IFERROR(R25*S25,0) -> 0 | W25: =IFERROR(U25*V25,0) -> 0 | Z25: =IFERROR(X25*Y25,0) -> 0 | AC25: =IFERROR(AA25*AB25,0) -> 0 | AF25: =IFERROR(AD25*AE25,0) -> 0 | AG25: =F25+I25+L25+O25+R25+U25+X25+AA25+AD25 -> 130 | AH25: =H25+K25+N25+Q25+T25+W25+Z25+AC25+AF25 -> 8510 | AI25: =IFERROR(AH25/AG25,E25) -> 65.461538
A26: BV005 | B26: Cocoa Powder | C26: Coffee & Tea | D26: Kg | E26: ='Item Master'!E25 -> 350 | H26: =IFERROR(F26*G26,0) -> 0 | K26: =IFERROR(I26*J26,0) -> 0 | N26: =IFERROR(L26*M26,0) -> 0 | Q26: =IFERROR(O26*P26,0) -> 0 | T26: =IFERROR(R26*S26,0) -> 0 | W26: =IFERROR(U26*V26,0) -> 0 | Z26: =IFERROR(X26*Y26,0) -> 0 | AC26: =IFERROR(AA26*AB26,0) -> 0 | AF26: =IFERROR(AD26*AE26,0) -> 0 | AG26: =F26+I26+L26+O26+R26+U26+X26+AA26+AD26 -> 0 | AH26: =H26+K26+N26+Q26+T26+W26+Z26+AC26+AF26 -> 0 | AI26: =IFERROR(AH26/AG26,E26) -> 350
A27: BV006 | B27: White Rum | C27: Bar & Spirits | D27: Ltr | E27: ='Item Master'!E26 -> 950 | F27: 12 | G27: 950 | H27: =IFERROR(F27*G27,0) -> 11400 | K27: =IFERROR(I27*J27,0) -> 0 | N27: =IFERROR(L27*M27,0) -> 0 | Q27: =IFERROR(O27*P27,0) -> 0 | T27: =IFERROR(R27*S27,0) -> 0 | W27: =IFERROR(U27*V27,0) -> 0 | Z27: =IFERROR(X27*Y27,0) -> 0 | AC27: =IFERROR(AA27*AB27,0) -> 0 | AF27: =IFERROR(AD27*AE27,0) -> 0 | AG27: =F27+I27+L27+O27+R27+U27+X27+AA27+AD27 -> 12 | AH27: =H27+K27+N27+Q27+T27+W27+Z27+AC27+AF27 -> 11400 | AI27: =IFERROR(AH27/AG27,E27) -> 950
A28: BV007 | B28: Fresh Mint Leaves | C28: Bar Garnish | D28: Kg | E28: ='Item Master'!E27 -> 150 | H28: =IFERROR(F28*G28,0) -> 0 | K28: =IFERROR(I28*J28,0) -> 0 | N28: =IFERROR(L28*M28,0) -> 0 | Q28: =IFERROR(O28*P28,0) -> 0 | T28: =IFERROR(R28*S28,0) -> 0 | W28: =IFERROR(U28*V28,0) -> 0 | Z28: =IFERROR(X28*Y28,0) -> 0 | AC28: =IFERROR(AA28*AB28,0) -> 0 | AF28: =IFERROR(AD28*AE28,0) -> 0 | AG28: =F28+I28+L28+O28+R28+U28+X28+AA28+AD28 -> 0 | AH28: =H28+K28+N28+Q28+T28+W28+Z28+AC28+AF28 -> 0 | AI28: =IFERROR(AH28/AG28,E28) -> 150
A29: BV008 | B29: Fresh Lime | C29: Bar Garnish | D29: Kg | E29: ='Item Master'!E28 -> 100 | F29: 12 | G29: 100 | H29: =IFERROR(F29*G29,0) -> 1200 | K29: =IFERROR(I29*J29,0) -> 0 | N29: =IFERROR(L29*M29,0) -> 0 | Q29: =IFERROR(O29*P29,0) -> 0 | T29: =IFERROR(R29*S29,0) -> 0 | W29: =IFERROR(U29*V29,0) -> 0 | Z29: =IFERROR(X29*Y29,0) -> 0 | AC29: =IFERROR(AA29*AB29,0) -> 0 | AF29: =IFERROR(AD29*AE29,0) -> 0 | AG29: =F29+I29+L29+O29+R29+U29+X29+AA29+AD29 -> 12 | AH29: =H29+K29+N29+Q29+T29+W29+Z29+AC29+AF29 -> 1200 | AI29: =IFERROR(AH29/AG29,E29) -> 100
A30: BV009 | B30: Fresh Avocado | C30: Fresh Produce | D30: Kg | E30: ='Item Master'!E29 -> 90 | F30: 20 | G30: 90 | H30: =IFERROR(F30*G30,0) -> 1800 | K30: =IFERROR(I30*J30,0) -> 0 | N30: =IFERROR(L30*M30,0) -> 0 | Q30: =IFERROR(O30*P30,0) -> 0 | T30: =IFERROR(R30*S30,0) -> 0 | W30: =IFERROR(U30*V30,0) -> 0 | Z30: =IFERROR(X30*Y30,0) -> 0 | AC30: =IFERROR(AA30*AB30,0) -> 0 | AF30: =IFERROR(AD30*AE30,0) -> 0 | AG30: =F30+I30+L30+O30+R30+U30+X30+AA30+AD30 -> 20 | AH30: =H30+K30+N30+Q30+T30+W30+Z30+AC30+AF30 -> 1800 | AI30: =IFERROR(AH30/AG30,E30) -> 90
A31: BV010 | B31: Soda Water | C31: Bar & Mixers | D31: Ltr | E31: ='Item Master'!E30 -> 45 | F31: 35 | G31: 45 | H31: =IFERROR(F31*G31,0) -> 1575 | K31: =IFERROR(I31*J31,0) -> 0 | N31: =IFERROR(L31*M31,0) -> 0 | Q31: =IFERROR(O31*P31,0) -> 0 | T31: =IFERROR(R31*S31,0) -> 0 | W31: =IFERROR(U31*V31,0) -> 0 | Z31: =IFERROR(X31*Y31,0) -> 0 | AC31: =IFERROR(AA31*AB31,0) -> 0 | AF31: =IFERROR(AD31*AE31,0) -> 0 | AG31: =F31+I31+L31+O31+R31+U31+X31+AA31+AD31 -> 35 | AH31: =H31+K31+N31+Q31+T31+W31+Z31+AC31+AF31 -> 1575 | AI31: =IFERROR(AH31/AG31,E31) -> 45
A32: BV011 | B32: Coca-Cola (330ml Bottle) | C32: Soft Drinks | D32: Bottle | E32: ='Item Master'!E31 -> 35 | F32: 220 | G32: 35 | H32: =IFERROR(F32*G32,0) -> 7700 | K32: =IFERROR(I32*J32,0) -> 0 | N32: =IFERROR(L32*M32,0) -> 0 | Q32: =IFERROR(O32*P32,0) -> 0 | T32: =IFERROR(R32*S32,0) -> 0 | W32: =IFERROR(U32*V32,0) -> 0 | Z32: =IFERROR(X32*Y32,0) -> 0 | AC32: =IFERROR(AA32*AB32,0) -> 0 | AF32: =IFERROR(AD32*AE32,0) -> 0 | AG32: =F32+I32+L32+O32+R32+U32+X32+AA32+AD32 -> 220 | AH32: =H32+K32+N32+Q32+T32+W32+Z32+AC32+AF32 -> 7700 | AI32: =IFERROR(AH32/AG32,E32) -> 35
A33: OTHERS
A34: OT001 | B34: Burger Takeaway Box | C34: Packaging | D34: Pcs | E34: ='Item Master'!E33 -> 8 | F34: 400 | G34: 8 | H34: =IFERROR(F34*G34,0) -> 3200 | K34: =IFERROR(I34*J34,0) -> 0 | N34: =IFERROR(L34*M34,0) -> 0 | Q34: =IFERROR(O34*P34,0) -> 0 | T34: =IFERROR(R34*S34,0) -> 0 | W34: =IFERROR(U34*V34,0) -> 0 | Z34: =IFERROR(X34*Y34,0) -> 0 | AC34: =IFERROR(AA34*AB34,0) -> 0 | AF34: =IFERROR(AD34*AE34,0) -> 0 | AG34: =F34+I34+L34+O34+R34+U34+X34+AA34+AD34 -> 400 | AH34: =H34+K34+N34+Q34+T34+W34+Z34+AC34+AF34 -> 3200 | AI34: =IFERROR(AH34/AG34,E34) -> 8
A35: OT002 | B35: Pizza Takeaway Box | C35: Packaging | D35: Pcs | E35: ='Item Master'!E34 -> 15 | F35: 300 | G35: 15 | H35: =IFERROR(F35*G35,0) -> 4500 | K35: =IFERROR(I35*J35,0) -> 0 | N35: =IFERROR(L35*M35,0) -> 0 | Q35: =IFERROR(O35*P35,0) -> 0 | T35: =IFERROR(R35*S35,0) -> 0 | W35: =IFERROR(U35*V35,0) -> 0 | Z35: =IFERROR(X35*Y35,0) -> 0 | AC35: =IFERROR(AA35*AB35,0) -> 0 | AF35: =IFERROR(AD35*AE35,0) -> 0 | AG35: =F35+I35+L35+O35+R35+U35+X35+AA35+AD35 -> 300 | AH35: =H35+K35+N35+Q35+T35+W35+Z35+AC35+AF35 -> 4500 | AI35: =IFERROR(AH35/AG35,E35) -> 15
A36: OT003 | B36: Paper Napkins | C36: Consumables | D36: Pcs | E36: ='Item Master'!E35 -> 1 | H36: =IFERROR(F36*G36,0) -> 0 | K36: =IFERROR(I36*J36,0) -> 0 | N36: =IFERROR(L36*M36,0) -> 0 | Q36: =IFERROR(O36*P36,0) -> 0 | T36: =IFERROR(R36*S36,0) -> 0 | W36: =IFERROR(U36*V36,0) -> 0 | Z36: =IFERROR(X36*Y36,0) -> 0 | AC36: =IFERROR(AA36*AB36,0) -> 0 | AF36: =IFERROR(AD36*AE36,0) -> 0 | AG36: =F36+I36+L36+O36+R36+U36+X36+AA36+AD36 -> 0 | AH36: =H36+K36+N36+Q36+T36+W36+Z36+AC36+AF36 -> 0 | AI36: =IFERROR(AH36/AG36,E36) -> 1
A37: OT004 | B37: Disposable Straws | C37: Consumables | D37: Pcs | E37: ='Item Master'!E36 -> 1 | H37: =IFERROR(F37*G37,0) -> 0 | K37: =IFERROR(I37*J37,0) -> 0 | N37: =IFERROR(L37*M37,0) -> 0 | Q37: =IFERROR(O37*P37,0) -> 0 | T37: =IFERROR(R37*S37,0) -> 0 | W37: =IFERROR(U37*V37,0) -> 0 | Z37: =IFERROR(X37*Y37,0) -> 0 | AC37: =IFERROR(AA37*AB37,0) -> 0 | AF37: =IFERROR(AD37*AE37,0) -> 0 | AG37: =F37+I37+L37+O37+R37+U37+X37+AA37+AD37 -> 0 | AH37: =H37+K37+N37+Q37+T37+W37+Z37+AC37+AF37 -> 0 | AI37: =IFERROR(AH37/AG37,E37) -> 1
A38: OT005 | B38: White Sugar | C38: Pantry & Dry Goods | D38: Kg | E38: ='Item Master'!E37 -> 60 | F38: 45 | G38: 60 | H38: =IFERROR(F38*G38,0) -> 2700 | K38: =IFERROR(I38*J38,0) -> 0 | N38: =IFERROR(L38*M38,0) -> 0 | Q38: =IFERROR(O38*P38,0) -> 0 | T38: =IFERROR(R38*S38,0) -> 0 | W38: =IFERROR(U38*V38,0) -> 0 | Z38: =IFERROR(X38*Y38,0) -> 0 | AC38: =IFERROR(AA38*AB38,0) -> 0 | AF38: =IFERROR(AD38*AE38,0) -> 0 | AG38: =F38+I38+L38+O38+R38+U38+X38+AA38+AD38 -> 45 | AH38: =H38+K38+N38+Q38+T38+W38+Z38+AC38+AF38 -> 2700 | AI38: =IFERROR(AH38/AG38,E38) -> 60
A39: OT006 | B39: Iodized Salt | C39: Pantry & Dry Goods | D39: Kg | E39: ='Item Master'!E38 -> 25 | H39: =IFERROR(F39*G39,0) -> 0 | K39: =IFERROR(I39*J39,0) -> 0 | N39: =IFERROR(L39*M39,0) -> 0 | Q39: =IFERROR(O39*P39,0) -> 0 | T39: =IFERROR(R39*S39,0) -> 0 | W39: =IFERROR(U39*V39,0) -> 0 | Z39: =IFERROR(X39*Y39,0) -> 0 | AC39: =IFERROR(AA39*AB39,0) -> 0 | AF39: =IFERROR(AD39*AE39,0) -> 0 | AG39: =F39+I39+L39+O39+R39+U39+X39+AA39+AD39 -> 0 | AH39: =H39+K39+N39+Q39+T39+W39+Z39+AC39+AF39 -> 0 | AI39: =IFERROR(AH39/AG39,E39) -> 25
A40: OT007 | B40: Cooking / Vegetable Oil | C40: Pantry & Dry Goods | D40: Ltr | E40: ='Item Master'!E39 -> 150 | F40: 45 | G40: 150 | H40: =IFERROR(F40*G40,0) -> 6750 | K40: =IFERROR(I40*J40,0) -> 0 | N40: =IFERROR(L40*M40,0) -> 0 | Q40: =IFERROR(O40*P40,0) -> 0 | T40: =IFERROR(R40*S40,0) -> 0 | W40: =IFERROR(U40*V40,0) -> 0 | Z40: =IFERROR(X40*Y40,0) -> 0 | AC40: =IFERROR(AA40*AB40,0) -> 0 | AF40: =IFERROR(AD40*AE40,0) -> 0 | AG40: =F40+I40+L40+O40+R40+U40+X40+AA40+AD40 -> 45 | AH40: =H40+K40+N40+Q40+T40+W40+Z40+AC40+AF40 -> 6750 | AI40: =IFERROR(AH40/AG40,E40) -> 150
A41: OT008 | B41: Instant Dry Yeast | C41: Pantry & Dry Goods | D41: Kg | E41: ='Item Master'!E40 -> 400 | F41: 12 | G41: 400 | H41: =IFERROR(F41*G41,0) -> 4800 | K41: =IFERROR(I41*J41,0) -> 0 | N41: =IFERROR(L41*M41,0) -> 0 | Q41: =IFERROR(O41*P41,0) -> 0 | T41: =IFERROR(R41*S41,0) -> 0 | W41: =IFERROR(U41*V41,0) -> 0 | Z41: =IFERROR(X41*Y41,0) -> 0 | AC41: =IFERROR(AA41*AB41,0) -> 0 | AF41: =IFERROR(AD41*AE41,0) -> 0 | AG41: =F41+I41+L41+O41+R41+U41+X41+AA41+AD41 -> 12 | AH41: =H41+K41+N41+Q41+T41+W41+Z41+AC41+AF41 -> 4800 | AI41: =IFERROR(AH41/AG41,E41) -> 400
A42: OT009 | B42: Black Pepper (Ground) | C42: Pantry & Dry Goods | D42: Kg | E42: ='Item Master'!E41 -> 500 | H42: =IFERROR(F42*G42,0) -> 0 | K42: =IFERROR(I42*J42,0) -> 0 | N42: =IFERROR(L42*M42,0) -> 0 | Q42: =IFERROR(O42*P42,0) -> 0 | T42: =IFERROR(R42*S42,0) -> 0 | W42: =IFERROR(U42*V42,0) -> 0 | Z42: =IFERROR(X42*Y42,0) -> 0 | AC42: =IFERROR(AA42*AB42,0) -> 0 | AF42: =IFERROR(AD42*AE42,0) -> 0 | AG42: =F42+I42+L42+O42+R42+U42+X42+AA42+AD42 -> 0 | AH42: =H42+K42+N42+Q42+T42+W42+Z42+AC42+AF42 -> 0 | AI42: =IFERROR(AH42/AG42,E42) -> 500

Sheet Store Receiving
A1: STORE RECEIVING
A2: Goods received into the Main Store — builds available stock & moving-average cost
H3: 46206 | K3: 46218 | N3: Insert Date | Q3: Insert Date | T3: Insert Date | W3: Insert Date | Z3: Insert Date | AC3: Insert Date | AF3: Insert Date
A4: ITEM CODE | B4: ITEM NAME | C4: CATEGORY | D4: UOM | E4: Beginning Qty | F4: Beginning Cost | G4: Beginning Value | H4: R1 Qty | I4: R1 Cost | J4: R1 Total | K4: R2 Qty | L4: R2 Cost | M4: R2 Total | N4: R3 Qty | O4: R3 Cost | P4: R3 Total | Q4: R4 Qty | R4: R4 Cost | S4: R4 Total | T4: R5 Qty | U4: R5 Cost | V4: R5 Total | W4: R6 Qty | X4: R6 Cost | Y4: R6 Total | Z4: R7 Qty | AA4: R7 Cost | AB4: R7 Total | AC4: R8 Qty | AD4: R8 Cost | AE4: R8 Total | AF4: R9 Qty | AG4: R9 Cost | AH4: R9 Total | AI4: Total Received Qty | AJ4: Available Qty | AK4: Average Cost | AL4: Total Store Value
A5: FOOD
A6: FD001 | B6: Beef Mince (80% Lean) | C6: Meat & Poultry | D6: Kg | E6: 0 | F6: ='Item Master'!E5 -> 550 | G6: =E6*F6 -> 0 | H6: 45 | I6: 555 | J6: =IFERROR(H6*I6,0) -> 24975 | K6: 40 | L6: 560 | M6: =IFERROR(K6*L6,0) -> 22400 | P6: =IFERROR(N6*O6,0) -> 0 | S6: =IFERROR(Q6*R6,0) -> 0 | V6: =IFERROR(T6*U6,0) -> 0 | Y6: =IFERROR(W6*X6,0) -> 0 | AB6: =IFERROR(Z6*AA6,0) -> 0 | AE6: =IFERROR(AC6*AD6,0) -> 0 | AH6: =IFERROR(AF6*AG6,0) -> 0 | AI6: =H6+K6+N6+Q6+T6+W6+Z6+AC6+AF6 -> 85 | AJ6: =E6+AI6 -> 85 | AK6: =IFERROR((G6+J6+M6+P6+S6+V6+Y6+AB6+AE6+AH6)/AJ6,F6) -> 557.35294 | AL6: =AJ6*AK6 -> 47375
A7: FD002 | B7: Chicken Breast (Boneless) | C7: Meat & Poultry | D7: Kg | E7: 0 | F7: ='Item Master'!E6 -> 480 | G7: =E7*F7 -> 0 | H7: 40 | I7: 485 | J7: =IFERROR(H7*I7,0) -> 19400 | K7: 35 | L7: 480 | M7: =IFERROR(K7*L7,0) -> 16800 | P7: =IFERROR(N7*O7,0) -> 0 | S7: =IFERROR(Q7*R7,0) -> 0 | V7: =IFERROR(T7*U7,0) -> 0 | Y7: =IFERROR(W7*X7,0) -> 0 | AB7: =IFERROR(Z7*AA7,0) -> 0 | AE7: =IFERROR(AC7*AD7,0) -> 0 | AH7: =IFERROR(AF7*AG7,0) -> 0 | AI7: =H7+K7+N7+Q7+T7+W7+Z7+AC7+AF7 -> 75 | AJ7: =E7+AI7 -> 75 | AK7: =IFERROR((G7+J7+M7+P7+S7+V7+Y7+AB7+AE7+AH7)/AJ7,F7) -> 482.66667 | AL7: =AJ7*AK7 -> 36200
A8: FD003 | B8: Bacon Strips | C8: Meat & Poultry | D8: Kg | E8: 0 | F8: ='Item Master'!E7 -> 650 | G8: =E8*F8 -> 0 | H8: 20 | I8: 650 | J8: =IFERROR(H8*I8,0) -> 13000 | M8: =IFERROR(K8*L8,0) -> 0 | P8: =IFERROR(N8*O8,0) -> 0 | S8: =IFERROR(Q8*R8,0) -> 0 | V8: =IFERROR(T8*U8,0) -> 0 | Y8: =IFERROR(W8*X8,0) -> 0 | AB8: =IFERROR(Z8*AA8,0) -> 0 | AE8: =IFERROR(AC8*AD8,0) -> 0 | AH8: =IFERROR(AF8*AG8,0) -> 0 | AI8: =H8+K8+N8+Q8+T8+W8+Z8+AC8+AF8 -> 20 | AJ8: =E8+AI8 -> 20 | AK8: =IFERROR((G8+J8+M8+P8+S8+V8+Y8+AB8+AE8+AH8)/AJ8,F8) -> 650 | AL8: =AJ8*AK8 -> 13000
A9: FD004 | B9: Fresh Lettuce | C9: Fresh Produce | D9: Kg | E9: 0 | F9: ='Item Master'!E8 -> 60 | G9: =E9*F9 -> 0 | H9: 25 | I9: 58 | J9: =IFERROR(H9*I9,0) -> 1450 | K9: 25 | L9: 62 | M9: =IFERROR(K9*L9,0) -> 1550 | P9: =IFERROR(N9*O9,0) -> 0 | S9: =IFERROR(Q9*R9,0) -> 0 | V9: =IFERROR(T9*U9,0) -> 0 | Y9: =IFERROR(W9*X9,0) -> 0 | AB9: =IFERROR(Z9*AA9,0) -> 0 | AE9: =IFERROR(AC9*AD9,0) -> 0 | AH9: =IFERROR(AF9*AG9,0) -> 0 | AI9: =H9+K9+N9+Q9+T9+W9+Z9+AC9+AF9 -> 50 | AJ9: =E9+AI9 -> 50 | AK9: =IFERROR((G9+J9+M9+P9+S9+V9+Y9+AB9+AE9+AH9)/AJ9,F9) -> 60 | AL9: =AJ9*AK9 -> 3000
A10: FD005 | B10: Fresh Tomato | C10: Fresh Produce | D10: Kg | E10: 0 | F10: ='Item Master'!E9 -> 55 | G10: =E10*F10 -> 0 | H10: 25 | I10: 55 | J10: =IFERROR(H10*I10,0) -> 1375 | K10: 25 | L10: 57 | M10: =IFERROR(K10*L10,0) -> 1425 | P10: =IFERROR(N10*O10,0) -> 0 | S10: =IFERROR(Q10*R10,0) -> 0 | V10: =IFERROR(T10*U10,0) -> 0 | Y10: =IFERROR(W10*X10,0) -> 0 | AB10: =IFERROR(Z10*AA10,0) -> 0 | AE10: =IFERROR(AC10*AD10,0) -> 0 | AH10: =IFERROR(AF10*AG10,0) -> 0 | AI10: =H10+K10+N10+Q10+T10+W10+Z10+AC10+AF10 -> 50 | AJ10: =E10+AI10 -> 50 | AK10: =IFERROR((G10+J10+M10+P10+S10+V10+Y10+AB10+AE10+AH10)/AJ10,F10) -> 56 | AL10: =AJ10*AK10 -> 2800
A11: FD006 | B11: Onion | C11: Fresh Produce | D11: Kg | E11: 0 | F11: ='Item Master'!E10 -> 40 | G11: =E11*F11 -> 0 | H11: 25 | I11: 40 | J11: =IFERROR(H11*I11,0) -> 1000 | M11: =IFERROR(K11*L11,0) -> 0 | P11: =IFERROR(N11*O11,0) -> 0 | S11: =IFERROR(Q11*R11,0) -> 0 | V11: =IFERROR(T11*U11,0) -> 0 | Y11: =IFERROR(W11*X11,0) -> 0 | AB11: =IFERROR(Z11*AA11,0) -> 0 | AE11: =IFERROR(AC11*AD11,0) -> 0 | AH11: =IFERROR(AF11*AG11,0) -> 0 | AI11: =H11+K11+N11+Q11+T11+W11+Z11+AC11+AF11 -> 25 | AJ11: =E11+AI11 -> 25 | AK11: =IFERROR((G11+J11+M11+P11+S11+V11+Y11+AB11+AE11+AH11)/AJ11,F11) -> 40 | AL11: =AJ11*AK11 -> 1000
A12: FD007 | B12: Cheddar Cheese Slice | C12: Dairy | D12: Pcs | E12: 0 | F12: ='Item Master'!E11 -> 12 | G12: =E12*F12 -> 0 | H12: 150 | I12: 12 | J12: =IFERROR(H12*I12,0) -> 1800 | M12: =IFERROR(K12*L12,0) -> 0 | P12: =IFERROR(N12*O12,0) -> 0 | S12: =IFERROR(Q12*R12,0) -> 0 | V12: =IFERROR(T12*U12,0) -> 0 | Y12: =IFERROR(W12*X12,0) -> 0 | AB12: =IFERROR(Z12*AA12,0) -> 0 | AE12: =IFERROR(AC12*AD12,0) -> 0 | AH12: =IFERROR(AF12*AG12,0) -> 0 | AI12: =H12+K12+N12+Q12+T12+W12+Z12+AC12+AF12 -> 150 | AJ12: =E12+AI12 -> 150 | AK12: =IFERROR((G12+J12+M12+P12+S12+V12+Y12+AB12+AE12+AH12)/AJ12,F12) -> 12 | AL12: =AJ12*AK12 -> 1800
A13: FD008 | B13: All-Purpose Flour | C13: Bakery & Dry Goods | D13: Kg | E13: 0 | F13: ='Item Master'!E12 -> 55 | G13: =E13*F13 -> 0 | H13: 60 | I13: 55 | J13: =IFERROR(H13*I13,0) -> 3300 | M13: =IFERROR(K13*L13,0) -> 0 | P13: =IFERROR(N13*O13,0) -> 0 | S13: =IFERROR(Q13*R13,0) -> 0 | V13: =IFERROR(T13*U13,0) -> 0 | Y13: =IFERROR(W13*X13,0) -> 0 | AB13: =IFERROR(Z13*AA13,0) -> 0 | AE13: =IFERROR(AC13*AD13,0) -> 0 | AH13: =IFERROR(AF13*AG13,0) -> 0 | AI13: =H13+K13+N13+Q13+T13+W13+Z13+AC13+AF13 -> 60 | AJ13: =E13+AI13 -> 60 | AK13: =IFERROR((G13+J13+M13+P13+S13+V13+Y13+AB13+AE13+AH13)/AJ13,F13) -> 55 | AL13: =AJ13*AK13 -> 3300
A14: FD009 | B14: Butter (Unsalted) | C14: Dairy | D14: Kg | E14: 0 | F14: ='Item Master'!E13 -> 480 | G14: =E14*F14 -> 0 | H14: 20 | I14: 480 | J14: =IFERROR(H14*I14,0) -> 9600 | M14: =IFERROR(K14*L14,0) -> 0 | P14: =IFERROR(N14*O14,0) -> 0 | S14: =IFERROR(Q14*R14,0) -> 0 | V14: =IFERROR(T14*U14,0) -> 0 | Y14: =IFERROR(W14*X14,0) -> 0 | AB14: =IFERROR(Z14*AA14,0) -> 0 | AE14: =IFERROR(AC14*AD14,0) -> 0 | AH14: =IFERROR(AF14*AG14,0) -> 0 | AI14: =H14+K14+N14+Q14+T14+W14+Z14+AC14+AF14 -> 20 | AJ14: =E14+AI14 -> 20 | AK14: =IFERROR((G14+J14+M14+P14+S14+V14+Y14+AB14+AE14+AH14)/AJ14,F14) -> 480 | AL14: =AJ14*AK14 -> 9600
A15: FD010 | B15: Fresh Eggs | C15: Dairy | D15: Pcs | E15: 0 | F15: ='Item Master'!E14 -> 8 | G15: =E15*F15 -> 0 | H15: 150 | I15: 8 | J15: =IFERROR(H15*I15,0) -> 1200 | M15: =IFERROR(K15*L15,0) -> 0 | P15: =IFERROR(N15*O15,0) -> 0 | S15: =IFERROR(Q15*R15,0) -> 0 | V15: =IFERROR(T15*U15,0) -> 0 | Y15: =IFERROR(W15*X15,0) -> 0 | AB15: =IFERROR(Z15*AA15,0) -> 0 | AE15: =IFERROR(AC15*AD15,0) -> 0 | AH15: =IFERROR(AF15*AG15,0) -> 0 | AI15: =H15+K15+N15+Q15+T15+W15+Z15+AC15+AF15 -> 150 | AJ15: =E15+AI15 -> 150 | AK15: =IFERROR((G15+J15+M15+P15+S15+V15+Y15+AB15+AE15+AH15)/AJ15,F15) -> 8 | AL15: =AJ15*AK15 -> 1200
A16: FD011 | B16: Spaghetti Pasta | C16: Bakery & Dry Goods | D16: Kg | E16: 0 | F16: ='Item Master'!E15 -> 120 | G16: =E16*F16 -> 0 | H16: 35 | I16: 120 | J16: =IFERROR(H16*I16,0) -> 4200 | M16: =IFERROR(K16*L16,0) -> 0 | P16: =IFERROR(N16*O16,0) -> 0 | S16: =IFERROR(Q16*R16,0) -> 0 | V16: =IFERROR(T16*U16,0) -> 0 | Y16: =IFERROR(W16*X16,0) -> 0 | AB16: =IFERROR(Z16*AA16,0) -> 0 | AE16: =IFERROR(AC16*AD16,0) -> 0 | AH16: =IFERROR(AF16*AG16,0) -> 0 | AI16: =H16+K16+N16+Q16+T16+W16+Z16+AC16+AF16 -> 35 | AJ16: =E16+AI16 -> 35 | AK16: =IFERROR((G16+J16+M16+P16+S16+V16+Y16+AB16+AE16+AH16)/AJ16,F16) -> 120 | AL16: =AJ16*AK16 -> 4200
A17: FD012 | B17: Tortilla Wrap | C17: Bakery & Dry Goods | D17: Pcs | E17: 0 | F17: ='Item Master'!E16 -> 15 | G17: =E17*F17 -> 0 | H17: 90 | I17: 15 | J17: =IFERROR(H17*I17,0) -> 1350 | M17: =IFERROR(K17*L17,0) -> 0 | P17: =IFERROR(N17*O17,0) -> 0 | S17: =IFERROR(Q17*R17,0) -> 0 | V17: =IFERROR(T17*U17,0) -> 0 | Y17: =IFERROR(W17*X17,0) -> 0 | AB17: =IFERROR(Z17*AA17,0) -> 0 | AE17: =IFERROR(AC17*AD17,0) -> 0 | AH17: =IFERROR(AF17*AG17,0) -> 0 | AI17: =H17+K17+N17+Q17+T17+W17+Z17+AC17+AF17 -> 90 | AJ17: =E17+AI17 -> 90 | AK17: =IFERROR((G17+J17+M17+P17+S17+V17+Y17+AB17+AE17+AH17)/AJ17,F17) -> 15 | AL17: =AJ17*AK17 -> 1350
A18: FD013 | B18: Mayonnaise | C18: Condiments & Sauces | D18: Kg | E18: 0 | F18: ='Item Master'!E17 -> 220 | G18: =E18*F18 -> 0 | H18: 35 | I18: 220 | J18: =IFERROR(H18*I18,0) -> 7700 | M18: =IFERROR(K18*L18,0) -> 0 | P18: =IFERROR(N18*O18,0) -> 0 | S18: =IFERROR(Q18*R18,0) -> 0 | V18: =IFERROR(T18*U18,0) -> 0 | Y18: =IFERROR(W18*X18,0) -> 0 | AB18: =IFERROR(Z18*AA18,0) -> 0 | AE18: =IFERROR(AC18*AD18,0) -> 0 | AH18: =IFERROR(AF18*AG18,0) -> 0 | AI18: =H18+K18+N18+Q18+T18+W18+Z18+AC18+AF18 -> 35 | AJ18: =E18+AI18 -> 35 | AK18: =IFERROR((G18+J18+M18+P18+S18+V18+Y18+AB18+AE18+AH18)/AJ18,F18) -> 220 | AL18: =AJ18*AK18 -> 7700
A19: FD014 | B19: Tomato Ketchup | C19: Condiments & Sauces | D19: Kg | E19: 0 | F19: ='Item Master'!E18 -> 180 | G19: =E19*F19 -> 0 | H19: 35 | I19: 180 | J19: =IFERROR(H19*I19,0) -> 6300 | M19: =IFERROR(K19*L19,0) -> 0 | P19: =IFERROR(N19*O19,0) -> 0 | S19: =IFERROR(Q19*R19,0) -> 0 | V19: =IFERROR(T19*U19,0) -> 0 | Y19: =IFERROR(W19*X19,0) -> 0 | AB19: =IFERROR(Z19*AA19,0) -> 0 | AE19: =IFERROR(AC19*AD19,0) -> 0 | AH19: =IFERROR(AF19*AG19,0) -> 0 | AI19: =H19+K19+N19+Q19+T19+W19+Z19+AC19+AF19 -> 35 | AJ19: =E19+AI19 -> 35 | AK19: =IFERROR((G19+J19+M19+P19+S19+V19+Y19+AB19+AE19+AH19)/AJ19,F19) -> 180 | AL19: =AJ19*AK19 -> 6300
A20: FD015 | B20: Mozzarella Cheese | C20: Dairy | D20: Kg | E20: 0 | F20: ='Item Master'!E19 -> 620 | G20: =E20*F20 -> 0 | H20: 25 | I20: 620 | J20: =IFERROR(H20*I20,0) -> 15500 | M20: =IFERROR(K20*L20,0) -> 0 | P20: =IFERROR(N20*O20,0) -> 0 | S20: =IFERROR(Q20*R20,0) -> 0 | V20: =IFERROR(T20*U20,0) -> 0 | Y20: =IFERROR(W20*X20,0) -> 0 | AB20: =IFERROR(Z20*AA20,0) -> 0 | AE20: =IFERROR(AC20*AD20,0) -> 0 | AH20: =IFERROR(AF20*AG20,0) -> 0 | AI20: =H20+K20+N20+Q20+T20+W20+Z20+AC20+AF20 -> 25 | AJ20: =E20+AI20 -> 25 | AK20: =IFERROR((G20+J20+M20+P20+S20+V20+Y20+AB20+AE20+AH20)/AJ20,F20) -> 620 | AL20: =AJ20*AK20 -> 15500
A21: BEVERAGE
A22: BV001 | B22: Coffee Beans (Roasted) | C22: Coffee & Tea | D22: Kg | E22: 0 | F22: ='Item Master'!E21 -> 900 | G22: =E22*F22 -> 0 | H22: 25 | I22: 900 | J22: =IFERROR(H22*I22,0) -> 22500 | M22: =IFERROR(K22*L22,0) -> 0 | P22: =IFERROR(N22*O22,0) -> 0 | S22: =IFERROR(Q22*R22,0) -> 0 | V22: =IFERROR(T22*U22,0) -> 0 | Y22: =IFERROR(W22*X22,0) -> 0 | AB22: =IFERROR(Z22*AA22,0) -> 0 | AE22: =IFERROR(AC22*AD22,0) -> 0 | AH22: =IFERROR(AF22*AG22,0) -> 0 | AI22: =H22+K22+N22+Q22+T22+W22+Z22+AC22+AF22 -> 25 | AJ22: =E22+AI22 -> 25 | AK22: =IFERROR((G22+J22+M22+P22+S22+V22+Y22+AB22+AE22+AH22)/AJ22,F22) -> 900 | AL22: =AJ22*AK22 -> 22500
A23: BV002 | B23: Black Tea Bags | C23: Coffee & Tea | D23: Pcs | E23: 0 | F23: ='Item Master'!E22 -> 3 | G23: =E23*F23 -> 0 | J23: =IFERROR(H23*I23,0) -> 0 | M23: =IFERROR(K23*L23,0) -> 0 | P23: =IFERROR(N23*O23,0) -> 0 | S23: =IFERROR(Q23*R23,0) -> 0 | V23: =IFERROR(T23*U23,0) -> 0 | Y23: =IFERROR(W23*X23,0) -> 0 | AB23: =IFERROR(Z23*AA23,0) -> 0 | AE23: =IFERROR(AC23*AD23,0) -> 0 | AH23: =IFERROR(AF23*AG23,0) -> 0 | AI23: =H23+K23+N23+Q23+T23+W23+Z23+AC23+AF23 -> 0 | AJ23: =E23+AI23 -> 0 | AK23: =IFERROR((G23+J23+M23+P23+S23+V23+Y23+AB23+AE23+AH23)/AJ23,F23) -> 3 | AL23: =AJ23*AK23 -> 0
A24: BV003 | B24: Green Tea Bags | C24: Coffee & Tea | D24: Pcs | E24: 0 | F24: ='Item Master'!E23 -> 4 | G24: =E24*F24 -> 0 | J24: =IFERROR(H24*I24,0) -> 0 | M24: =IFERROR(K24*L24,0) -> 0 | P24: =IFERROR(N24*O24,0) -> 0 | S24: =IFERROR(Q24*R24,0) -> 0 | V24: =IFERROR(T24*U24,0) -> 0 | Y24: =IFERROR(W24*X24,0) -> 0 | AB24: =IFERROR(Z24*AA24,0) -> 0 | AE24: =IFERROR(AC24*AD24,0) -> 0 | AH24: =IFERROR(AF24*AG24,0) -> 0 | AI24: =H24+K24+N24+Q24+T24+W24+Z24+AC24+AF24 -> 0 | AJ24: =E24+AI24 -> 0 | AK24: =IFERROR((G24+J24+M24+P24+S24+V24+Y24+AB24+AE24+AH24)/AJ24,F24) -> 4 | AL24: =AJ24*AK24 -> 0
A25: BV004 | B25: Fresh Milk | C25: Dairy & Bar | D25: Ltr | E25: 0 | F25: ='Item Master'!E24 -> 65 | G25: =E25*F25 -> 0 | H25: 70 | I25: 65 | J25: =IFERROR(H25*I25,0) -> 4550 | K25: 60 | L25: 66 | M25: =IFERROR(K25*L25,0) -> 3960 | P25: =IFERROR(N25*O25,0) -> 0 | S25: =IFERROR(Q25*R25,0) -> 0 | V25: =IFERROR(T25*U25,0) -> 0 | Y25: =IFERROR(W25*X25,0) -> 0 | AB25: =IFERROR(Z25*AA25,0) -> 0 | AE25: =IFERROR(AC25*AD25,0) -> 0 | AH25: =IFERROR(AF25*AG25,0) -> 0 | AI25: =H25+K25+N25+Q25+T25+W25+Z25+AC25+AF25 -> 130 | AJ25: =E25+AI25 -> 130 | AK25: =IFERROR((G25+J25+M25+P25+S25+V25+Y25+AB25+AE25+AH25)/AJ25,F25) -> 65.461538 | AL25: =AJ25*AK25 -> 8510
A26: BV005 | B26: Cocoa Powder | C26: Coffee & Tea | D26: Kg | E26: 0 | F26: ='Item Master'!E25 -> 350 | G26: =E26*F26 -> 0 | J26: =IFERROR(H26*I26,0) -> 0 | M26: =IFERROR(K26*L26,0) -> 0 | P26: =IFERROR(N26*O26,0) -> 0 | S26: =IFERROR(Q26*R26,0) -> 0 | V26: =IFERROR(T26*U26,0) -> 0 | Y26: =IFERROR(W26*X26,0) -> 0 | AB26: =IFERROR(Z26*AA26,0) -> 0 | AE26: =IFERROR(AC26*AD26,0) -> 0 | AH26: =IFERROR(AF26*AG26,0) -> 0 | AI26: =H26+K26+N26+Q26+T26+W26+Z26+AC26+AF26 -> 0 | AJ26: =E26+AI26 -> 0 | AK26: =IFERROR((G26+J26+M26+P26+S26+V26+Y26+AB26+AE26+AH26)/AJ26,F26) -> 350 | AL26: =AJ26*AK26 -> 0
A27: BV006 | B27: White Rum | C27: Bar & Spirits | D27: Ltr | E27: 0 | F27: ='Item Master'!E26 -> 950 | G27: =E27*F27 -> 0 | H27: 12 | I27: 950 | J27: =IFERROR(H27*I27,0) -> 11400 | M27: =IFERROR(K27*L27,0) -> 0 | P27: =IFERROR(N27*O27,0) -> 0 | S27: =IFERROR(Q27*R27,0) -> 0 | V27: =IFERROR(T27*U27,0) -> 0 | Y27: =IFERROR(W27*X27,0) -> 0 | AB27: =IFERROR(Z27*AA27,0) -> 0 | AE27: =IFERROR(AC27*AD27,0) -> 0 | AH27: =IFERROR(AF27*AG27,0) -> 0 | AI27: =H27+K27+N27+Q27+T27+W27+Z27+AC27+AF27 -> 12 | AJ27: =E27+AI27 -> 12 | AK27: =IFERROR((G27+J27+M27+P27+S27+V27+Y27+AB27+AE27+AH27)/AJ27,F27) -> 950 | AL27: =AJ27*AK27 -> 11400
A28: BV007 | B28: Fresh Mint Leaves | C28: Bar Garnish | D28: Kg | E28: 0 | F28: ='Item Master'!E27 -> 150 | G28: =E28*F28 -> 0 | J28: =IFERROR(H28*I28,0) -> 0 | M28: =IFERROR(K28*L28,0) -> 0 | P28: =IFERROR(N28*O28,0) -> 0 | S28: =IFERROR(Q28*R28,0) -> 0 | V28: =IFERROR(T28*U28,0) -> 0 | Y28: =IFERROR(W28*X28,0) -> 0 | AB28: =IFERROR(Z28*AA28,0) -> 0 | AE28: =IFERROR(AC28*AD28,0) -> 0 | AH28: =IFERROR(AF28*AG28,0) -> 0 | AI28: =H28+K28+N28+Q28+T28+W28+Z28+AC28+AF28 -> 0 | AJ28: =E28+AI28 -> 0 | AK28: =IFERROR((G28+J28+M28+P28+S28+V28+Y28+AB28+AE28+AH28)/AJ28,F28) -> 150 | AL28: =AJ28*AK28 -> 0
A29: BV008 | B29: Fresh Lime | C29: Bar Garnish | D29: Kg | E29: 0 | F29: ='Item Master'!E28 -> 100 | G29: =E29*F29 -> 0 | H29: 12 | I29: 100 | J29: =IFERROR(H29*I29,0) -> 1200 | M29: =IFERROR(K29*L29,0) -> 0 | P29: =IFERROR(N29*O29,0) -> 0 | S29: =IFERROR(Q29*R29,0) -> 0 | V29: =IFERROR(T29*U29,0) -> 0 | Y29: =IFERROR(W29*X29,0) -> 0 | AB29: =IFERROR(Z29*AA29,0) -> 0 | AE29: =IFERROR(AC29*AD29,0) -> 0 | AH29: =IFERROR(AF29*AG29,0) -> 0 | AI29: =H29+K29+N29+Q29+T29+W29+Z29+AC29+AF29 -> 12 | AJ29: =E29+AI29 -> 12 | AK29: =IFERROR((G29+J29+M29+P29+S29+V29+Y29+AB29+AE29+AH29)/AJ29,F29) -> 100 | AL29: =AJ29*AK29 -> 1200
A30: BV009 | B30: Fresh Avocado | C30: Fresh Produce | D30: Kg | E30: 0 | F30: ='Item Master'!E29 -> 90 | G30: =E30*F30 -> 0 | H30: 20 | I30: 90 | J30: =IFERROR(H30*I30,0) -> 1800 | M30: =IFERROR(K30*L30,0) -> 0 | P30: =IFERROR(N30*O30,0) -> 0 | S30: =IFERROR(Q30*R30,0) -> 0 | V30: =IFERROR(T30*U30,0) -> 0 | Y30: =IFERROR(W30*X30,0) -> 0 | AB30: =IFERROR(Z30*AA30,0) -> 0 | AE30: =IFERROR(AC30*AD30,0) -> 0 | AH30: =IFERROR(AF30*AG30,0) -> 0 | AI30: =H30+K30+N30+Q30+T30+W30+Z30+AC30+AF30 -> 20 | AJ30: =E30+AI30 -> 20 | AK30: =IFERROR((G30+J30+M30+P30+S30+V30+Y30+AB30+AE30+AH30)/AJ30,F30) -> 90 | AL30: =AJ30*AK30 -> 1800
A31: BV010 | B31: Soda Water | C31: Bar & Mixers | D31: Ltr | E31: 0 | F31: ='Item Master'!E30 -> 45 | G31: =E31*F31 -> 0 | H31: 35 | I31: 45 | J31: =IFERROR(H31*I31,0) -> 1575 | M31: =IFERROR(K31*L31,0) -> 0 | P31: =IFERROR(N31*O31,0) -> 0 | S31: =IFERROR(Q31*R31,0) -> 0 | V31: =IFERROR(T31*U31,0) -> 0 | Y31: =IFERROR(W31*X31,0) -> 0 | AB31: =IFERROR(Z31*AA31,0) -> 0 | AE31: =IFERROR(AC31*AD31,0) -> 0 | AH31: =IFERROR(AF31*AG31,0) -> 0 | AI31: =H31+K31+N31+Q31+T31+W31+Z31+AC31+AF31 -> 35 | AJ31: =E31+AI31 -> 35 | AK31: =IFERROR((G31+J31+M31+P31+S31+V31+Y31+AB31+AE31+AH31)/AJ31,F31) -> 45 | AL31: =AJ31*AK31 -> 1575
A32: BV011 | B32: Coca-Cola (330ml Bottle) | C32: Soft Drinks | D32: Bottle | E32: 0 | F32: ='Item Master'!E31 -> 35 | G32: =E32*F32 -> 0 | H32: 220 | I32: 35 | J32: =IFERROR(H32*I32,0) -> 7700 | M32: =IFERROR(K32*L32,0) -> 0 | P32: =IFERROR(N32*O32,0) -> 0 | S32: =IFERROR(Q32*R32,0) -> 0 | V32: =IFERROR(T32*U32,0) -> 0 | Y32: =IFERROR(W32*X32,0) -> 0 | AB32: =IFERROR(Z32*AA32,0) -> 0 | AE32: =IFERROR(AC32*AD32,0) -> 0 | AH32: =IFERROR(AF32*AG32,0) -> 0 | AI32: =H32+K32+N32+Q32+T32+W32+Z32+AC32+AF32 -> 220 | AJ32: =E32+AI32 -> 220 | AK32: =IFERROR((G32+J32+M32+P32+S32+V32+Y32+AB32+AE32+AH32)/AJ32,F32) -> 35 | AL32: =AJ32*AK32 -> 7700
A33: OTHERS
A34: OT001 | B34: Burger Takeaway Box | C34: Packaging | D34: Pcs | E34: 0 | F34: ='Item Master'!E33 -> 8 | G34: =E34*F34 -> 0 | H34: 400 | I34: 8 | J34: =IFERROR(H34*I34,0) -> 3200 | M34: =IFERROR(K34*L34,0) -> 0 | P34: =IFERROR(N34*O34,0) -> 0 | S34: =IFERROR(Q34*R34,0) -> 0 | V34: =IFERROR(T34*U34,0) -> 0 | Y34: =IFERROR(W34*X34,0) -> 0 | AB34: =IFERROR(Z34*AA34,0) -> 0 | AE34: =IFERROR(AC34*AD34,0) -> 0 | AH34: =IFERROR(AF34*AG34,0) -> 0 | AI34: =H34+K34+N34+Q34+T34+W34+Z34+AC34+AF34 -> 400 | AJ34: =E34+AI34 -> 400 | AK34: =IFERROR((G34+J34+M34+P34+S34+V34+Y34+AB34+AE34+AH34)/AJ34,F34) -> 8 | AL34: =AJ34*AK34 -> 3200
A35: OT002 | B35: Pizza Takeaway Box | C35: Packaging | D35: Pcs | E35: 0 | F35: ='Item Master'!E34 -> 15 | G35: =E35*F35 -> 0 | H35: 300 | I35: 15 | J35: =IFERROR(H35*I35,0) -> 4500 | M35: =IFERROR(K35*L35,0) -> 0 | P35: =IFERROR(N35*O35,0) -> 0 | S35: =IFERROR(Q35*R35,0) -> 0 | V35: =IFERROR(T35*U35,0) -> 0 | Y35: =IFERROR(W35*X35,0) -> 0 | AB35: =IFERROR(Z35*AA35,0) -> 0 | AE35: =IFERROR(AC35*AD35,0) -> 0 | AH35: =IFERROR(AF35*AG35,0) -> 0 | AI35: =H35+K35+N35+Q35+T35+W35+Z35+AC35+AF35 -> 300 | AJ35: =E35+AI35 -> 300 | AK35: =IFERROR((G35+J35+M35+P35+S35+V35+Y35+AB35+AE35+AH35)/AJ35,F35) -> 15 | AL35: =AJ35*AK35 -> 4500
A36: OT003 | B36: Paper Napkins | C36: Consumables | D36: Pcs | E36: 0 | F36: ='Item Master'!E35 -> 1 | G36: =E36*F36 -> 0 | J36: =IFERROR(H36*I36,0) -> 0 | M36: =IFERROR(K36*L36,0) -> 0 | P36: =IFERROR(N36*O36,0) -> 0 | S36: =IFERROR(Q36*R36,0) -> 0 | V36: =IFERROR(T36*U36,0) -> 0 | Y36: =IFERROR(W36*X36,0) -> 0 | AB36: =IFERROR(Z36*AA36,0) -> 0 | AE36: =IFERROR(AC36*AD36,0) -> 0 | AH36: =IFERROR(AF36*AG36,0) -> 0 | AI36: =H36+K36+N36+Q36+T36+W36+Z36+AC36+AF36 -> 0 | AJ36: =E36+AI36 -> 0 | AK36: =IFERROR((G36+J36+M36+P36+S36+V36+Y36+AB36+AE36+AH36)/AJ36,F36) -> 1 | AL36: =AJ36*AK36 -> 0
A37: OT004 | B37: Disposable Straws | C37: Consumables | D37: Pcs | E37: 0 | F37: ='Item Master'!E36 -> 1 | G37: =E37*F37 -> 0 | J37: =IFERROR(H37*I37,0) -> 0 | M37: =IFERROR(K37*L37,0) -> 0 | P37: =IFERROR(N37*O37,0) -> 0 | S37: =IFERROR(Q37*R37,0) -> 0 | V37: =IFERROR(T37*U37,0) -> 0 | Y37: =IFERROR(W37*X37,0) -> 0 | AB37: =IFERROR(Z37*AA37,0) -> 0 | AE37: =IFERROR(AC37*AD37,0) -> 0 | AH37: =IFERROR(AF37*AG37,0) -> 0 | AI37: =H37+K37+N37+Q37+T37+W37+Z37+AC37+AF37 -> 0 | AJ37: =E37+AI37 -> 0 | AK37: =IFERROR((G37+J37+M37+P37+S37+V37+Y37+AB37+AE37+AH37)/AJ37,F37) -> 1 | AL37: =AJ37*AK37 -> 0
A38: OT005 | B38: White Sugar | C38: Pantry & Dry Goods | D38: Kg | E38: 0 | F38: ='Item Master'!E37 -> 60 | G38: =E38*F38 -> 0 | H38: 45 | I38: 60 | J38: =IFERROR(H38*I38,0) -> 2700 | M38: =IFERROR(K38*L38,0) -> 0 | P38: =IFERROR(N38*O38,0) -> 0 | S38: =IFERROR(Q38*R38,0) -> 0 | V38: =IFERROR(T38*U38,0) -> 0 | Y38: =IFERROR(W38*X38,0) -> 0 | AB38: =IFERROR(Z38*AA38,0) -> 0 | AE38: =IFERROR(AC38*AD38,0) -> 0 | AH38: =IFERROR(AF38*AG38,0) -> 0 | AI38: =H38+K38+N38+Q38+T38+W38+Z38+AC38+AF38 -> 45 | AJ38: =E38+AI38 -> 45 | AK38: =IFERROR((G38+J38+M38+P38+S38+V38+Y38+AB38+AE38+AH38)/AJ38,F38) -> 60 | AL38: =AJ38*AK38 -> 2700
A39: OT006 | B39: Iodized Salt | C39: Pantry & Dry Goods | D39: Kg | E39: 0 | F39: ='Item Master'!E38 -> 25 | G39: =E39*F39 -> 0 | J39: =IFERROR(H39*I39,0) -> 0 | M39: =IFERROR(K39*L39,0) -> 0 | P39: =IFERROR(N39*O39,0) -> 0 | S39: =IFERROR(Q39*R39,0) -> 0 | V39: =IFERROR(T39*U39,0) -> 0 | Y39: =IFERROR(W39*X39,0) -> 0 | AB39: =IFERROR(Z39*AA39,0) -> 0 | AE39: =IFERROR(AC39*AD39,0) -> 0 | AH39: =IFERROR(AF39*AG39,0) -> 0 | AI39: =H39+K39+N39+Q39+T39+W39+Z39+AC39+AF39 -> 0 | AJ39: =E39+AI39 -> 0 | AK39: =IFERROR((G39+J39+M39+P39+S39+V39+Y39+AB39+AE39+AH39)/AJ39,F39) -> 25 | AL39: =AJ39*AK39 -> 0
A40: OT007 | B40: Cooking / Vegetable Oil | C40: Pantry & Dry Goods | D40: Ltr | E40: 0 | F40: ='Item Master'!E39 -> 150 | G40: =E40*F40 -> 0 | H40: 45 | I40: 150 | J40: =IFERROR(H40*I40,0) -> 6750 | M40: =IFERROR(K40*L40,0) -> 0 | P40: =IFERROR(N40*O40,0) -> 0 | S40: =IFERROR(Q40*R40,0) -> 0 | V40: =IFERROR(T40*U40,0) -> 0 | Y40: =IFERROR(W40*X40,0) -> 0 | AB40: =IFERROR(Z40*AA40,0) -> 0 | AE40: =IFERROR(AC40*AD40,0) -> 0 | AH40: =IFERROR(AF40*AG40,0) -> 0 | AI40: =H40+K40+N40+Q40+T40+W40+Z40+AC40+AF40 -> 45 | AJ40: =E40+AI40 -> 45 | AK40: =IFERROR((G40+J40+M40+P40+S40+V40+Y40+AB40+AE40+AH40)/AJ40,F40) -> 150 | AL40: =AJ40*AK40 -> 6750
A41: OT008 | B41: Instant Dry Yeast | C41: Pantry & Dry Goods | D41: Kg | E41: 0 | F41: ='Item Master'!E40 -> 400 | G41: =E41*F41 -> 0 | H41: 12 | I41: 400 | J41: =IFERROR(H41*I41,0) -> 4800 | M41: =IFERROR(K41*L41,0) -> 0 | P41: =IFERROR(N41*O41,0) -> 0 | S41: =IFERROR(Q41*R41,0) -> 0 | V41: =IFERROR(T41*U41,0) -> 0 | Y41: =IFERROR(W41*X41,0) -> 0 | AB41: =IFERROR(Z41*AA41,0) -> 0 | AE41: =IFERROR(AC41*AD41,0) -> 0 | AH41: =IFERROR(AF41*AG41,0) -> 0 | AI41: =H41+K41+N41+Q41+T41+W41+Z41+AC41+AF41 -> 12 | AJ41: =E41+AI41 -> 12 | AK41: =IFERROR((G41+J41+M41+P41+S41+V41+Y41+AB41+AE41+AH41)/AJ41,F41) -> 400 | AL41: =AJ41*AK41 -> 4800
A42: OT009 | B42: Black Pepper (Ground) | C42: Pantry & Dry Goods | D42: Kg | E42: 0 | F42: ='Item Master'!E41 -> 500 | G42: =E42*F42 -> 0 | J42: =IFERROR(H42*I42,0) -> 0 | M42: =IFERROR(K42*L42,0) -> 0 | P42: =IFERROR(N42*O42,0) -> 0 | S42: =IFERROR(Q42*R42,0) -> 0 | V42: =IFERROR(T42*U42,0) -> 0 | Y42: =IFERROR(W42*X42,0) -> 0 | AB42: =IFERROR(Z42*AA42,0) -> 0 | AE42: =IFERROR(AC42*AD42,0) -> 0 | AH42: =IFERROR(AF42*AG42,0) -> 0 | AI42: =H42+K42+N42+Q42+T42+W42+Z42+AC42+AF42 -> 0 | AJ42: =E42+AI42 -> 0 | AK42: =IFERROR((G42+J42+M42+P42+S42+V42+Y42+AB42+AE42+AH42)/AJ42,F42) -> 500 | AL42: =AJ42*AK42 -> 0

Sheet Store Inventory
A1: STORE INVENTORY
A2: Main Store balance — Min/Max Par Level with automatic Reorder Status
A3: ITEM CODE | B3: ITEM NAME | C3: CATEGORY | D3: UOM | E3: AVAILABLE QTY | F3: AVERAGE COST | G3: STORE VALUE | H3: MIN PAR LEVEL | I3: MAX PAR LEVEL | J3: REORDER STATUS | K3: DAYS COVER (est.) | L3: REORDER RANK
A4: FOOD
A5: FD001 | B5: Beef Mince (80% Lean) | C5: Meat & Poultry | D5: Kg | E5: ='Store Receiving'!AJ6 -> 85 | F5: ='Store Receiving'!AK6 -> 557.35294 | G5: =E5*F5 -> 47375 | H5: 8 | I5: 25 | J5: =IF(E5<H5,"REORDER NOW",IF(E5>I5,"OVERSTOCK","OK")) -> OVERSTOCK | K5: =IFERROR(E5/(SUMIF('Store Issue'!$A$5:$A$5,A5,'Store Issue'!$P$5:$P$5)/30),0) -> 0 | L5: =IF(J5="REORDER NOW",COUNTIF($J$4:J5,"REORDER NOW"),"")
A6: FD002 | B6: Chicken Breast (Boneless) | C6: Meat & Poultry | D6: Kg | E6: ='Store Receiving'!AJ7 -> 75 | F6: ='Store Receiving'!AK7 -> 482.66667 | G6: =E6*F6 -> 36200 | H6: 8 | I6: 25 | J6: =IF(E6<H6,"REORDER NOW",IF(E6>I6,"OVERSTOCK","OK")) -> OVERSTOCK | K6: =IFERROR(E6/(SUMIF('Store Issue'!$A$5:$A$6,A6,'Store Issue'!$P$5:$P$6)/30),0) -> 0 | L6: =IF(J6="REORDER NOW",COUNTIF($J$4:J6,"REORDER NOW"),"")
A7: FD003 | B7: Bacon Strips | C7: Meat & Poultry | D7: Kg | E7: ='Store Receiving'!AJ8 -> 20 | F7: ='Store Receiving'!AK8 -> 650 | G7: =E7*F7 -> 13000 | H7: 5 | I7: 15 | J7: =IF(E7<H7,"REORDER NOW",IF(E7>I7,"OVERSTOCK","OK")) -> OVERSTOCK | K7: =IFERROR(E7/(SUMIF('Store Issue'!$A$5:$A$7,A7,'Store Issue'!$P$5:$P$7)/30),0) -> 0 | L7: =IF(J7="REORDER NOW",COUNTIF($J$4:J7,"REORDER NOW"),"")
A8: FD004 | B8: Fresh Lettuce | C8: Fresh Produce | D8: Kg | E8: ='Store Receiving'!AJ9 -> 50 | F8: ='Store Receiving'!AK9 -> 60 | G8: =E8*F8 -> 3000 | H8: 5 | I8: 15 | J8: =IF(E8<H8,"REORDER NOW",IF(E8>I8,"OVERSTOCK","OK")) -> OVERSTOCK | K8: =IFERROR(E8/(SUMIF('Store Issue'!$A$5:$A$8,A8,'Store Issue'!$P$5:$P$8)/30),0) -> 0 | L8: =IF(J8="REORDER NOW",COUNTIF($J$4:J8,"REORDER NOW"),"")
A9: FD005 | B9: Fresh Tomato | C9: Fresh Produce | D9: Kg | E9: ='Store Receiving'!AJ10 -> 50 | F9: ='Store Receiving'!AK10 -> 56 | G9: =E9*F9 -> 2800 | H9: 5 | I9: 15 | J9: =IF(E9<H9,"REORDER NOW",IF(E9>I9,"OVERSTOCK","OK")) -> OVERSTOCK | K9: =IFERROR(E9/(SUMIF('Store Issue'!$A$5:$A$9,A9,'Store Issue'!$P$5:$P$9)/30),0) -> 0 | L9: =IF(J9="REORDER NOW",COUNTIF($J$4:J9,"REORDER NOW"),"")
A10: FD006 | B10: Onion | C10: Fresh Produce | D10: Kg | E10: ='Store Receiving'!AJ11 -> 25 | F10: ='Store Receiving'!AK11 -> 40 | G10: =E10*F10 -> 1000 | H10: 5 | I10: 15 | J10: =IF(E10<H10,"REORDER NOW",IF(E10>I10,"OVERSTOCK","OK")) -> OVERSTOCK | K10: =IFERROR(E10/(SUMIF('Store Issue'!$A$5:$A$10,A10,'Store Issue'!$P$5:$P$10)/30),0) -> 0 | L10: =IF(J10="REORDER NOW",COUNTIF($J$4:J10,"REORDER NOW"),"")
A11: FD007 | B11: Cheddar Cheese Slice | C11: Dairy | D11: Pcs | E11: ='Store Receiving'!AJ12 -> 150 | F11: ='Store Receiving'!AK12 -> 12 | G11: =E11*F11 -> 1800 | H11: 20 | I11: 80 | J11: =IF(E11<H11,"REORDER NOW",IF(E11>I11,"OVERSTOCK","OK")) -> OVERSTOCK | K11: =IFERROR(E11/(SUMIF('Store Issue'!$A$5:$A$11,A11,'Store Issue'!$P$5:$P$11)/30),0) -> 0 | L11: =IF(J11="REORDER NOW",COUNTIF($J$4:J11,"REORDER NOW"),"")
A12: FD008 | B12: All-Purpose Flour | C12: Bakery & Dry Goods | D12: Kg | E12: ='Store Receiving'!AJ13 -> 60 | F12: ='Store Receiving'!AK13 -> 55 | G12: =E12*F12 -> 3300 | H12: 10 | I12: 30 | J12: =IF(E12<H12,"REORDER NOW",IF(E12>I12,"OVERSTOCK","OK")) -> OVERSTOCK | K12: =IFERROR(E12/(SUMIF('Store Issue'!$A$5:$A$12,A12,'Store Issue'!$P$5:$P$12)/30),0) -> 0 | L12: =IF(J12="REORDER NOW",COUNTIF($J$4:J12,"REORDER NOW"),"")
A13: FD009 | B13: Butter (Unsalted) | C13: Dairy | D13: Kg | E13: ='Store Receiving'!AJ14 -> 20 | F13: ='Store Receiving'!AK14 -> 480 | G13: =E13*F13 -> 9600 | H13: 3 | I13: 10 | J13: =IF(E13<H13,"REORDER NOW",IF(E13>I13,"OVERSTOCK","OK")) -> OVERSTOCK | K13: =IFERROR(E13/(SUMIF('Store Issue'!$A$5:$A$13,A13,'Store Issue'!$P$5:$P$13)/30),0) -> 0 | L13: =IF(J13="REORDER NOW",COUNTIF($J$4:J13,"REORDER NOW"),"")
A14: FD010 | B14: Fresh Eggs | C14: Dairy | D14: Pcs | E14: ='Store Receiving'!AJ15 -> 150 | F14: ='Store Receiving'!AK15 -> 8 | G14: =E14*F14 -> 1200 | H14: 20 | I14: 80 | J14: =IF(E14<H14,"REORDER NOW",IF(E14>I14,"OVERSTOCK","OK")) -> OVERSTOCK | K14: =IFERROR(E14/(SUMIF('Store Issue'!$A$5:$A$14,A14,'Store Issue'!$P$5:$P$14)/30),0) -> 0 | L14: =IF(J14="REORDER NOW",COUNTIF($J$4:J14,"REORDER NOW"),"")
A15: FD011 | B15: Spaghetti Pasta | C15: Bakery & Dry Goods | D15: Kg | E15: ='Store Receiving'!AJ16 -> 35 | F15: ='Store Receiving'!AK16 -> 120 | G15: =E15*F15 -> 4200 | H15: 10 | I15: 30 | J15: =IF(E15<H15,"REORDER NOW",IF(E15>I15,"OVERSTOCK","OK")) -> OVERSTOCK | K15: =IFERROR(E15/(SUMIF('Store Issue'!$A$5:$A$15,A15,'Store Issue'!$P$5:$P$15)/30),0) -> 0 | L15: =IF(J15="REORDER NOW",COUNTIF($J$4:J15,"REORDER NOW"),"")
A16: FD012 | B16: Tortilla Wrap | C16: Bakery & Dry Goods | D16: Pcs | E16: ='Store Receiving'!AJ17 -> 90 | F16: ='Store Receiving'!AK17 -> 15 | G16: =E16*F16 -> 1350 | H16: 20 | I16: 80 | J16: =IF(E16<H16,"REORDER NOW",IF(E16>I16,"OVERSTOCK","OK")) -> OVERSTOCK | K16: =IFERROR(E16/(SUMIF('Store Issue'!$A$5:$A$16,A16,'Store Issue'!$P$5:$P$16)/30),0) -> 0 | L16: =IF(J16="REORDER NOW",COUNTIF($J$4:J16,"REORDER NOW"),"")
A17: FD013 | B17: Mayonnaise | C17: Condiments & Sauces | D17: Kg | E17: ='Store Receiving'!AJ18 -> 35 | F17: ='Store Receiving'!AK18 -> 220 | G17: =E17*F17 -> 7700 | H17: 10 | I17: 30 | J17: =IF(E17<H17,"REORDER NOW",IF(E17>I17,"OVERSTOCK","OK")) -> OVERSTOCK | K17: =IFERROR(E17/(SUMIF('Store Issue'!$A$5:$A$17,A17,'Store Issue'!$P$5:$P$17)/30),0) -> 0 | L17: =IF(J17="REORDER NOW",COUNTIF($J$4:J17,"REORDER NOW"),"")
A18: FD014 | B18: Tomato Ketchup | C18: Condiments & Sauces | D18: Kg | E18: ='Store Receiving'!AJ19 -> 35 | F18: ='Store Receiving'!AK19 -> 180 | G18: =E18*F18 -> 6300 | H18: 10 | I18: 30 | J18: =IF(E18<H18,"REORDER NOW",IF(E18>I18,"OVERSTOCK","OK")) -> OVERSTOCK | K18: =IFERROR(E18/(SUMIF('Store Issue'!$A$5:$A$18,A18,'Store Issue'!$P$5:$P$18)/30),0) -> 0 | L18: =IF(J18="REORDER NOW",COUNTIF($J$4:J18,"REORDER NOW"),"")
A19: FD015 | B19: Mozzarella Cheese | C19: Dairy | D19: Kg | E19: ='Store Receiving'!AJ20 -> 25 | F19: ='Store Receiving'!AK20 -> 620 | G19: =E19*F19 -> 15500 | H19: 3 | I19: 10 | J19: =IF(E19<H19,"REORDER NOW",IF(E19>I19,"OVERSTOCK","OK")) -> OVERSTOCK | K19: =IFERROR(E19/(SUMIF('Store Issue'!$A$5:$A$19,A19,'Store Issue'!$P$5:$P$19)/30),0) -> 0 | L19: =IF(J19="REORDER NOW",COUNTIF($J$4:J19,"REORDER NOW"),"")
A20: BEVERAGE
A21: BV001 | B21: Coffee Beans (Roasted) | C21: Coffee & Tea | D21: Kg | E21: ='Store Receiving'!AJ22 -> 25 | F21: ='Store Receiving'!AK22 -> 900 | G21: =E21*F21 -> 22500 | H21: 10 | I21: 30 | J21: =IF(E21<H21,"REORDER NOW",IF(E21>I21,"OVERSTOCK","OK")) -> OK | K21: =IFERROR(E21/(SUMIF('Store Issue'!$A$5:$A$21,A21,'Store Issue'!$P$5:$P$21)/30),0) -> 0 | L21: =IF(J21="REORDER NOW",COUNTIF($J$4:J21,"REORDER NOW"),"")
A22: BV002 | B22: Black Tea Bags | C22: Coffee & Tea | D22: Pcs | E22: ='Store Receiving'!AJ23 -> 0 | F22: ='Store Receiving'!AK23 -> 3 | G22: =E22*F22 -> 0 | H22: 20 | I22: 80 | J22: =IF(E22<H22,"REORDER NOW",IF(E22>I22,"OVERSTOCK","OK")) -> REORDER NOW | K22: =IFERROR(E22/(SUMIF('Store Issue'!$A$5:$A$22,A22,'Store Issue'!$P$5:$P$22)/30),0) -> 0 | L22: =IF(J22="REORDER NOW",COUNTIF($J$4:J22,"REORDER NOW"),"") -> 1
A23: BV003 | B23: Green Tea Bags | C23: Coffee & Tea | D23: Pcs | E23: ='Store Receiving'!AJ24 -> 0 | F23: ='Store Receiving'!AK24 -> 4 | G23: =E23*F23 -> 0 | H23: 20 | I23: 80 | J23: =IF(E23<H23,"REORDER NOW",IF(E23>I23,"OVERSTOCK","OK")) -> REORDER NOW | K23: =IFERROR(E23/(SUMIF('Store Issue'!$A$5:$A$23,A23,'Store Issue'!$P$5:$P$23)/30),0) -> 0 | L23: =IF(J23="REORDER NOW",COUNTIF($J$4:J23,"REORDER NOW"),"") -> 2
A24: BV004 | B24: Fresh Milk | C24: Dairy & Bar | D24: Ltr | E24: ='Store Receiving'!AJ25 -> 130 | F24: ='Store Receiving'!AK25 -> 65.461538 | G24: =E24*F24 -> 8510 | H24: 5 | I24: 20 | J24: =IF(E24<H24,"REORDER NOW",IF(E24>I24,"OVERSTOCK","OK")) -> OVERSTOCK | K24: =IFERROR(E24/(SUMIF('Store Issue'!$A$5:$A$24,A24,'Store Issue'!$P$5:$P$24)/30),0) -> 0 | L24: =IF(J24="REORDER NOW",COUNTIF($J$4:J24,"REORDER NOW"),"")
A25: BV005 | B25: Cocoa Powder | C25: Coffee & Tea | D25: Kg | E25: ='Store Receiving'!AJ26 -> 0 | F25: ='Store Receiving'!AK26 -> 350 | G25: =E25*F25 -> 0 | H25: 10 | I25: 30 | J25: =IF(E25<H25,"REORDER NOW",IF(E25>I25,"OVERSTOCK","OK")) -> REORDER NOW | K25: =IFERROR(E25/(SUMIF('Store Issue'!$A$5:$A$25,A25,'Store Issue'!$P$5:$P$25)/30),0) -> 0 | L25: =IF(J25="REORDER NOW",COUNTIF($J$4:J25,"REORDER NOW"),"") -> 3
A26: BV006 | B26: White Rum | C26: Bar & Spirits | D26: Ltr | E26: ='Store Receiving'!AJ27 -> 12 | F26: ='Store Receiving'!AK27 -> 950 | G26: =E26*F26 -> 11400 | H26: 5 | I26: 20 | J26: =IF(E26<H26,"REORDER NOW",IF(E26>I26,"OVERSTOCK","OK")) -> OK | K26: =IFERROR(E26/(SUMIF('Store Issue'!$A$5:$A$26,A26,'Store Issue'!$P$5:$P$26)/30),0) -> 0 | L26: =IF(J26="REORDER NOW",COUNTIF($J$4:J26,"REORDER NOW"),"")
A27: BV007 | B27: Fresh Mint Leaves | C27: Bar Garnish | D27: Kg | E27: ='Store Receiving'!AJ28 -> 0 | F27: ='Store Receiving'!AK28 -> 150 | G27: =E27*F27 -> 0 | H27: 10 | I27: 30 | J27: =IF(E27<H27,"REORDER NOW",IF(E27>I27,"OVERSTOCK","OK")) -> REORDER NOW | K27: =IFERROR(E27/(SUMIF('Store Issue'!$A$5:$A$27,A27,'Store Issue'!$P$5:$P$27)/30),0) -> 0 | L27: =IF(J27="REORDER NOW",COUNTIF($J$4:J27,"REORDER NOW"),"") -> 4
A28: BV008 | B28: Fresh Lime | C28: Bar Garnish | D28: Kg | E28: ='Store Receiving'!AJ29 -> 12 | F28: ='Store Receiving'!AK29 -> 100 | G28: =E28*F28 -> 1200 | H28: 10 | I28: 30 | J28: =IF(E28<H28,"REORDER NOW",IF(E28>I28,"OVERSTOCK","OK")) -> OK | K28: =IFERROR(E28/(SUMIF('Store Issue'!$A$5:$A$28,A28,'Store Issue'!$P$5:$P$28)/30),0) -> 0 | L28: =IF(J28="REORDER NOW",COUNTIF($J$4:J28,"REORDER NOW"),"")
A29: BV009 | B29: Fresh Avocado | C29: Fresh Produce | D29: Kg | E29: ='Store Receiving'!AJ30 -> 20 | F29: ='Store Receiving'!AK30 -> 90 | G29: =E29*F29 -> 1800 | H29: 5 | I29: 15 | J29: =IF(E29<H29,"REORDER NOW",IF(E29>I29,"OVERSTOCK","OK")) -> OVERSTOCK | K29: =IFERROR(E29/(SUMIF('Store Issue'!$A$5:$A$29,A29,'Store Issue'!$P$5:$P$29)/30),0) -> 0 | L29: =IF(J29="REORDER NOW",COUNTIF($J$4:J29,"REORDER NOW"),"")
A30: BV010 | B30: Soda Water | C30: Bar & Mixers | D30: Ltr | E30: ='Store Receiving'!AJ31 -> 35 | F30: ='Store Receiving'!AK31 -> 45 | G30: =E30*F30 -> 1575 | H30: 5 | I30: 20 | J30: =IF(E30<H30,"REORDER NOW",IF(E30>I30,"OVERSTOCK","OK")) -> OVERSTOCK | K30: =IFERROR(E30/(SUMIF('Store Issue'!$A$5:$A$30,A30,'Store Issue'!$P$5:$P$30)/30),0) -> 0 | L30: =IF(J30="REORDER NOW",COUNTIF($J$4:J30,"REORDER NOW"),"")
A31: BV011 | B31: Coca-Cola (330ml Bottle) | C31: Soft Drinks | D31: Bottle | E31: ='Store Receiving'!AJ32 -> 220 | F31: ='Store Receiving'!AK32 -> 35 | G31: =E31*F31 -> 7700 | H31: 24 | I31: 96 | J31: =IF(E31<H31,"REORDER NOW",IF(E31>I31,"OVERSTOCK","OK")) -> OVERSTOCK | K31: =IFERROR(E31/(SUMIF('Store Issue'!$A$5:$A$31,A31,'Store Issue'!$P$5:$P$31)/30),0) -> 0 | L31: =IF(J31="REORDER NOW",COUNTIF($J$4:J31,"REORDER NOW"),"")
A32: OTHERS
A33: OT001 | B33: Burger Takeaway Box | C33: Packaging | D33: Pcs | E33: ='Store Receiving'!AJ34 -> 400 | F33: ='Store Receiving'!AK34 -> 8 | G33: =E33*F33 -> 3200 | H33: 100 | I33: 400 | J33: =IF(E33<H33,"REORDER NOW",IF(E33>I33,"OVERSTOCK","OK")) -> OK | K33: =IFERROR(E33/(SUMIF('Store Issue'!$A$5:$A$33,A33,'Store Issue'!$P$5:$P$33)/30),0) -> 0 | L33: =IF(J33="REORDER NOW",COUNTIF($J$4:J33,"REORDER NOW"),"")
A34: OT002 | B34: Pizza Takeaway Box | C34: Packaging | D34: Pcs | E34: ='Store Receiving'!AJ35 -> 300 | F34: ='Store Receiving'!AK35 -> 15 | G34: =E34*F34 -> 4500 | H34: 100 | I34: 400 | J34: =IF(E34<H34,"REORDER NOW",IF(E34>I34,"OVERSTOCK","OK")) -> OK | K34: =IFERROR(E34/(SUMIF('Store Issue'!$A$5:$A$34,A34,'Store Issue'!$P$5:$P$34)/30),0) -> 0 | L34: =IF(J34="REORDER NOW",COUNTIF($J$4:J34,"REORDER NOW"),"")
A35: OT003 | B35: Paper Napkins | C35: Consumables | D35: Pcs | E35: ='Store Receiving'!AJ36 -> 0 | F35: ='Store Receiving'!AK36 -> 1 | G35: =E35*F35 -> 0 | H35: 100 | I35: 400 | J35: =IF(E35<H35,"REORDER NOW",IF(E35>I35,"OVERSTOCK","OK")) -> REORDER NOW | K35: =IFERROR(E35/(SUMIF('Store Issue'!$A$5:$A$35,A35,'Store Issue'!$P$5:$P$35)/30),0) -> 0 | L35: =IF(J35="REORDER NOW",COUNTIF($J$4:J35,"REORDER NOW"),"") -> 5
A36: OT004 | B36: Disposable Straws | C36: Consumables | D36: Pcs | E36: ='Store Receiving'!AJ37 -> 0 | F36: ='Store Receiving'!AK37 -> 1 | G36: =E36*F36 -> 0 | H36: 100 | I36: 400 | J36: =IF(E36<H36,"REORDER NOW",IF(E36>I36,"OVERSTOCK","OK")) -> REORDER NOW | K36: =IFERROR(E36/(SUMIF('Store Issue'!$A$5:$A$36,A36,'Store Issue'!$P$5:$P$36)/30),0) -> 0 | L36: =IF(J36="REORDER NOW",COUNTIF($J$4:J36,"REORDER NOW"),"") -> 6
A37: OT005 | B37: White Sugar | C37: Pantry & Dry Goods | D37: Kg | E37: ='Store Receiving'!AJ38 -> 45 | F37: ='Store Receiving'!AK38 -> 60 | G37: =E37*F37 -> 2700 | H37: 10 | I37: 30 | J37: =IF(E37<H37,"REORDER NOW",IF(E37>I37,"OVERSTOCK","OK")) -> OVERSTOCK | K37: =IFERROR(E37/(SUMIF('Store Issue'!$A$5:$A$37,A37,'Store Issue'!$P$5:$P$37)/30),0) -> 0 | L37: =IF(J37="REORDER NOW",COUNTIF($J$4:J37,"REORDER NOW"),"")
A38: OT006 | B38: Iodized Salt | C38: Pantry & Dry Goods | D38: Kg | E38: ='Store Receiving'!AJ39 -> 0 | F38: ='Store Receiving'!AK39 -> 25 | G38: =E38*F38 -> 0 | H38: 10 | I38: 30 | J38: =IF(E38<H38,"REORDER NOW",IF(E38>I38,"OVERSTOCK","OK")) -> REORDER NOW | K38: =IFERROR(E38/(SUMIF('Store Issue'!$A$5:$A$38,A38,'Store Issue'!$P$5:$P$38)/30),0) -> 0 | L38: =IF(J38="REORDER NOW",COUNTIF($J$4:J38,"REORDER NOW"),"") -> 7
A39: OT007 | B39: Cooking / Vegetable Oil | C39: Pantry & Dry Goods | D39: Ltr | E39: ='Store Receiving'!AJ40 -> 45 | F39: ='Store Receiving'!AK40 -> 150 | G39: =E39*F39 -> 6750 | H39: 5 | I39: 20 | J39: =IF(E39<H39,"REORDER NOW",IF(E39>I39,"OVERSTOCK","OK")) -> OVERSTOCK | K39: =IFERROR(E39/(SUMIF('Store Issue'!$A$5:$A$39,A39,'Store Issue'!$P$5:$P$39)/30),0) -> 0 | L39: =IF(J39="REORDER NOW",COUNTIF($J$4:J39,"REORDER NOW"),"")
A40: OT008 | B40: Instant Dry Yeast | C40: Pantry & Dry Goods | D40: Kg | E40: ='Store Receiving'!AJ41 -> 12 | F40: ='Store Receiving'!AK41 -> 400 | G40: =E40*F40 -> 4800 | H40: 10 | I40: 30 | J40: =IF(E40<H40,"REORDER NOW",IF(E40>I40,"OVERSTOCK","OK")) -> OK | K40: =IFERROR(E40/(SUMIF('Store Issue'!$A$5:$A$40,A40,'Store Issue'!$P$5:$P$40)/30),0) -> 0 | L40: =IF(J40="REORDER NOW",COUNTIF($J$4:J40,"REORDER NOW"),"")
A41: OT009 | B41: Black Pepper (Ground) | C41: Pantry & Dry Goods | D41: Kg | E41: ='Store Receiving'!AJ42 -> 0 | F41: ='Store Receiving'!AK42 -> 500 | G41: =E41*F41 -> 0 | H41: 10 | I41: 30 | J41: =IF(E41<H41,"REORDER NOW",IF(E41>I41,"OVERSTOCK","OK")) -> REORDER NOW | K41: =IFERROR(E41/(SUMIF('Store Issue'!$A$5:$A$41,A41,'Store Issue'!$P$5:$P$41)/30),0) -> 0 | L41: =IF(J41="REORDER NOW",COUNTIF($J$4:J41,"REORDER NOW"),"") -> 8

Sheet Store Issue
A1: STORE ISSUE
A2: Stock issued from the Main Store to the outlet's Kitchen & Bar
A3: Enter each issue event's date in row 3 above its column; one column = one issue to Kitchen & Bar. | G3: 46207 | H3: 46219 | I3: Insert Date | J3: Insert Date | K3: Insert Date | L3: Insert Date | M3: Insert Date | N3: Insert Date | O3: Insert Date
A4: ITEM CODE | B4: ITEM NAME | C4: CATEGORY | D4: UOM | E4: Available Qty | F4: Average Cost | G4: Issue 1 | H4: Issue 2 | I4: Issue 3 | J4: Issue 4 | K4: Issue 5 | L4: Issue 6 | M4: Issue 7 | N4: Issue 8 | O4: Issue 9 | P4: Total Issued Qty | Q4: Issue Value | R4: Remaining Qty
A5: FOOD
A6: FD001 | B6: Beef Mince (80% Lean) | C6: Meat & Poultry | D6: Kg | E6: ='Store Inventory'!E5 -> 85 | F6: ='Store Inventory'!F5 -> 557.35294 | G6: 20 | H6: 16 | P6: =SUM(G6:O6) -> 36 | Q6: =P6*F6 -> 20064.706 | R6: =E6-P6 -> 49
A7: FD002 | B7: Chicken Breast (Boneless) | C7: Meat & Poultry | D7: Kg | E7: ='Store Inventory'!E6 -> 75 | F7: ='Store Inventory'!F6 -> 482.66667 | G7: 18 | H7: 16 | P7: =SUM(G7:O7) -> 34 | Q7: =P7*F7 -> 16410.667 | R7: =E7-P7 -> 41
A8: FD003 | B8: Bacon Strips | C8: Meat & Poultry | D8: Kg | E8: ='Store Inventory'!E7 -> 20 | F8: ='Store Inventory'!F7 -> 650 | G8: 10 | P8: =SUM(G8:O8) -> 10 | Q8: =P8*F8 -> 6500 | R8: =E8-P8 -> 10
A9: FD004 | B9: Fresh Lettuce | C9: Fresh Produce | D9: Kg | E9: ='Store Inventory'!E8 -> 50 | F9: ='Store Inventory'!F8 -> 60 | G9: 12 | H9: 11 | P9: =SUM(G9:O9) -> 23 | Q9: =P9*F9 -> 1380 | R9: =E9-P9 -> 27
A10: FD005 | B10: Fresh Tomato | C10: Fresh Produce | D10: Kg | E10: ='Store Inventory'!E9 -> 50 | F10: ='Store Inventory'!F9 -> 56 | G10: 12 | H10: 11 | P10: =SUM(G10:O10) -> 23 | Q10: =P10*F10 -> 1288 | R10: =E10-P10 -> 27
A11: FD006 | B11: Onion | C11: Fresh Produce | D11: Kg | E11: ='Store Inventory'!E10 -> 25 | F11: ='Store Inventory'!F10 -> 40 | G11: 10 | P11: =SUM(G11:O11) -> 10 | Q11: =P11*F11 -> 400 | R11: =E11-P11 -> 15
A12: FD007 | B12: Cheddar Cheese Slice | C12: Dairy | D12: Pcs | E12: ='Store Inventory'!E11 -> 150 | F12: ='Store Inventory'!F11 -> 12 | G12: 130 | P12: =SUM(G12:O12) -> 130 | Q12: =P12*F12 -> 1560 | R12: =E12-P12 -> 20
A13: FD008 | B13: All-Purpose Flour | C13: Bakery & Dry Goods | D13: Kg | E13: ='Store Inventory'!E12 -> 60 | F13: ='Store Inventory'!F12 -> 55 | G13: 35 | P13: =SUM(G13:O13) -> 35 | Q13: =P13*F13 -> 1925 | R13: =E13-P13 -> 25
A14: FD009 | B14: Butter (Unsalted) | C14: Dairy | D14: Kg | E14: ='Store Inventory'!E13 -> 20 | F14: ='Store Inventory'!F13 -> 480 | G14: 10 | P14: =SUM(G14:O14) -> 10 | Q14: =P14*F14 -> 4800 | R14: =E14-P14 -> 10
A15: FD010 | B15: Fresh Eggs | C15: Dairy | D15: Pcs | E15: ='Store Inventory'!E14 -> 150 | F15: ='Store Inventory'!F14 -> 8 | G15: 100 | P15: =SUM(G15:O15) -> 100 | Q15: =P15*F15 -> 800 | R15: =E15-P15 -> 50
A16: FD011 | B16: Spaghetti Pasta | C16: Bakery & Dry Goods | D16: Kg | E16: ='Store Inventory'!E15 -> 35 | F16: ='Store Inventory'!F15 -> 120 | G16: 18 | P16: =SUM(G16:O16) -> 18 | Q16: =P16*F16 -> 2160 | R16: =E16-P16 -> 17
A17: FD012 | B17: Tortilla Wrap | C17: Bakery & Dry Goods | D17: Pcs | E17: ='Store Inventory'!E16 -> 90 | F17: ='Store Inventory'!F16 -> 15 | G17: 55 | P17: =SUM(G17:O17) -> 55 | Q17: =P17*F17 -> 825 | R17: =E17-P17 -> 35
A18: FD013 | B18: Mayonnaise | C18: Condiments & Sauces | D18: Kg | E18: ='Store Inventory'!E17 -> 35 | F18: ='Store Inventory'!F17 -> 220 | G18: 20 | P18: =SUM(G18:O18) -> 20 | Q18: =P18*F18 -> 4400 | R18: =E18-P18 -> 15
A19: FD014 | B19: Tomato Ketchup | C19: Condiments & Sauces | D19: Kg | E19: ='Store Inventory'!E18 -> 35 | F19: ='Store Inventory'!F18 -> 180 | G19: 18 | P19: =SUM(G19:O19) -> 18 | Q19: =P19*F19 -> 3240 | R19: =E19-P19 -> 17
A20: FD015 | B20: Mozzarella Cheese | C20: Dairy | D20: Kg | E20: ='Store Inventory'!E19 -> 25 | F20: ='Store Inventory'!F19 -> 620 | G20: 15 | P20: =SUM(G20:O20) -> 15 | Q20: =P20*F20 -> 9300 | R20: =E20-P20 -> 10
A21: BEVERAGE
A22: BV001 | B22: Coffee Beans (Roasted) | C22: Coffee & Tea | D22: Kg | E22: ='Store Inventory'!E21 -> 25 | F22: ='Store Inventory'!F21 -> 900 | G22: 15 | P22: =SUM(G22:O22) -> 15 | Q22: =P22*F22 -> 13500 | R22: =E22-P22 -> 10
A23: BV002 | B23: Black Tea Bags | C23: Coffee & Tea | D23: Pcs | E23: ='Store Inventory'!E22 -> 0 | F23: ='Store Inventory'!F22 -> 3 | P23: =SUM(G23:O23) -> 0 | Q23: =P23*F23 -> 0 | R23: =E23-P23 -> 0
A24: BV003 | B24: Green Tea Bags | C24: Coffee & Tea | D24: Pcs | E24: ='Store Inventory'!E23 -> 0 | F24: ='Store Inventory'!F23 -> 4 | P24: =SUM(G24:O24) -> 0 | Q24: =P24*F24 -> 0 | R24: =E24-P24 -> 0
A25: BV004 | B25: Fresh Milk | C25: Dairy & Bar | D25: Ltr | E25: ='Store Inventory'!E24 -> 130 | F25: ='Store Inventory'!F24 -> 65.461538 | G25: 45 | H25: 40 | P25: =SUM(G25:O25) -> 85 | Q25: =P25*F25 -> 5564.2308 | R25: =E25-P25 -> 45
A26: BV005 | B26: Cocoa Powder | C26: Coffee & Tea | D26: Kg | E26: ='Store Inventory'!E25 -> 0 | F26: ='Store Inventory'!F25 -> 350 | P26: =SUM(G26:O26) -> 0 | Q26: =P26*F26 -> 0 | R26: =E26-P26 -> 0
A27: BV006 | B27: White Rum | C27: Bar & Spirits | D27: Ltr | E27: ='Store Inventory'!E26 -> 12 | F27: ='Store Inventory'!F26 -> 950 | G27: 6 | P27: =SUM(G27:O27) -> 6 | Q27: =P27*F27 -> 5700 | R27: =E27-P27 -> 6
A28: BV007 | B28: Fresh Mint Leaves | C28: Bar Garnish | D28: Kg | E28: ='Store Inventory'!E27 -> 0 | F28: ='Store Inventory'!F27 -> 150 | P28: =SUM(G28:O28) -> 0 | Q28: =P28*F28 -> 0 | R28: =E28-P28 -> 0
A29: BV008 | B29: Fresh Lime | C29: Bar Garnish | D29: Kg | E29: ='Store Inventory'!E28 -> 12 | F29: ='Store Inventory'!F28 -> 100 | G29: 6 | P29: =SUM(G29:O29) -> 6 | Q29: =P29*F29 -> 600 | R29: =E29-P29 -> 6
A30: BV009 | B30: Fresh Avocado | C30: Fresh Produce | D30: Kg | E30: ='Store Inventory'!E29 -> 20 | F30: ='Store Inventory'!F29 -> 90 | G30: 12 | P30: =SUM(G30:O30) -> 12 | Q30: =P30*F30 -> 1080 | R30: =E30-P30 -> 8
A31: BV010 | B31: Soda Water | C31: Bar & Mixers | D31: Ltr | E31: ='Store Inventory'!E30 -> 35 | F31: ='Store Inventory'!F30 -> 45 | G31: 18 | P31: =SUM(G31:O31) -> 18 | Q31: =P31*F31 -> 810 | R31: =E31-P31 -> 17
A32: BV011 | B32: Coca-Cola (330ml Bottle) | C32: Soft Drinks | D32: Bottle | E32: ='Store Inventory'!E31 -> 220 | F32: ='Store Inventory'!F31 -> 35 | G32: 150 | P32: =SUM(G32:O32) -> 150 | Q32: =P32*F32 -> 5250 | R32: =E32-P32 -> 70
A33: OTHERS
A34: OT001 | B34: Burger Takeaway Box | C34: Packaging | D34: Pcs | E34: ='Store Inventory'!E33 -> 400 | F34: ='Store Inventory'!F33 -> 8 | G34: 280 | P34: =SUM(G34:O34) -> 280 | Q34: =P34*F34 -> 2240 | R34: =E34-P34 -> 120
A35: OT002 | B35: Pizza Takeaway Box | C35: Packaging | D35: Pcs | E35: ='Store Inventory'!E34 -> 300 | F35: ='Store Inventory'!F34 -> 15 | G35: 200 | P35: =SUM(G35:O35) -> 200 | Q35: =P35*F35 -> 3000 | R35: =E35-P35 -> 100
A36: OT003 | B36: Paper Napkins | C36: Consumables | D36: Pcs | E36: ='Store Inventory'!E35 -> 0 | F36: ='Store Inventory'!F35 -> 1 | P36: =SUM(G36:O36) -> 0 | Q36: =P36*F36 -> 0 | R36: =E36-P36 -> 0
A37: OT004 | B37: Disposable Straws | C37: Consumables | D37: Pcs | E37: ='Store Inventory'!E36 -> 0 | F37: ='Store Inventory'!F36 -> 1 | P37: =SUM(G37:O37) -> 0 | Q37: =P37*F37 -> 0 | R37: =E37-P37 -> 0
A38: OT005 | B38: White Sugar | C38: Pantry & Dry Goods | D38: Kg | E38: ='Store Inventory'!E37 -> 45 | F38: ='Store Inventory'!F37 -> 60 | G38: 20 | P38: =SUM(G38:O38) -> 20 | Q38: =P38*F38 -> 1200 | R38: =E38-P38 -> 25
A39: OT006 | B39: Iodized Salt | C39: Pantry & Dry Goods | D39: Kg | E39: ='Store Inventory'!E38 -> 0 | F39: ='Store Inventory'!F38 -> 25 | P39: =SUM(G39:O39) -> 0 | Q39: =P39*F39 -> 0 | R39: =E39-P39 -> 0
A40: OT007 | B40: Cooking / Vegetable Oil | C40: Pantry & Dry Goods | D40: Ltr | E40: ='Store Inventory'!E39 -> 45 | F40: ='Store Inventory'!F39 -> 150 | G40: 18 | P40: =SUM(G40:O40) -> 18 | Q40: =P40*F40 -> 2700 | R40: =E40-P40 -> 27
A41: OT008 | B41: Instant Dry Yeast | C41: Pantry & Dry Goods | D41: Kg | E41: ='Store Inventory'!E40 -> 12 | F41: ='Store Inventory'!F40 -> 400 | G41: 8 | P41: =SUM(G41:O41) -> 8 | Q41: =P41*F41 -> 3200 | R41: =E41-P41 -> 4
A42: OT009 | B42: Black Pepper (Ground) | C42: Pantry & Dry Goods | D42: Kg | E42: ='Store Inventory'!E41 -> 0 | F42: ='Store Inventory'!F41 -> 500 | P42: =SUM(G42:O42) -> 0 | Q42: =P42*F42 -> 0 | R42: =E42-P42 -> 0
A44: Issue Value by Category (per event) — feeds Daily Flash Cost
A45: Event Date | G45: =G$3 -> 46207 | H45: =H$3 -> 46219 | I45: =I$3 -> Insert Date | J45: =J$3 -> Insert Date | K45: =K$3 -> Insert Date | L45: =L$3 -> Insert Date | M45: =M$3 -> Insert Date | N45: =N$3 -> Insert Date | O45: =O$3 -> Insert Date
A46: Food Issue Value | G46: =SUMPRODUCT((LEFT($A$5:$A$42,2)="FD")*G$5:G$42*$F$5:$F$42) -> 57137.059 | H46: =SUMPRODUCT((LEFT($A$5:$A$42,2)="FD")*H$5:H$42*$F$5:$F$42) -> 17916.314 | I46: =SUMPRODUCT((LEFT($A$5:$A$42,2)="FD")*I$5:I$42*$F$5:$F$42) -> 0 | J46: =SUMPRODUCT((LEFT($A$5:$A$42,2)="FD")*J$5:J$42*$F$5:$F$42) -> 0 | K46: =SUMPRODUCT((LEFT($A$5:$A$42,2)="FD")*K$5:K$42*$F$5:$F$42) -> 0 | L46: =SUMPRODUCT((LEFT($A$5:$A$42,2)="FD")*L$5:L$42*$F$5:$F$42) -> 0 | M46: =SUMPRODUCT((LEFT($A$5:$A$42,2)="FD")*M$5:M$42*$F$5:$F$42) -> 0 | N46: =SUMPRODUCT((LEFT($A$5:$A$42,2)="FD")*N$5:N$42*$F$5:$F$42) -> 0 | O46: =SUMPRODUCT((LEFT($A$5:$A$42,2)="FD")*O$5:O$42*$F$5:$F$42) -> 0
A47: Beverage Issue Value | G47: =SUMPRODUCT((LEFT($A$5:$A$42,2)="BV")*G$5:G$42*$F$5:$F$42) -> 29885.769 | H47: =SUMPRODUCT((LEFT($A$5:$A$42,2)="BV")*H$5:H$42*$F$5:$F$42) -> 2618.4615 | I47: =SUMPRODUCT((LEFT($A$5:$A$42,2)="BV")*I$5:I$42*$F$5:$F$42) -> 0 | J47: =SUMPRODUCT((LEFT($A$5:$A$42,2)="BV")*J$5:J$42*$F$5:$F$42) -> 0 | K47: =SUMPRODUCT((LEFT($A$5:$A$42,2)="BV")*K$5:K$42*$F$5:$F$42) -> 0 | L47: =SUMPRODUCT((LEFT($A$5:$A$42,2)="BV")*L$5:L$42*$F$5:$F$42) -> 0 | M47: =SUMPRODUCT((LEFT($A$5:$A$42,2)="BV")*M$5:M$42*$F$5:$F$42) -> 0 | N47: =SUMPRODUCT((LEFT($A$5:$A$42,2)="BV")*N$5:N$42*$F$5:$F$42) -> 0 | O47: =SUMPRODUCT((LEFT($A$5:$A$42,2)="BV")*O$5:O$42*$F$5:$F$42) -> 0

Sheet Kitchen & Bar Receiving
A1: KITCHEN & BAR RECEIVING
A2: Confirms what the outlet actually received from the Main Store
F3: 46207 | G3: 46219 | H3: Insert Date | I3: Insert Date | J3: Insert Date | K3: Insert Date | L3: Insert Date | M3: Insert Date | N3: Insert Date
A4: ITEM CODE | B4: ITEM NAME | C4: CATEGORY | D4: UOM | E4: Beginning Qty | F4: Receiving 1 | G4: Receiving 2 | H4: Receiving 3 | I4: Receiving 4 | J4: Receiving 5 | K4: Receiving 6 | L4: Receiving 7 | M4: Receiving 8 | N4: Receiving 9 | O4: Total Received | P4: Available Qty | Q4: Average Cost | R4: Inventory Value
A5: FOOD
A6: FD001 | B6: Beef Mince (80% Lean) | C6: Meat & Poultry | D6: Kg | E6: 0 | F6: 20 | G6: 16 | O6: =SUM(F6:N6) -> 36 | P6: =E6+O6 -> 36 | Q6: ='Store Issue'!F6 -> 557.35294 | R6: =P6*Q6 -> 20064.706
A7: FD002 | B7: Chicken Breast (Boneless) | C7: Meat & Poultry | D7: Kg | E7: 0 | F7: 18 | G7: 16 | O7: =SUM(F7:N7) -> 34 | P7: =E7+O7 -> 34 | Q7: ='Store Issue'!F7 -> 482.66667 | R7: =P7*Q7 -> 16410.667
A8: FD003 | B8: Bacon Strips | C8: Meat & Poultry | D8: Kg | E8: 0 | F8: 10 | O8: =SUM(F8:N8) -> 10 | P8: =E8+O8 -> 10 | Q8: ='Store Issue'!F8 -> 650 | R8: =P8*Q8 -> 6500
A9: FD004 | B9: Fresh Lettuce | C9: Fresh Produce | D9: Kg | E9: 0 | F9: 12 | G9: 11 | O9: =SUM(F9:N9) -> 23 | P9: =E9+O9 -> 23 | Q9: ='Store Issue'!F9 -> 60 | R9: =P9*Q9 -> 1380
A10: FD005 | B10: Fresh Tomato | C10: Fresh Produce | D10: Kg | E10: 0 | F10: 12 | G10: 11 | O10: =SUM(F10:N10) -> 23 | P10: =E10+O10 -> 23 | Q10: ='Store Issue'!F10 -> 56 | R10: =P10*Q10 -> 1288
A11: FD006 | B11: Onion | C11: Fresh Produce | D11: Kg | E11: 0 | F11: 10 | O11: =SUM(F11:N11) -> 10 | P11: =E11+O11 -> 10 | Q11: ='Store Issue'!F11 -> 40 | R11: =P11*Q11 -> 400
A12: FD007 | B12: Cheddar Cheese Slice | C12: Dairy | D12: Pcs | E12: 0 | F12: 130 | O12: =SUM(F12:N12) -> 130 | P12: =E12+O12 -> 130 | Q12: ='Store Issue'!F12 -> 12 | R12: =P12*Q12 -> 1560
A13: FD008 | B13: All-Purpose Flour | C13: Bakery & Dry Goods | D13: Kg | E13: 0 | F13: 35 | O13: =SUM(F13:N13) -> 35 | P13: =E13+O13 -> 35 | Q13: ='Store Issue'!F13 -> 55 | R13: =P13*Q13 -> 1925
A14: FD009 | B14: Butter (Unsalted) | C14: Dairy | D14: Kg | E14: 0 | F14: 10 | O14: =SUM(F14:N14) -> 10 | P14: =E14+O14 -> 10 | Q14: ='Store Issue'!F14 -> 480 | R14: =P14*Q14 -> 4800
A15: FD010 | B15: Fresh Eggs | C15: Dairy | D15: Pcs | E15: 0 | F15: 100 | O15: =SUM(F15:N15) -> 100 | P15: =E15+O15 -> 100 | Q15: ='Store Issue'!F15 -> 8 | R15: =P15*Q15 -> 800
A16: FD011 | B16: Spaghetti Pasta | C16: Bakery & Dry Goods | D16: Kg | E16: 0 | F16: 18 | O16: =SUM(F16:N16) -> 18 | P16: =E16+O16 -> 18 | Q16: ='Store Issue'!F16 -> 120 | R16: =P16*Q16 -> 2160
A17: FD012 | B17: Tortilla Wrap | C17: Bakery & Dry Goods | D17: Pcs | E17: 0 | F17: 55 | O17: =SUM(F17:N17) -> 55 | P17: =E17+O17 -> 55 | Q17: ='Store Issue'!F17 -> 15 | R17: =P17*Q17 -> 825
A18: FD013 | B18: Mayonnaise | C18: Condiments & Sauces | D18: Kg | E18: 0 | F18: 20 | O18: =SUM(F18:N18) -> 20 | P18: =E18+O18 -> 20 | Q18: ='Store Issue'!F18 -> 220 | R18: =P18*Q18 -> 4400
A19: FD014 | B19: Tomato Ketchup | C19: Condiments & Sauces | D19: Kg | E19: 0 | F19: 18 | O19: =SUM(F19:N19) -> 18 | P19: =E19+O19 -> 18 | Q19: ='Store Issue'!F19 -> 180 | R19: =P19*Q19 -> 3240
A20: FD015 | B20: Mozzarella Cheese | C20: Dairy | D20: Kg | E20: 0 | F20: 15 | O20: =SUM(F20:N20) -> 15 | P20: =E20+O20 -> 15 | Q20: ='Store Issue'!F20 -> 620 | R20: =P20*Q20 -> 9300
A21: BEVERAGE
A22: BV001 | B22: Coffee Beans (Roasted) | C22: Coffee & Tea | D22: Kg | E22: 0 | F22: 15 | O22: =SUM(F22:N22) -> 15 | P22: =E22+O22 -> 15 | Q22: ='Store Issue'!F22 -> 900 | R22: =P22*Q22 -> 13500
A23: BV002 | B23: Black Tea Bags | C23: Coffee & Tea | D23: Pcs | E23: 0 | O23: =SUM(F23:N23) -> 0 | P23: =E23+O23 -> 0 | Q23: ='Store Issue'!F23 -> 3 | R23: =P23*Q23 -> 0
A24: BV003 | B24: Green Tea Bags | C24: Coffee & Tea | D24: Pcs | E24: 0 | O24: =SUM(F24:N24) -> 0 | P24: =E24+O24 -> 0 | Q24: ='Store Issue'!F24 -> 4 | R24: =P24*Q24 -> 0
A25: BV004 | B25: Fresh Milk | C25: Dairy & Bar | D25: Ltr | E25: 0 | F25: 45 | G25: 40 | O25: =SUM(F25:N25) -> 85 | P25: =E25+O25 -> 85 | Q25: ='Store Issue'!F25 -> 65.461538 | R25: =P25*Q25 -> 5564.2308
A26: BV005 | B26: Cocoa Powder | C26: Coffee & Tea | D26: Kg | E26: 0 | O26: =SUM(F26:N26) -> 0 | P26: =E26+O26 -> 0 | Q26: ='Store Issue'!F26 -> 350 | R26: =P26*Q26 -> 0
A27: BV006 | B27: White Rum | C27: Bar & Spirits | D27: Ltr | E27: 0 | F27: 6 | O27: =SUM(F27:N27) -> 6 | P27: =E27+O27 -> 6 | Q27: ='Store Issue'!F27 -> 950 | R27: =P27*Q27 -> 5700
A28: BV007 | B28: Fresh Mint Leaves | C28: Bar Garnish | D28: Kg | E28: 0 | O28: =SUM(F28:N28) -> 0 | P28: =E28+O28 -> 0 | Q28: ='Store Issue'!F28 -> 150 | R28: =P28*Q28 -> 0
A29: BV008 | B29: Fresh Lime | C29: Bar Garnish | D29: Kg | E29: 0 | F29: 6 | O29: =SUM(F29:N29) -> 6 | P29: =E29+O29 -> 6 | Q29: ='Store Issue'!F29 -> 100 | R29: =P29*Q29 -> 600
A30: BV009 | B30: Fresh Avocado | C30: Fresh Produce | D30: Kg | E30: 0 | F30: 12 | O30: =SUM(F30:N30) -> 12 | P30: =E30+O30 -> 12 | Q30: ='Store Issue'!F30 -> 90 | R30: =P30*Q30 -> 1080
A31: BV010 | B31: Soda Water | C31: Bar & Mixers | D31: Ltr | E31: 0 | F31: 18 | O31: =SUM(F31:N31) -> 18 | P31: =E31+O31 -> 18 | Q31: ='Store Issue'!F31 -> 45 | R31: =P31*Q31 -> 810
A32: BV011 | B32: Coca-Cola (330ml Bottle) | C32: Soft Drinks | D32: Bottle | E32: 0 | F32: 150 | O32: =SUM(F32:N32) -> 150 | P32: =E32+O32 -> 150 | Q32: ='Store Issue'!F32 -> 35 | R32: =P32*Q32 -> 5250
A33: OTHERS
A34: OT001 | B34: Burger Takeaway Box | C34: Packaging | D34: Pcs | E34: 0 | F34: 280 | O34: =SUM(F34:N34) -> 280 | P34: =E34+O34 -> 280 | Q34: ='Store Issue'!F34 -> 8 | R34: =P34*Q34 -> 2240
A35: OT002 | B35: Pizza Takeaway Box | C35: Packaging | D35: Pcs | E35: 0 | F35: 200 | O35: =SUM(F35:N35) -> 200 | P35: =E35+O35 -> 200 | Q35: ='Store Issue'!F35 -> 15 | R35: =P35*Q35 -> 3000
A36: OT003 | B36: Paper Napkins | C36: Consumables | D36: Pcs | E36: 0 | O36: =SUM(F36:N36) -> 0 | P36: =E36+O36 -> 0 | Q36: ='Store Issue'!F36 -> 1 | R36: =P36*Q36 -> 0
A37: OT004 | B37: Disposable Straws | C37: Consumables | D37: Pcs | E37: 0 | O37: =SUM(F37:N37) -> 0 | P37: =E37+O37 -> 0 | Q37: ='Store Issue'!F37 -> 1 | R37: =P37*Q37 -> 0
A38: OT005 | B38: White Sugar | C38: Pantry & Dry Goods | D38: Kg | E38: 0 | F38: 20 | O38: =SUM(F38:N38) -> 20 | P38: =E38+O38 -> 20 | Q38: ='Store Issue'!F38 -> 60 | R38: =P38*Q38 -> 1200
A39: OT006 | B39: Iodized Salt | C39: Pantry & Dry Goods | D39: Kg | E39: 0 | O39: =SUM(F39:N39) -> 0 | P39: =E39+O39 -> 0 | Q39: ='Store Issue'!F39 -> 25 | R39: =P39*Q39 -> 0
A40: OT007 | B40: Cooking / Vegetable Oil | C40: Pantry & Dry Goods | D40: Ltr | E40: 0 | F40: 18 | O40: =SUM(F40:N40) -> 18 | P40: =E40+O40 -> 18 | Q40: ='Store Issue'!F40 -> 150 | R40: =P40*Q40 -> 2700
A41: OT008 | B41: Instant Dry Yeast | C41: Pantry & Dry Goods | D41: Kg | E41: 0 | F41: 8 | O41: =SUM(F41:N41) -> 8 | P41: =E41+O41 -> 8 | Q41: ='Store Issue'!F41 -> 400 | R41: =P41*Q41 -> 3200
A42: OT009 | B42: Black Pepper (Ground) | C42: Pantry & Dry Goods | D42: Kg | E42: 0 | O42: =SUM(F42:N42) -> 0 | P42: =E42+O42 -> 0 | Q42: ='Store Issue'!F42 -> 500 | R42: =P42*Q42 -> 0

Sheet Daily Inventory
A1: DAILY INVENTORY
A2: Daily physical stock counts at the outlet — raw ingredients
A4: ITEM CODE | B4: ITEM NAME | C4: CATEGORY | D4: UOM | E4: Opening Qty | F4: Day 1 | G4: Day 2 | H4: Day 3 | I4: Day 4 | J4: Day 5 | K4: Day 6 | L4: Day 7 | M4: Day 8 | N4: Day 9 | O4: Day 10 | P4: Day 11 | Q4: Day 12 | R4: Day 13 | S4: Day 14 | T4: Day 15 | U4: Day 16 | V4: Day 17 | W4: Day 18 | X4: Day 19 | Y4: Day 20 | Z4: Day 21 | AA4: Day 22 | AB4: Day 23 | AC4: Day 24 | AD4: Day 25 | AE4: Day 26 | AF4: Day 27 | AG4: Day 28 | AH4: Day 29 | AI4: Day 30 | AJ4: Day 31
A5: FOOD
A6: FD001 | B6: Beef Mince (80% Lean) | C6: Meat & Poultry | D6: Kg | E6: 0 | F6: 14 | G6: 13 | H6: 12
A7: FD002 | B7: Chicken Breast (Boneless) | C7: Meat & Poultry | D7: Kg | E7: 0 | F7: 10 | G7: 9 | H7: 9
A8: FD003 | B8: Bacon Strips | C8: Meat & Poultry | D8: Kg | E8: 0
A9: FD004 | B9: Fresh Lettuce | C9: Fresh Produce | D9: Kg | E9: 0 | F9: 6 | G9: 5 | H9: 5
A10: FD005 | B10: Fresh Tomato | C10: Fresh Produce | D10: Kg | E10: 0 | F10: 6 | G10: 5 | H10: 5
A11: FD006 | B11: Onion | C11: Fresh Produce | D11: Kg | E11: 0
A12: FD007 | B12: Cheddar Cheese Slice | C12: Dairy | D12: Pcs | E12: 0
A13: FD008 | B13: All-Purpose Flour | C13: Bakery & Dry Goods | D13: Kg | E13: 0
A14: FD009 | B14: Butter (Unsalted) | C14: Dairy | D14: Kg | E14: 0 | F14: 4 | G14: 4 | H14: 3.5
A15: FD010 | B15: Fresh Eggs | C15: Dairy | D15: Pcs | E15: 0
A16: FD011 | B16: Spaghetti Pasta | C16: Bakery & Dry Goods | D16: Kg | E16: 0
A17: FD012 | B17: Tortilla Wrap | C17: Bakery & Dry Goods | D17: Pcs | E17: 0
A18: FD013 | B18: Mayonnaise | C18: Condiments & Sauces | D18: Kg | E18: 0
A19: FD014 | B19: Tomato Ketchup | C19: Condiments & Sauces | D19: Kg | E19: 0
A20: FD015 | B20: Mozzarella Cheese | C20: Dairy | D20: Kg | E20: 0 | F20: 5 | G20: 4.5 | H20: 4
A21: BEVERAGE
A22: BV001 | B22: Coffee Beans (Roasted) | C22: Coffee & Tea | D22: Kg | E22: 0
A23: BV002 | B23: Black Tea Bags | C23: Coffee & Tea | D23: Pcs | E23: 0
A24: BV003 | B24: Green Tea Bags | C24: Coffee & Tea | D24: Pcs | E24: 0
A25: BV004 | B25: Fresh Milk | C25: Dairy & Bar | D25: Ltr | E25: 0 | F25: 18 | G25: 16 | H25: 15
A26: BV005 | B26: Cocoa Powder | C26: Coffee & Tea | D26: Kg | E26: 0
A27: BV006 | B27: White Rum | C27: Bar & Spirits | D27: Ltr | E27: 0 | F27: 4 | G27: 4 | H27: 3.8
A28: BV007 | B28: Fresh Mint Leaves | C28: Bar Garnish | D28: Kg | E28: 0
A29: BV008 | B29: Fresh Lime | C29: Bar Garnish | D29: Kg | E29: 0
A30: BV009 | B30: Fresh Avocado | C30: Fresh Produce | D30: Kg | E30: 0
A31: BV010 | B31: Soda Water | C31: Bar & Mixers | D31: Ltr | E31: 0
A32: BV011 | B32: Coca-Cola (330ml Bottle) | C32: Soft Drinks | D32: Bottle | E32: 0
A33: OTHERS
A34: OT001 | B34: Burger Takeaway Box | C34: Packaging | D34: Pcs | E34: 0
A35: OT002 | B35: Pizza Takeaway Box | C35: Packaging | D35: Pcs | E35: 0
A36: OT003 | B36: Paper Napkins | C36: Consumables | D36: Pcs | E36: 0
A37: OT004 | B37: Disposable Straws | C37: Consumables | D37: Pcs | E37: 0
A38: OT005 | B38: White Sugar | C38: Pantry & Dry Goods | D38: Kg | E38: 0
A39: OT006 | B39: Iodized Salt | C39: Pantry & Dry Goods | D39: Kg | E39: 0
A40: OT007 | B40: Cooking / Vegetable Oil | C40: Pantry & Dry Goods | D40: Ltr | E40: 0
A41: OT008 | B41: Instant Dry Yeast | C41: Pantry & Dry Goods | D41: Kg | E41: 0
A42: OT009 | B42: Black Pepper (Ground) | C42: Pantry & Dry Goods | D42: Kg | E42: 0

Sheet Semi-Finished Inventory
A1: SEMI-FINISHED INVENTORY
A2: Daily physical stock counts at the outlet — homemade prep (Sub-Recipe) items
A4: SUB-RECIPE CODE | B4: COMPONENT NAME | C4: YIELD UOM | D4: BATCH YIELD QTY | E4: Opening Qty | F4: Day 1 | G4: Day 2 | H4: Day 3 | I4: Day 4 | J4: Day 5 | K4: Day 6 | L4: Day 7 | M4: Day 8 | N4: Day 9 | O4: Day 10 | P4: Day 11 | Q4: Day 12 | R4: Day 13 | S4: Day 14 | T4: Day 15 | U4: Day 16 | V4: Day 17 | W4: Day 18 | X4: Day 19 | Y4: Day 20 | Z4: Day 21 | AA4: Day 22 | AB4: Day 23 | AC4: Day 24 | AD4: Day 25 | AE4: Day 26 | AF4: Day 27 | AG4: Day 28 | AH4: Day 29 | AI4: Day 30 | AJ4: Day 31
A5: SR001 | B5: Burger Bun (Homemade) | C5: Pcs | D5: ='Sub-Recipe'!I10 -> 20 | E5: 0 | F5: 8 | G5: 6 | H5: 4
A6: SR002 | B6: Sandwich Bread Loaf (Homemade) | C6: Slices | D6: ='Sub-Recipe'!I17 -> 20 | E6: 0 | F6: 10 | G6: 8 | H6: 6
A7: SR003 | B7: Croissant Dough (Homemade) | C7: Pcs | D7: ='Sub-Recipe'!I24 -> 10 | E7: 0
A8: SR004 | B8: Danish Pastry Dough (Homemade) | C8: Pcs | D8: ='Sub-Recipe'!I30 -> 10 | E8: 0
A9: SR005 | B9: Pizza Dough Base (Homemade) | C9: Bases | D9: ='Sub-Recipe'!I36 -> 5 | E9: 0
A10: SR006 | B10: Bolognese Sauce (Homemade) | C10: Portions (250g) | D10: ='Sub-Recipe'!I43 -> 8 | E10: 0
A11: SR007 | B11: Alfredo Sauce (Homemade) | C11: Portions (125g) | D11: ='Sub-Recipe'!I49 -> 8 | E11: 0
A12: SR008 | B12: Caesar Dressing (Homemade) | C12: Portions (100g) | D12: ='Sub-Recipe'!I55 -> 10 | E12: 0 | F12: 4 | G12: 3 | H12: 2
A13: SR009 | B13: Pizza Tomato Sauce (Homemade) | C13: Portions (100g) | D13: ='Sub-Recipe'!I61 -> 10 | E13: 0
A14: SR010 | B14: Mojito Syrup Base (Homemade) | C14: Servings (50ml) | D14: ='Sub-Recipe'!I66 -> 20 | E14: 0

Sheet Wastage
A1: WASTAGE
A2: Every item spoiled, dropped or discarded — logged as it happens
A4: Wastage No. | B4: Date | C4: Item Code | D4: Item Name | E4: Category | F4: UOM | G4: Qty Wasted | H4: Average Cost | I4: Wastage Value | J4: Wastage Type | K4: Reason | L4: Department | M4: Reported By | N4: Approved By
A5: =IF(C5="","","WST-"&TEXT(ROW()-4,"000")) -> WST-001 | B5: 46205 | C5: FD005 | D5: Fresh Tomato | E5: Food | F5: Kg | G5: 1.5 | H5: =IFERROR(INDEX('Item Master'!$E$4:$E$41,MATCH(C5,'Item Master'!$A$4:$A$41,0)),0) -> 55 | I5: =IFERROR(G5*H5,0) -> 82.5 | J5: Spoilage | K5: Over-ripened before use | L5: Kitchen | M5: Chef A | N5: Manager K
A6: =IF(C6="","","WST-"&TEXT(ROW()-4,"000")) -> WST-002 | B6: 46206 | C6: FD004 | D6: Fresh Lettuce | E6: Food | F6: Kg | G6: 0.8 | H6: =IFERROR(INDEX('Item Master'!$E$4:$E$41,MATCH(C6,'Item Master'!$A$4:$A$41,0)),0) -> 60 | I6: =IFERROR(G6*H6,0) -> 48 | J6: Spoilage | K6: Wilted | L6: Kitchen | M6: Chef A | N6: Manager K
A7: =IF(C7="","","WST-"&TEXT(ROW()-4,"000")) -> WST-003 | B7: 46207 | C7: BV004 | D7: Fresh Milk | E7: Beverage | F7: Ltr | G7: 1 | H7: =IFERROR(INDEX('Item Master'!$E$4:$E$41,MATCH(C7,'Item Master'!$A$4:$A$41,0)),0) -> 65 | I7: =IFERROR(G7*H7,0) -> 65 | J7: Spillage | K7: Dropped during prep | L7: Bar | M7: Barista B | N7: Manager K
A8: =IF(C8="","","WST-"&TEXT(ROW()-4,"000")) -> WST-004 | B8: 46208 | C8: FD010 | D8: Fresh Eggs | E8: Food | F8: Pcs | G8: 3 | H8: =IFERROR(INDEX('Item Master'!$E$4:$E$41,MATCH(C8,'Item Master'!$A$4:$A$41,0)),0) -> 8 | I8: =IFERROR(G8*H8,0) -> 24 | J8: Breakage | K8: Broken in delivery | L8: Kitchen | M8: Chef A | N8: Manager K
A9: =IF(C9="","","WST-"&TEXT(ROW()-4,"000")) | H9: =IFERROR(INDEX('Item Master'!$E$4:$E$41,MATCH(C9,'Item Master'!$A$4:$A$41,0)),0) -> 0 | I9: =IFERROR(G9*H9,0) -> 0
A10: =IF(C10="","","WST-"&TEXT(ROW()-4,"000")) | H10: =IFERROR(INDEX('Item Master'!$E$4:$E$41,MATCH(C10,'Item Master'!$A$4:$A$41,0)),0) -> 0 | I10: =IFERROR(G10*H10,0) -> 0
A11: =IF(C11="","","WST-"&TEXT(ROW()-4,"000")) | H11: =IFERROR(INDEX('Item Master'!$E$4:$E$41,MATCH(C11,'Item Master'!$A$4:$A$41,0)),0) -> 0 | I11: =IFERROR(G11*H11,0) -> 0
A12: =IF(C12="","","WST-"&TEXT(ROW()-4,"000")) | H12: =IFERROR(INDEX('Item Master'!$E$4:$E$41,MATCH(C12,'Item Master'!$A$4:$A$41,0)),0) -> 0 | I12: =IFERROR(G12*H12,0) -> 0
A13: =IF(C13="","","WST-"&TEXT(ROW()-4,"000")) | H13: =IFERROR(INDEX('Item Master'!$E$4:$E$41,MATCH(C13,'Item Master'!$A$4:$A$41,0)),0) -> 0 | I13: =IFERROR(G13*H13,0) -> 0
A14: =IF(C14="","","WST-"&TEXT(ROW()-4,"000")) | H14: =IFERROR(INDEX('Item Master'!$E$4:$E$41,MATCH(C14,'Item Master'!$A$4:$A$41,0)),0) -> 0 | I14: =IFERROR(G14*H14,0) -> 0
A15: =IF(C15="","","WST-"&TEXT(ROW()-4,"000")) | H15: =IFERROR(INDEX('Item Master'!$E$4:$E$41,MATCH(C15,'Item Master'!$A$4:$A$41,0)),0) -> 0 | I15: =IFERROR(G15*H15,0) -> 0
A16: =IF(C16="","","WST-"&TEXT(ROW()-4,"000")) | H16: =IFERROR(INDEX('Item Master'!$E$4:$E$41,MATCH(C16,'Item Master'!$A$4:$A$41,0)),0) -> 0 | I16: =IFERROR(G16*H16,0) -> 0
A17: =IF(C17="","","WST-"&TEXT(ROW()-4,"000")) | H17: =IFERROR(INDEX('Item Master'!$E$4:$E$41,MATCH(C17,'Item Master'!$A$4:$A$41,0)),0) -> 0 | I17: =IFERROR(G17*H17,0) -> 0
A18: =IF(C18="","","WST-"&TEXT(ROW()-4,"000")) | H18: =IFERROR(INDEX('Item Master'!$E$4:$E$41,MATCH(C18,'Item Master'!$A$4:$A$41,0)),0) -> 0 | I18: =IFERROR(G18*H18,0) -> 0
A19: =IF(C19="","","WST-"&TEXT(ROW()-4,"000")) | H19: =IFERROR(INDEX('Item Master'!$E$4:$E$41,MATCH(C19,'Item Master'!$A$4:$A$41,0)),0) -> 0 | I19: =IFERROR(G19*H19,0) -> 0
A20: =IF(C20="","","WST-"&TEXT(ROW()-4,"000")) | H20: =IFERROR(INDEX('Item Master'!$E$4:$E$41,MATCH(C20,'Item Master'!$A$4:$A$41,0)),0) -> 0 | I20: =IFERROR(G20*H20,0) -> 0
... A64: =IF(C64="","","WST-"&TEXT(ROW()-4,"000")) | H64: =IFERROR(INDEX('Item Master'!$E$4:$E$41,MATCH(C64,'Item Master'!$A$4:$A$41,0)),0) -> 0 | I64: =IFERROR(G64*H64,0) -> 0

Sheet Daily Void
A1: DAILY VOID
A2: POS transactions that were cancelled or voided after ringing
A4: Void No. | B4: Date | C4: Time | D4: POS Bill No. | E4: Menu Code | F4: Menu Item | G4: Category | H4: Qty | I4: Selling Price | J4: Void Amount | K4: Cost Value | L4: Void Reason | M4: Cashier | N4: Authorized By | O4: Remarks
A5: =IF(E5="","","VD-"&TEXT(ROW()-4,"000")) -> VD-001 | B5: 46205 | C5: 12:40 | D5: B-1042 | E5: FM003 | F5: =IFERROR(INDEX('Menu Master'!$B$4:$B$60,MATCH(E5,'Menu Master'!$A$4:$A$60,0)),"") -> Chicken Caesar Wrap | G5: =IFERROR(INDEX('Menu Master'!$C$4:$C$60,MATCH(E5,'Menu Master'!$A$4:$A$60,0)),"") -> Food | H5: 1 | I5: =IFERROR(INDEX('Daily Sales'!$D$5:$D$30,MATCH(E5,'Daily Sales'!$A$5:$A$30,0)),0) -> 280 | J5: =H5*I5 -> 280 | K5: =H5*IFERROR(INDEX('Daily Sales'!$E$5:$E$30,MATCH(E5,'Daily Sales'!$A$5:$A$30,0)),0) -> 107.4 | L5: Wrong item rung | M5: Cashier J | N5: Manager K
A6: =IF(E6="","","VD-"&TEXT(ROW()-4,"000")) -> VD-002 | B6: 46207 | C6: 19:15 | D6: B-1108 | E6: BM006 | F6: =IFERROR(INDEX('Menu Master'!$B$4:$B$60,MATCH(E6,'Menu Master'!$A$4:$A$60,0)),"") -> Classic Mojito | G6: =IFERROR(INDEX('Menu Master'!$C$4:$C$60,MATCH(E6,'Menu Master'!$A$4:$A$60,0)),"") -> Beverage | H6: 2 | I6: =IFERROR(INDEX('Daily Sales'!$D$5:$D$30,MATCH(E6,'Daily Sales'!$A$5:$A$30,0)),0) -> 220 | J6: =H6*I6 -> 440 | K6: =H6*IFERROR(INDEX('Daily Sales'!$E$5:$E$30,MATCH(E6,'Daily Sales'!$A$5:$A$30,0)),0) -> 108.5 | L6: Guest changed order | M6: Cashier J | N6: Manager K
A7: =IF(E7="","","VD-"&TEXT(ROW()-4,"000")) | F7: =IFERROR(INDEX('Menu Master'!$B$4:$B$60,MATCH(E7,'Menu Master'!$A$4:$A$60,0)),"") | G7: =IFERROR(INDEX('Menu Master'!$C$4:$C$60,MATCH(E7,'Menu Master'!$A$4:$A$60,0)),"") | I7: =IFERROR(INDEX('Daily Sales'!$D$5:$D$30,MATCH(E7,'Daily Sales'!$A$5:$A$30,0)),0) -> 0 | J7: =H7*I7 -> 0 | K7: =H7*IFERROR(INDEX('Daily Sales'!$E$5:$E$30,MATCH(E7,'Daily Sales'!$A$5:$A$30,0)),0) -> 0
A8: =IF(E8="","","VD-"&TEXT(ROW()-4,"000")) | F8: =IFERROR(INDEX('Menu Master'!$B$4:$B$60,MATCH(E8,'Menu Master'!$A$4:$A$60,0)),"") | G8: =IFERROR(INDEX('Menu Master'!$C$4:$C$60,MATCH(E8,'Menu Master'!$A$4:$A$60,0)),"") | I8: =IFERROR(INDEX('Daily Sales'!$D$5:$D$30,MATCH(E8,'Daily Sales'!$A$5:$A$30,0)),0) -> 0 | J8: =H8*I8 -> 0 | K8: =H8*IFERROR(INDEX('Daily Sales'!$E$5:$E$30,MATCH(E8,'Daily Sales'!$A$5:$A$30,0)),0) -> 0
A9: =IF(E9="","","VD-"&TEXT(ROW()-4,"000")) | F9: =IFERROR(INDEX('Menu Master'!$B$4:$B$60,MATCH(E9,'Menu Master'!$A$4:$A$60,0)),"") | G9: =IFERROR(INDEX('Menu Master'!$C$4:$C$60,MATCH(E9,'Menu Master'!$A$4:$A$60,0)),"") | I9: =IFERROR(INDEX('Daily Sales'!$D$5:$D$30,MATCH(E9,'Daily Sales'!$A$5:$A$30,0)),0) -> 0 | J9: =H9*I9 -> 0 | K9: =H9*IFERROR(INDEX('Daily Sales'!$E$5:$E$30,MATCH(E9,'Daily Sales'!$A$5:$A$30,0)),0) -> 0
A10: =IF(E10="","","VD-"&TEXT(ROW()-4,"000")) | F10: =IFERROR(INDEX('Menu Master'!$B$4:$B$60,MATCH(E10,'Menu Master'!$A$4:$A$60,0)),"") | G10: =IFERROR(INDEX('Menu Master'!$C$4:$C$60,MATCH(E10,'Menu Master'!$A$4:$A$60,0)),"") | I10: =IFERROR(INDEX('Daily Sales'!$D$5:$D$30,MATCH(E10,'Daily Sales'!$A$5:$A$30,0)),0) -> 0 | J10: =H10*I10 -> 0 | K10: =H10*IFERROR(INDEX('Daily Sales'!$E$5:$E$30,MATCH(E10,'Daily Sales'!$A$5:$A$30,0)),0) -> 0
A11: =IF(E11="","","VD-"&TEXT(ROW()-4,"000")) | F11: =IFERROR(INDEX('Menu Master'!$B$4:$B$60,MATCH(E11,'Menu Master'!$A$4:$A$60,0)),"") | G11: =IFERROR(INDEX('Menu Master'!$C$4:$C$60,MATCH(E11,'Menu Master'!$A$4:$A$60,0)),"") | I11: =IFERROR(INDEX('Daily Sales'!$D$5:$D$30,MATCH(E11,'Daily Sales'!$A$5:$A$30,0)),0) -> 0 | J11: =H11*I11 -> 0 | K11: =H11*IFERROR(INDEX('Daily Sales'!$E$5:$E$30,MATCH(E11,'Daily Sales'!$A$5:$A$30,0)),0) -> 0
A12: =IF(E12="","","VD-"&TEXT(ROW()-4,"000")) | F12: =IFERROR(INDEX('Menu Master'!$B$4:$B$60,MATCH(E12,'Menu Master'!$A$4:$A$60,0)),"") | G12: =IFERROR(INDEX('Menu Master'!$C$4:$C$60,MATCH(E12,'Menu Master'!$A$4:$A$60,0)),"") | I12: =IFERROR(INDEX('Daily Sales'!$D$5:$D$30,MATCH(E12,'Daily Sales'!$A$5:$A$30,0)),0) -> 0 | J12: =H12*I12 -> 0 | K12: =H12*IFERROR(INDEX('Daily Sales'!$E$5:$E$30,MATCH(E12,'Daily Sales'!$A$5:$A$30,0)),0) -> 0
A13: =IF(E13="","","VD-"&TEXT(ROW()-4,"000")) | F13: =IFERROR(INDEX('Menu Master'!$B$4:$B$60,MATCH(E13,'Menu Master'!$A$4:$A$60,0)),"") | G13: =IFERROR(INDEX('Menu Master'!$C$4:$C$60,MATCH(E13,'Menu Master'!$A$4:$A$60,0)),"") | I13: =IFERROR(INDEX('Daily Sales'!$D$5:$D$30,MATCH(E13,'Daily Sales'!$A$5:$A$30,0)),0) -> 0 | J13: =H13*I13 -> 0 | K13: =H13*IFERROR(INDEX('Daily Sales'!$E$5:$E$30,MATCH(E13,'Daily Sales'!$A$5:$A$30,0)),0) -> 0
A14: =IF(E14="","","VD-"&TEXT(ROW()-4,"000")) | F14: =IFERROR(INDEX('Menu Master'!$B$4:$B$60,MATCH(E14,'Menu Master'!$A$4:$A$60,0)),"") | G14: =IFERROR(INDEX('Menu Master'!$C$4:$C$60,MATCH(E14,'Menu Master'!$A$4:$A$60,0)),"") | I14: =IFERROR(INDEX('Daily Sales'!$D$5:$D$30,MATCH(E14,'Daily Sales'!$A$5:$A$30,0)),0) -> 0 | J14: =H14*I14 -> 0 | K14: =H14*IFERROR(INDEX('Daily Sales'!$E$5:$E$30,MATCH(E14,'Daily Sales'!$A$5:$A$30,0)),0) -> 0
A15: =IF(E15="","","VD-"&TEXT(ROW()-4,"000")) | F15: =IFERROR(INDEX('Menu Master'!$B$4:$B$60,MATCH(E15,'Menu Master'!$A$4:$A$60,0)),"") | G15: =IFERROR(INDEX('Menu Master'!$C$4:$C$60,MATCH(E15,'Menu Master'!$A$4:$A$60,0)),"") | I15: =IFERROR(INDEX('Daily Sales'!$D$5:$D$30,MATCH(E15,'Daily Sales'!$A$5:$A$30,0)),0) -> 0 | J15: =H15*I15 -> 0 | K15: =H15*IFERROR(INDEX('Daily Sales'!$E$5:$E$30,MATCH(E15,'Daily Sales'!$A$5:$A$30,0)),0) -> 0
A16: =IF(E16="","","VD-"&TEXT(ROW()-4,"000")) | F16: =IFERROR(INDEX('Menu Master'!$B$4:$B$60,MATCH(E16,'Menu Master'!$A$4:$A$60,0)),"") | G16: =IFERROR(INDEX('Menu Master'!$C$4:$C$60,MATCH(E16,'Menu Master'!$A$4:$A$60,0)),"") | I16: =IFERROR(INDEX('Daily Sales'!$D$5:$D$30,MATCH(E16,'Daily Sales'!$A$5:$A$30,0)),0) -> 0 | J16: =H16*I16 -> 0 | K16: =H16*IFERROR(INDEX('Daily Sales'!$E$5:$E$30,MATCH(E16,'Daily Sales'!$A$5:$A$30,0)),0) -> 0
A17: =IF(E17="","","VD-"&TEXT(ROW()-4,"000")) | F17: =IFERROR(INDEX('Menu Master'!$B$4:$B$60,MATCH(E17,'Menu Master'!$A$4:$A$60,0)),"") | G17: =IFERROR(INDEX('Menu Master'!$C$4:$C$60,MATCH(E17,'Menu Master'!$A$4:$A$60,0)),"") | I17: =IFERROR(INDEX('Daily Sales'!$D$5:$D$30,MATCH(E17,'Daily Sales'!$A$5:$A$30,0)),0) -> 0 | J17: =H17*I17 -> 0 | K17: =H17*IFERROR(INDEX('Daily Sales'!$E$5:$E$30,MATCH(E17,'Daily Sales'!$A$5:$A$30,0)),0) -> 0
A18: =IF(E18="","","VD-"&TEXT(ROW()-4,"000")) | F18: =IFERROR(INDEX('Menu Master'!$B$4:$B$60,MATCH(E18,'Menu Master'!$A$4:$A$60,0)),"") | G18: =IFERROR(INDEX('Menu Master'!$C$4:$C$60,MATCH(E18,'Menu Master'!$A$4:$A$60,0)),"") | I18: =IFERROR(INDEX('Daily Sales'!$D$5:$D$30,MATCH(E18,'Daily Sales'!$A$5:$A$30,0)),0) -> 0 | J18: =H18*I18 -> 0 | K18: =H18*IFERROR(INDEX('Daily Sales'!$E$5:$E$30,MATCH(E18,'Daily Sales'!$A$5:$A$30,0)),0) -> 0
... A44: =IF(E44="","","VD-"&TEXT(ROW()-4,"000")) | F44: =IFERROR(INDEX('Menu Master'!$B$4:$B$60,MATCH(E44,'Menu Master'!$A$4:$A$60,0)),"") | G44: =IFERROR(INDEX('Menu Master'!$C$4:$C$60,MATCH(E44,'Menu Master'!$A$4:$A$60,0)),"") | I44: =IFERROR(INDEX('Daily Sales'!$D$5:$D$30,MATCH(E44,'Daily Sales'!$A$5:$A$30,0)),0) -> 0 | J44: =H44*I44 -> 0 | K44: =H44*IFERROR(INDEX('Daily Sales'!$E$5:$E$30,MATCH(E44,'Daily Sales'!$A$5:$A$30,0)),0) -> 0

Sheet Complementary
A1: COMPLEMENTARY
A2: Food and drink given away free — management comps, guest recovery, tastings
A4: Comp No. | B4: Date | C4: Time | D4: Bill No. | E4: Menu Code | F4: Menu Item | G4: Category | H4: Qty | I4: Selling Price | J4: Sales Value | K4: Standard Cost | L4: Cost Value | M4: Reason | N4: Guest / Company | O4: Authorized By | P4: Remarks
A5: =IF(E5="","","CMP-"&TEXT(ROW()-4,"000")) -> CMP-001 | B5: 46206 | C5: 13:10 | D5: B-1071 | E5: BM001 | F5: =IFERROR(INDEX('Menu Master'!$B$4:$B$60,MATCH(E5,'Menu Master'!$A$4:$A$60,0)),"") -> Americano | G5: =IFERROR(INDEX('Menu Master'!$C$4:$C$60,MATCH(E5,'Menu Master'!$A$4:$A$60,0)),"") -> Beverage | H5: 2 | I5: =IFERROR(INDEX('Daily Sales'!$D$5:$D$30,MATCH(E5,'Daily Sales'!$A$5:$A$30,0)),0) -> 90 | J5: =H5*I5 -> 180 | K5: =IFERROR(INDEX('Daily Sales'!$E$5:$E$30,MATCH(E5,'Daily Sales'!$A$5:$A$30,0)),0) -> 16.2 | L5: =H5*K5 -> 32.4 | M5: Manager Comp | N5: Regular guest | O5: Manager K
A6: =IF(E6="","","CMP-"&TEXT(ROW()-4,"000")) | F6: =IFERROR(INDEX('Menu Master'!$B$4:$B$60,MATCH(E6,'Menu Master'!$A$4:$A$60,0)),"") | G6: =IFERROR(INDEX('Menu Master'!$C$4:$C$60,MATCH(E6,'Menu Master'!$A$4:$A$60,0)),"") | I6: =IFERROR(INDEX('Daily Sales'!$D$5:$D$30,MATCH(E6,'Daily Sales'!$A$5:$A$30,0)),0) -> 0 | J6: =H6*I6 -> 0 | K6: =IFERROR(INDEX('Daily Sales'!$E$5:$E$30,MATCH(E6,'Daily Sales'!$A$5:$A$30,0)),0) -> 0 | L6: =H6*K6 -> 0
A7: =IF(E7="","","CMP-"&TEXT(ROW()-4,"000")) | F7: =IFERROR(INDEX('Menu Master'!$B$4:$B$60,MATCH(E7,'Menu Master'!$A$4:$A$60,0)),"") | G7: =IFERROR(INDEX('Menu Master'!$C$4:$C$60,MATCH(E7,'Menu Master'!$A$4:$A$60,0)),"") | I7: =IFERROR(INDEX('Daily Sales'!$D$5:$D$30,MATCH(E7,'Daily Sales'!$A$5:$A$30,0)),0) -> 0 | J7: =H7*I7 -> 0 | K7: =IFERROR(INDEX('Daily Sales'!$E$5:$E$30,MATCH(E7,'Daily Sales'!$A$5:$A$30,0)),0) -> 0 | L7: =H7*K7 -> 0
A8: =IF(E8="","","CMP-"&TEXT(ROW()-4,"000")) | F8: =IFERROR(INDEX('Menu Master'!$B$4:$B$60,MATCH(E8,'Menu Master'!$A$4:$A$60,0)),"") | G8: =IFERROR(INDEX('Menu Master'!$C$4:$C$60,MATCH(E8,'Menu Master'!$A$4:$A$60,0)),"") | I8: =IFERROR(INDEX('Daily Sales'!$D$5:$D$30,MATCH(E8,'Daily Sales'!$A$5:$A$30,0)),0) -> 0 | J8: =H8*I8 -> 0 | K8: =IFERROR(INDEX('Daily Sales'!$E$5:$E$30,MATCH(E8,'Daily Sales'!$A$5:$A$30,0)),0) -> 0 | L8: =H8*K8 -> 0
A9: =IF(E9="","","CMP-"&TEXT(ROW()-4,"000")) | F9: =IFERROR(INDEX('Menu Master'!$B$4:$B$60,MATCH(E9,'Menu Master'!$A$4:$A$60,0)),"") | G9: =IFERROR(INDEX('Menu Master'!$C$4:$C$60,MATCH(E9,'Menu Master'!$A$4:$A$60,0)),"") | I9: =IFERROR(INDEX('Daily Sales'!$D$5:$D$30,MATCH(E9,'Daily Sales'!$A$5:$A$30,0)),0) -> 0 | J9: =H9*I9 -> 0 | K9: =IFERROR(INDEX('Daily Sales'!$E$5:$E$30,MATCH(E9,'Daily Sales'!$A$5:$A$30,0)),0) -> 0 | L9: =H9*K9 -> 0
A10: =IF(E10="","","CMP-"&TEXT(ROW()-4,"000")) | F10: =IFERROR(INDEX('Menu Master'!$B$4:$B$60,MATCH(E10,'Menu Master'!$A$4:$A$60,0)),"") | G10: =IFERROR(INDEX('Menu Master'!$C$4:$C$60,MATCH(E10,'Menu Master'!$A$4:$A$60,0)),"") | I10: =IFERROR(INDEX('Daily Sales'!$D$5:$D$30,MATCH(E10,'Daily Sales'!$A$5:$A$30,0)),0) -> 0 | J10: =H10*I10 -> 0 | K10: =IFERROR(INDEX('Daily Sales'!$E$5:$E$30,MATCH(E10,'Daily Sales'!$A$5:$A$30,0)),0) -> 0 | L10: =H10*K10 -> 0
A11: =IF(E11="","","CMP-"&TEXT(ROW()-4,"000")) | F11: =IFERROR(INDEX('Menu Master'!$B$4:$B$60,MATCH(E11,'Menu Master'!$A$4:$A$60,0)),"") | G11: =IFERROR(INDEX('Menu Master'!$C$4:$C$60,MATCH(E11,'Menu Master'!$A$4:$A$60,0)),"") | I11: =IFERROR(INDEX('Daily Sales'!$D$5:$D$30,MATCH(E11,'Daily Sales'!$A$5:$A$30,0)),0) -> 0 | J11: =H11*I11 -> 0 | K11: =IFERROR(INDEX('Daily Sales'!$E$5:$E$30,MATCH(E11,'Daily Sales'!$A$5:$A$30,0)),0) -> 0 | L11: =H11*K11 -> 0
A12: =IF(E12="","","CMP-"&TEXT(ROW()-4,"000")) | F12: =IFERROR(INDEX('Menu Master'!$B$4:$B$60,MATCH(E12,'Menu Master'!$A$4:$A$60,0)),"") | G12: =IFERROR(INDEX('Menu Master'!$C$4:$C$60,MATCH(E12,'Menu Master'!$A$4:$A$60,0)),"") | I12: =IFERROR(INDEX('Daily Sales'!$D$5:$D$30,MATCH(E12,'Daily Sales'!$A$5:$A$30,0)),0) -> 0 | J12: =H12*I12 -> 0 | K12: =IFERROR(INDEX('Daily Sales'!$E$5:$E$30,MATCH(E12,'Daily Sales'!$A$5:$A$30,0)),0) -> 0 | L12: =H12*K12 -> 0
A13: =IF(E13="","","CMP-"&TEXT(ROW()-4,"000")) | F13: =IFERROR(INDEX('Menu Master'!$B$4:$B$60,MATCH(E13,'Menu Master'!$A$4:$A$60,0)),"") | G13: =IFERROR(INDEX('Menu Master'!$C$4:$C$60,MATCH(E13,'Menu Master'!$A$4:$A$60,0)),"") | I13: =IFERROR(INDEX('Daily Sales'!$D$5:$D$30,MATCH(E13,'Daily Sales'!$A$5:$A$30,0)),0) -> 0 | J13: =H13*I13 -> 0 | K13: =IFERROR(INDEX('Daily Sales'!$E$5:$E$30,MATCH(E13,'Daily Sales'!$A$5:$A$30,0)),0) -> 0 | L13: =H13*K13 -> 0
A14: =IF(E14="","","CMP-"&TEXT(ROW()-4,"000")) | F14: =IFERROR(INDEX('Menu Master'!$B$4:$B$60,MATCH(E14,'Menu Master'!$A$4:$A$60,0)),"") | G14: =IFERROR(INDEX('Menu Master'!$C$4:$C$60,MATCH(E14,'Menu Master'!$A$4:$A$60,0)),"") | I14: =IFERROR(INDEX('Daily Sales'!$D$5:$D$30,MATCH(E14,'Daily Sales'!$A$5:$A$30,0)),0) -> 0 | J14: =H14*I14 -> 0 | K14: =IFERROR(INDEX('Daily Sales'!$E$5:$E$30,MATCH(E14,'Daily Sales'!$A$5:$A$30,0)),0) -> 0 | L14: =H14*K14 -> 0
A15: =IF(E15="","","CMP-"&TEXT(ROW()-4,"000")) | F15: =IFERROR(INDEX('Menu Master'!$B$4:$B$60,MATCH(E15,'Menu Master'!$A$4:$A$60,0)),"") | G15: =IFERROR(INDEX('Menu Master'!$C$4:$C$60,MATCH(E15,'Menu Master'!$A$4:$A$60,0)),"") | I15: =IFERROR(INDEX('Daily Sales'!$D$5:$D$30,MATCH(E15,'Daily Sales'!$A$5:$A$30,0)),0) -> 0 | J15: =H15*I15 -> 0 | K15: =IFERROR(INDEX('Daily Sales'!$E$5:$E$30,MATCH(E15,'Daily Sales'!$A$5:$A$30,0)),0) -> 0 | L15: =H15*K15 -> 0
A16: =IF(E16="","","CMP-"&TEXT(ROW()-4,"000")) | F16: =IFERROR(INDEX('Menu Master'!$B$4:$B$60,MATCH(E16,'Menu Master'!$A$4:$A$60,0)),"") | G16: =IFERROR(INDEX('Menu Master'!$C$4:$C$60,MATCH(E16,'Menu Master'!$A$4:$A$60,0)),"") | I16: =IFERROR(INDEX('Daily Sales'!$D$5:$D$30,MATCH(E16,'Daily Sales'!$A$5:$A$30,0)),0) -> 0 | J16: =H16*I16 -> 0 | K16: =IFERROR(INDEX('Daily Sales'!$E$5:$E$30,MATCH(E16,'Daily Sales'!$A$5:$A$30,0)),0) -> 0 | L16: =H16*K16 -> 0
A17: =IF(E17="","","CMP-"&TEXT(ROW()-4,"000")) | F17: =IFERROR(INDEX('Menu Master'!$B$4:$B$60,MATCH(E17,'Menu Master'!$A$4:$A$60,0)),"") | G17: =IFERROR(INDEX('Menu Master'!$C$4:$C$60,MATCH(E17,'Menu Master'!$A$4:$A$60,0)),"") | I17: =IFERROR(INDEX('Daily Sales'!$D$5:$D$30,MATCH(E17,'Daily Sales'!$A$5:$A$30,0)),0) -> 0 | J17: =H17*I17 -> 0 | K17: =IFERROR(INDEX('Daily Sales'!$E$5:$E$30,MATCH(E17,'Daily Sales'!$A$5:$A$30,0)),0) -> 0 | L17: =H17*K17 -> 0
... A44: =IF(E44="","","CMP-"&TEXT(ROW()-4,"000")) | F44: =IFERROR(INDEX('Menu Master'!$B$4:$B$60,MATCH(E44,'Menu Master'!$A$4:$A$60,0)),"") | G44: =IFERROR(INDEX('Menu Master'!$C$4:$C$60,MATCH(E44,'Menu Master'!$A$4:$A$60,0)),"") | I44: =IFERROR(INDEX('Daily Sales'!$D$5:$D$30,MATCH(E44,'Daily Sales'!$A$5:$A$30,0)),0) -> 0 | J44: =H44*I44 -> 0 | K44: =IFERROR(INDEX('Daily Sales'!$E$5:$E$30,MATCH(E44,'Daily Sales'!$A$5:$A$30,0)),0) -> 0 | L44: =H44*K44 -> 0

Sheet Daily Staff Meal
A1: DAILY STAFF MEAL
A2: Meals prepared for staff — costed at raw-ingredient standard cost
A4: Entry No. | B4: Date | C4: Item Code | D4: Item / Meal Name | E4: Category | F4: Qty | G4: Unit Cost | H4: Total Cost | I4: Authorized By | J4: Remarks
A5: =IF(C5="","","SM-"&TEXT(ROW()-4,"000")) -> SM-001 | B5: 46205 | C5: FD002 | D5: Chicken Breast (Boneless) | E5: Food | F5: 2 | G5: =IFERROR(INDEX('Item Master'!$E$4:$E$41,MATCH(C5,'Item Master'!$A$4:$A$41,0)),0) -> 480 | H5: =F5*G5 -> 960 | I5: Manager K | J5: Staff lunch
A6: =IF(C6="","","SM-"&TEXT(ROW()-4,"000")) -> SM-002 | B6: 46206 | C6: FD011 | D6: Spaghetti Pasta | E6: Food | F6: 1.5 | G6: =IFERROR(INDEX('Item Master'!$E$4:$E$41,MATCH(C6,'Item Master'!$A$4:$A$41,0)),0) -> 120 | H6: =F6*G6 -> 180 | I6: Manager K | J6: Staff lunch
A7: =IF(C7="","","SM-"&TEXT(ROW()-4,"000")) -> SM-003 | B7: 46207 | C7: FD010 | D7: Fresh Eggs | E7: Food | F7: 6 | G7: =IFERROR(INDEX('Item Master'!$E$4:$E$41,MATCH(C7,'Item Master'!$A$4:$A$41,0)),0) -> 8 | H7: =F7*G7 -> 48 | I7: Manager K | J7: Staff breakfast
A8: =IF(C8="","","SM-"&TEXT(ROW()-4,"000")) | G8: =IFERROR(INDEX('Item Master'!$E$4:$E$41,MATCH(C8,'Item Master'!$A$4:$A$41,0)),0) -> 0 | H8: =F8*G8 -> 0
A9: =IF(C9="","","SM-"&TEXT(ROW()-4,"000")) | G9: =IFERROR(INDEX('Item Master'!$E$4:$E$41,MATCH(C9,'Item Master'!$A$4:$A$41,0)),0) -> 0 | H9: =F9*G9 -> 0
A10: =IF(C10="","","SM-"&TEXT(ROW()-4,"000")) | G10: =IFERROR(INDEX('Item Master'!$E$4:$E$41,MATCH(C10,'Item Master'!$A$4:$A$41,0)),0) -> 0 | H10: =F10*G10 -> 0
A11: =IF(C11="","","SM-"&TEXT(ROW()-4,"000")) | G11: =IFERROR(INDEX('Item Master'!$E$4:$E$41,MATCH(C11,'Item Master'!$A$4:$A$41,0)),0) -> 0 | H11: =F11*G11 -> 0
A12: =IF(C12="","","SM-"&TEXT(ROW()-4,"000")) | G12: =IFERROR(INDEX('Item Master'!$E$4:$E$41,MATCH(C12,'Item Master'!$A$4:$A$41,0)),0) -> 0 | H12: =F12*G12 -> 0
A13: =IF(C13="","","SM-"&TEXT(ROW()-4,"000")) | G13: =IFERROR(INDEX('Item Master'!$E$4:$E$41,MATCH(C13,'Item Master'!$A$4:$A$41,0)),0) -> 0 | H13: =F13*G13 -> 0
A14: =IF(C14="","","SM-"&TEXT(ROW()-4,"000")) | G14: =IFERROR(INDEX('Item Master'!$E$4:$E$41,MATCH(C14,'Item Master'!$A$4:$A$41,0)),0) -> 0 | H14: =F14*G14 -> 0
A15: =IF(C15="","","SM-"&TEXT(ROW()-4,"000")) | G15: =IFERROR(INDEX('Item Master'!$E$4:$E$41,MATCH(C15,'Item Master'!$A$4:$A$41,0)),0) -> 0 | H15: =F15*G15 -> 0
A16: =IF(C16="","","SM-"&TEXT(ROW()-4,"000")) | G16: =IFERROR(INDEX('Item Master'!$E$4:$E$41,MATCH(C16,'Item Master'!$A$4:$A$41,0)),0) -> 0 | H16: =F16*G16 -> 0
A17: =IF(C17="","","SM-"&TEXT(ROW()-4,"000")) | G17: =IFERROR(INDEX('Item Master'!$E$4:$E$41,MATCH(C17,'Item Master'!$A$4:$A$41,0)),0) -> 0 | H17: =F17*G17 -> 0
A18: =IF(C18="","","SM-"&TEXT(ROW()-4,"000")) | G18: =IFERROR(INDEX('Item Master'!$E$4:$E$41,MATCH(C18,'Item Master'!$A$4:$A$41,0)),0) -> 0 | H18: =F18*G18 -> 0
A19: =IF(C19="","","SM-"&TEXT(ROW()-4,"000")) | G19: =IFERROR(INDEX('Item Master'!$E$4:$E$41,MATCH(C19,'Item Master'!$A$4:$A$41,0)),0) -> 0 | H19: =F19*G19 -> 0
... A44: =IF(C44="","","SM-"&TEXT(ROW()-4,"000")) | G44: =IFERROR(INDEX('Item Master'!$E$4:$E$41,MATCH(C44,'Item Master'!$A$4:$A$41,0)),0) -> 0 | H44: =F44*G44 -> 0

Sheet Daily Sales
A1: DAILY SALES
A2: Every menu item sold, day by day for the month — drives Flash Cost, Variance & Menu Engineering
A4: MENU CODE | B4: MENU ITEM | C4: CATEGORY | D4: SELLING PRICE | E4: STANDARD COST | F4: Day 1 | G4: Day 2 | H4: Day 3 | I4: Day 4 | J4: Day 5 | K4: Day 6 | L4: Day 7 | M4: Day 8 | N4: Day 9 | O4: Day 10 | P4: Day 11 | Q4: Day 12 | R4: Day 13 | S4: Day 14 | T4: Day 15 | U4: Day 16 | V4: Day 17 | W4: Day 18 | X4: Day 19 | Y4: Day 20 | Z4: Day 21 | AA4: Day 22 | AB4: Day 23 | AC4: Day 24 | AD4: Day 25 | AE4: Day 26 | AF4: Day 27 | AG4: Day 28 | AH4: Day 29 | AI4: Day 30 | AJ4: Day 31 | AK4: MONTHLY QTY | AL4: MONTHLY SALES (ETB) | AM4: MONTHLY THEO. COST (ETB)
A5: ='Menu Master'!A6 -> FM001 | B5: ='Menu Master'!B6 -> Classic Beef Burger | C5: ='Menu Master'!C6 -> Food | D5: 320 | E5: ='Recipe Master'!H12 -> 106.15 | F5: 16 | G5: 11 | H5: 11 | I5: 16 | J5: 13 | K5: 12 | L5: 12 | AK5: =SUM(F5:AJ5) -> 91 | AL5: =AK5*D5 -> 29120 | AM5: =AK5*E5 -> 9659.65
A6: ='Menu Master'!A7 -> FM002 | B6: ='Menu Master'!B7 -> Double Beef Burger | C6: ='Menu Master'!C7 -> Food | D6: 420 | E6: ='Recipe Master'!H22 -> 200.65 | F6: 4 | G6: 8 | H6: 3 | I6: 8 | J6: 8 | K6: 7 | L6: 3 | AK6: =SUM(F6:AJ6) -> 41 | AL6: =AK6*D6 -> 17220 | AM6: =AK6*E6 -> 8226.65
A7: ='Menu Master'!A9 -> FM003 | B7: ='Menu Master'!B9 -> Chicken Caesar Wrap | C7: ='Menu Master'!C9 -> Food | D7: 280 | E7: ='Recipe Master'!H29 -> 107.4 | F7: 10 | G7: 9 | H7: 6 | I7: 6 | J7: 6 | K7: 7 | L7: 7 | AK7: =SUM(F7:AJ7) -> 51 | AL7: =AK7*D7 -> 14280 | AM7: =AK7*E7 -> 5477.4
A8: ='Menu Master'!A10 -> FM004 | B8: ='Menu Master'!B10 -> Crispy Chicken Wrap | C8: ='Menu Master'!C10 -> Food | D8: 260 | E8: ='Recipe Master'!H37 -> 103.7 | F8: 9 | G8: 9 | H8: 5 | I8: 9 | J8: 6 | K8: 10 | L8: 10 | AK8: =SUM(F8:AJ8) -> 58 | AL8: =AK8*D8 -> 15080 | AM8: =AK8*E8 -> 6014.6
A9: ='Menu Master'!A12 -> FM005 | B9: ='Menu Master'!B12 -> Club Sandwich | C9: ='Menu Master'!C12 -> Food | D9: 300 | E9: ='Recipe Master'!H46 -> 99.75 | F9: 9 | G9: 8 | H9: 7 | I9: 5 | J9: 7 | K9: 8 | L9: 6 | AK9: =SUM(F9:AJ9) -> 50 | AL9: =AK9*D9 -> 15000 | AM9: =AK9*E9 -> 4987.5
A10: ='Menu Master'!A13 -> FM006 | B10: ='Menu Master'!B13 -> Chicken Sandwich | C10: ='Menu Master'!C13 -> Food | D10: 240 | E10: ='Recipe Master'!H53 -> 64.3 | F10: 9 | G10: 9 | H10: 3 | I10: 9 | J10: 9 | K10: 4 | L10: 8 | AK10: =SUM(F10:AJ10) -> 51 | AL10: =AK10*D10 -> 12240 | AM10: =AK10*E10 -> 3279.3
A11: ='Menu Master'!A15 -> FM007 | B11: ='Menu Master'!B15 -> Spaghetti Bolognese | C11: ='Menu Master'!C15 -> Food | D11: 350 | E11: ='Recipe Master'!H58 -> 36.4 | F11: 10 | G11: 9 | H11: 9 | I11: 8 | J11: 8 | K11: 13 | L11: 9 | AK11: =SUM(F11:AJ11) -> 66 | AL11: =AK11*D11 -> 23100 | AM11: =AK11*E11 -> 2402.4
A12: ='Menu Master'!A16 -> FM008 | B12: ='Menu Master'!B16 -> Spaghetti Alfredo | C12: ='Menu Master'!C16 -> Food | D12: 330 | E12: ='Recipe Master'!H63 -> 62.4 | F12: 5 | G12: 5 | H12: 8 | I12: 5 | J12: 7 | K12: 11 | L12: 7 | AK12: =SUM(F12:AJ12) -> 48 | AL12: =AK12*D12 -> 15840 | AM12: =AK12*E12 -> 2995.2
A13: ='Menu Master'!A18 -> FM009 | B13: ='Menu Master'!B18 -> American Breakfast | C13: ='Menu Master'!C18 -> Food | D13: 280 | E13: ='Recipe Master'!H70 -> 74.6 | F13: 6 | G13: 4 | H13: 8 | I13: 2 | J13: 7 | K13: 5 | L13: 6 | AK13: =SUM(F13:AJ13) -> 38 | AL13: =AK13*D13 -> 10640 | AM13: =AK13*E13 -> 2834.8
A14: ='Menu Master'!A19 -> FM010 | B14: ='Menu Master'!B19 -> Continental Breakfast | C14: ='Menu Master'!C19 -> Food | D14: 260 | E14: ='Recipe Master'!H76 -> 16.8 | F14: 1 | G14: 4 | H14: 1 | I14: 5 | J14: 3 | K14: 7 | L14: 6 | AK14: =SUM(F14:AJ14) -> 27 | AL14: =AK14*D14 -> 7020 | AM14: =AK14*E14 -> 453.6
A15: ='Menu Master'!A21 -> FM011 | B15: ='Menu Master'!B21 -> Butter Croissant | C15: ='Menu Master'!C21 -> Food | D15: 110 | E15: ='Recipe Master'!H80 -> 9.6 | F15: 13 | G15: 15 | H15: 11 | I15: 13 | J15: 10 | K15: 14 | L15: 9 | AK15: =SUM(F15:AJ15) -> 85 | AL15: =AK15*D15 -> 9350 | AM15: =AK15*E15 -> 816
A16: ='Menu Master'!A22 -> FM012 | B16: ='Menu Master'!B22 -> Danish Pastry | C16: ='Menu Master'!C22 -> Food | D16: 120 | E16: ='Recipe Master'!H84 -> 4.8 | F16: 6 | G16: 11 | H16: 7 | I16: 12 | J16: 8 | K16: 6 | L16: 12 | AK16: =SUM(F16:AJ16) -> 62 | AL16: =AK16*D16 -> 7440 | AM16: =AK16*E16 -> 297.6
A17: ='Menu Master'!A24 -> FM013 | B17: ='Menu Master'!B24 -> Chicken Caesar Salad | C17: ='Menu Master'!C24 -> Food | D17: 260 | E17: ='Recipe Master'!H90 -> 76 | F17: 4 | G17: 9 | H17: 3 | I17: 6 | J17: 5 | K17: 6 | L17: 8 | AK17: =SUM(F17:AJ17) -> 41 | AL17: =AK17*D17 -> 10660 | AM17: =AK17*E17 -> 3116
A18: ='Menu Master'!A25 -> FM014 | B18: ='Menu Master'!B25 -> Avocado Salad | C18: ='Menu Master'!C25 -> Food | D18: 180 | E18: ='Recipe Master'!H97 -> 26.05 | F18: 8 | G18: 4 | H18: 3 | I18: 4 | J18: 4 | K18: 3 | L18: 7 | AK18: =SUM(F18:AJ18) -> 33 | AL18: =AK18*D18 -> 5940 | AM18: =AK18*E18 -> 859.65
A19: ='Menu Master'!A27 -> FM015 | B19: ='Menu Master'!B27 -> Margherita Pizza | C19: ='Menu Master'!C27 -> Food | D19: 380 | E19: ='Recipe Master'!H102 -> 93 | F19: 10 | G19: 13 | H19: 13 | I19: 13 | J19: 8 | K19: 12 | L19: 13 | AK19: =SUM(F19:AJ19) -> 82 | AL19: =AK19*D19 -> 31160 | AM19: =AK19*E19 -> 7626
A20: ='Menu Master'!A30 -> BM001 | B20: ='Menu Master'!B30 -> Americano | C20: ='Menu Master'!C30 -> Beverage | D20: 90 | E20: ='Recipe Master'!H105 -> 16.2 | F20: 18 | G20: 21 | H20: 22 | I20: 18 | J20: 18 | K20: 20 | L20: 20 | AK20: =SUM(F20:AJ20) -> 137 | AL20: =AK20*D20 -> 12330 | AM20: =AK20*E20 -> 2219.4
A21: ='Menu Master'!A31 -> BM002 | B21: ='Menu Master'!B31 -> Cappuccino | C21: ='Menu Master'!C31 -> Beverage | D21: 110 | E21: ='Recipe Master'!H109 -> 25.95 | F21: 21 | G21: 24 | H21: 24 | I21: 23 | J21: 20 | K21: 24 | L21: 21 | AK21: =SUM(F21:AJ21) -> 157 | AL21: =AK21*D21 -> 17270 | AM21: =AK21*E21 -> 4074.15
A22: ='Menu Master'!A33 -> BM003 | B22: ='Menu Master'!B33 -> English Breakfast Tea | C22: ='Menu Master'!C33 -> Beverage | D22: 70 | E22: ='Recipe Master'!H113 -> 6.25 | F22: 13 | G22: 13 | H22: 13 | I22: 7 | J22: 8 | K22: 13 | L22: 7 | AK22: =SUM(F22:AJ22) -> 74 | AL22: =AK22*D22 -> 5180 | AM22: =AK22*E22 -> 462.5
A23: ='Menu Master'!A34 -> BM004 | B23: ='Menu Master'!B34 -> Green Tea | C23: ='Menu Master'!C34 -> Beverage | D23: 70 | E23: ='Recipe Master'!H116 -> 4 | F23: 11 | G23: 7 | H23: 8 | I23: 7 | J23: 5 | K23: 6 | L23: 9 | AK23: =SUM(F23:AJ23) -> 53 | AL23: =AK23*D23 -> 3710 | AM23: =AK23*E23 -> 212
A24: ='Menu Master'!A36 -> BM005 | B24: ='Menu Master'!B36 -> Hot Chocolate | C24: ='Menu Master'!C36 -> Beverage | D24: 100 | E24: ='Recipe Master'!H120 -> 23.5 | F24: 9 | G24: 6 | H24: 5 | I24: 9 | J24: 7 | K24: 7 | L24: 9 | AK24: =SUM(F24:AJ24) -> 52 | AL24: =AK24*D24 -> 5200 | AM24: =AK24*E24 -> 1222
A25: ='Menu Master'!A38 -> BM006 | B25: ='Menu Master'!B38 -> Classic Mojito | C25: ='Menu Master'!C38 -> Beverage | D25: 220 | E25: ='Recipe Master'!H125 -> 54.25 | F25: 9 | G25: 7 | H25: 8 | I25: 7 | J25: 7 | K25: 11 | L25: 10 | AK25: =SUM(F25:AJ25) -> 59 | AL25: =AK25*D25 -> 12980 | AM25: =AK25*E25 -> 3200.75
A26: ='Menu Master'!A39 -> BM007 | B26: ='Menu Master'!B39 -> Strawberry Mojito | C26: ='Menu Master'!C39 -> Beverage | D26: 250 | E26: ='Recipe Master'!H131 -> 59.25 | F26: 7 | G26: 5 | H26: 8 | I26: 7 | J26: 6 | K26: 7 | L26: 6 | AK26: =SUM(F26:AJ26) -> 46 | AL26: =AK26*D26 -> 11500 | AM26: =AK26*E26 -> 2725.5
A27: ='Menu Master'!A41 -> BM008 | B27: ='Menu Master'!B41 -> Fresh Avocado Juice | C27: ='Menu Master'!C41 -> Beverage | D27: 130 | E27: ='Recipe Master'!H136 -> 30.2 | F27: 7 | G27: 6 | H27: 6 | I27: 9 | J27: 8 | K27: 5 | L27: 11 | AK27: =SUM(F27:AJ27) -> 52 | AL27: =AK27*D27 -> 6760 | AM27: =AK27*E27 -> 1570.4
A28: ='Menu Master'!A43 -> BM009 | B28: ='Menu Master'!B43 -> Coca-Cola | C28: ='Menu Master'!C43 -> Beverage | D28: 70 | E28: ='Recipe Master'!H139 -> 35 | F28: 12 | G28: 18 | H28: 12 | I28: 13 | J28: 17 | K28: 13 | L28: 18 | AK28: =SUM(F28:AJ28) -> 103 | AL28: =AK28*D28 -> 7210 | AM28: =AK28*E28 -> 3605
A29: ='Menu Master'!A45 -> OM001 | B29: ='Menu Master'!B45 -> Burger Takeaway Box | C29: ='Menu Master'!C45 -> To-Go Material | D29: 10 | E29: ='Recipe Master'!H142 -> 8 | F29: 6 | G29: 4 | H29: 5 | I29: 1 | J29: 4 | K29: 4 | L29: 5 | AK29: =SUM(F29:AJ29) -> 29 | AL29: =AK29*D29 -> 290 | AM29: =AK29*E29 -> 232
A30: ='Menu Master'!A46 -> OM002 | B30: ='Menu Master'!B46 -> Pizza Takeaway Box | C30: ='Menu Master'!C46 -> To-Go Material | D30: 18 | E30: ='Recipe Master'!H145 -> 15 | F30: 3 | G30: 4 | H30: 2 | I30: 4 | J30: 6 | K30: 0 | L30: 5 | AK30: =SUM(F30:AJ30) -> 24 | AL30: =AK30*D30 -> 432 | AM30: =AK30*E30 -> 360

Sheet Theoretical Consumption
A1: THEORETICAL CONSUMPTION
A2: What SHOULD have been used per recipe, vs what was actually issued from the Main Store
A3: ITEM CODE | B3: ITEM NAME | C3: CATEGORY | D3: UOM | E3: AVG. COST | F3: Direct Recipe Usage | G3: Via Sub-Recipe Usage | H3: TOTAL THEORETICAL QTY | I3: THEORETICAL COST | J3: ACTUAL QTY ISSUED | K3: ACTUAL COST | L3: VARIANCE QTY | M3: VARIANCE COST | N3: VARIANCE %
A4: FOOD
A5: FD001 | B5: Beef Mince (80% Lean) | C5: Meat & Poultry | D5: Kg | E5: ='Store Inventory'!F5 -> 557.35294 | F5: =SUMIF('Recipe Master'!$D$4:$D$146,A5,'Recipe Master'!$J$4:$J$146) -> 25.95 | G5: =SUMIF('Sub-Recipe'!$D$4:$D$67,A5,'Sub-Recipe'!$N$4:$N$67) -> 8.25 | H5: =F5+G5 -> 34.2 | I5: =H5*E5 -> 19061.471 | J5: ='Store Issue'!P6 -> 36 | K5: =J5*E5 -> 20064.706 | L5: =J5-H5 -> 1.8 | M5: =K5-I5 -> 1003.2353 | N5: =IFERROR(L5/H5,0) -> 0.052631579
A6: FD002 | B6: Chicken Breast (Boneless) | C6: Meat & Poultry | D6: Kg | E6: ='Store Inventory'!F6 -> 482.66667 | F6: =SUMIF('Recipe Master'!$D$4:$D$146,A6,'Recipe Master'!$J$4:$J$146) -> 36.23 | G6: =SUMIF('Sub-Recipe'!$D$4:$D$67,A6,'Sub-Recipe'!$N$4:$N$67) -> 0 | H6: =F6+G6 -> 36.23 | I6: =H6*E6 -> 17487.013 | J6: ='Store Issue'!P7 -> 34 | K6: =J6*E6 -> 16410.667 | L6: =J6-H6 -> -2.23 | M6: =K6-I6 -> -1076.3467 | N6: =IFERROR(L6/H6,0) -> -0.061551201
A7: FD003 | B7: Bacon Strips | C7: Meat & Poultry | D7: Kg | E7: ='Store Inventory'!F7 -> 650 | F7: =SUMIF('Recipe Master'!$D$4:$D$146,A7,'Recipe Master'!$J$4:$J$146) -> 5.54 | G7: =SUMIF('Sub-Recipe'!$D$4:$D$67,A7,'Sub-Recipe'!$N$4:$N$67) -> 0 | H7: =F7+G7 -> 5.54 | I7: =H7*E7 -> 3601 | J7: ='Store Issue'!P8 -> 10 | K7: =J7*E7 -> 6500 | L7: =J7-H7 -> 4.46 | M7: =K7-I7 -> 2899 | N7: =IFERROR(L7/H7,0) -> 0.80505415
A8: FD004 | B8: Fresh Lettuce | C8: Fresh Produce | D8: Kg | E8: ='Store Inventory'!F8 -> 60 | F8: =SUMIF('Recipe Master'!$D$4:$D$146,A8,'Recipe Master'!$J$4:$J$146) -> 15.33 | G8: =SUMIF('Sub-Recipe'!$D$4:$D$67,A8,'Sub-Recipe'!$N$4:$N$67) -> 0 | H8: =F8+G8 -> 15.33 | I8: =H8*E8 -> 919.8 | J8: ='Store Issue'!P9 -> 23 | K8: =J8*E8 -> 1380 | L8: =J8-H8 -> 7.67 | M8: =K8-I8 -> 460.2 | N8: =IFERROR(L8/H8,0) -> 0.50032616
A9: FD005 | B9: Fresh Tomato | C9: Fresh Produce | D9: Kg | E9: ='Store Inventory'!F9 -> 56 | F9: =SUMIF('Recipe Master'!$D$4:$D$146,A9,'Recipe Master'!$J$4:$J$146) -> 8.13 | G9: =SUMIF('Sub-Recipe'!$D$4:$D$67,A9,'Sub-Recipe'!$N$4:$N$67) -> 12.325 | H9: =F9+G9 -> 20.455 | I9: =H9*E9 -> 1145.48 | J9: ='Store Issue'!P10 -> 23 | K9: =J9*E9 -> 1288 | L9: =J9-H9 -> 2.545 | M9: =K9-I9 -> 142.52 | N9: =IFERROR(L9/H9,0) -> 0.12441946
A10: FD006 | B10: Onion | C10: Fresh Produce | D10: Kg | E10: ='Store Inventory'!F10 -> 40 | F10: =SUMIF('Recipe Master'!$D$4:$D$146,A10,'Recipe Master'!$J$4:$J$146) -> 4.46 | G10: =SUMIF('Sub-Recipe'!$D$4:$D$67,A10,'Sub-Recipe'!$N$4:$N$67) -> 4.115 | H10: =F10+G10 -> 8.575 | I10: =H10*E10 -> 343 | J10: ='Store Issue'!P11 -> 10 | K10: =J10*E10 -> 400 | L10: =J10-H10 -> 1.425 | M10: =K10-I10 -> 57 | N10: =IFERROR(L10/H10,0) -> 0.16618076
A11: FD007 | B11: Cheddar Cheese Slice | C11: Dairy | D11: Pcs | E11: ='Store Inventory'!F11 -> 12 | F11: =SUMIF('Recipe Master'!$D$4:$D$146,A11,'Recipe Master'!$J$4:$J$146) -> 250 | G11: =SUMIF('Sub-Recipe'!$D$4:$D$67,A11,'Sub-Recipe'!$N$4:$N$67) -> 0 | H11: =F11+G11 -> 250 | I11: =H11*E11 -> 3000 | J11: ='Store Issue'!P12 -> 130 | K11: =J11*E11 -> 1560 | L11: =J11-H11 -> -120 | M11: =K11-I11 -> -1440 | N11: =IFERROR(L11/H11,0) -> -0.48
A12: FD008 | B12: All-Purpose Flour | C12: Bakery & Dry Goods | D12: Kg | E12: ='Store Inventory'!F12 -> 55 | F12: =SUMIF('Recipe Master'!$D$4:$D$146,A12,'Recipe Master'!$J$4:$J$146) -> 0 | G12: =SUMIF('Sub-Recipe'!$D$4:$D$67,A12,'Sub-Recipe'!$N$4:$N$67) -> 59.5 | H12: =F12+G12 -> 59.5 | I12: =H12*E12 -> 3272.5 | J12: ='Store Issue'!P13 -> 35 | K12: =J12*E12 -> 1925 | L12: =J12-H12 -> -24.5 | M12: =K12-I12 -> -1347.5 | N12: =IFERROR(L12/H12,0) -> -0.41176471
A13: FD009 | B13: Butter (Unsalted) | C13: Dairy | D13: Kg | E13: ='Store Inventory'!F13 -> 480 | F13: =SUMIF('Recipe Master'!$D$4:$D$146,A13,'Recipe Master'!$J$4:$J$146) -> 2.97 | G13: =SUMIF('Sub-Recipe'!$D$4:$D$67,A13,'Sub-Recipe'!$N$4:$N$67) -> 12.308 | H13: =F13+G13 -> 15.278 | I13: =H13*E13 -> 7333.44 | J13: ='Store Issue'!P14 -> 10 | K13: =J13*E13 -> 4800 | L13: =J13-H13 -> -5.278 | M13: =K13-I13 -> -2533.44 | N13: =IFERROR(L13/H13,0) -> -0.34546407
A14: FD010 | B14: Fresh Eggs | C14: Dairy | D14: Pcs | E14: ='Store Inventory'!F14 -> 8 | F14: =SUMIF('Recipe Master'!$D$4:$D$146,A14,'Recipe Master'!$J$4:$J$146) -> 76 | G14: =SUMIF('Sub-Recipe'!$D$4:$D$67,A14,'Sub-Recipe'!$N$4:$N$67) -> 35.6 | H14: =F14+G14 -> 111.6 | I14: =H14*E14 -> 892.8 | J14: ='Store Issue'!P15 -> 100 | K14: =J14*E14 -> 800 | L14: =J14-H14 -> -11.6 | M14: =K14-I14 -> -92.8 | N14: =IFERROR(L14/H14,0) -> -0.10394265
A15: FD011 | B15: Spaghetti Pasta | C15: Bakery & Dry Goods | D15: Kg | E15: ='Store Inventory'!F15 -> 120 | F15: =SUMIF('Recipe Master'!$D$4:$D$146,A15,'Recipe Master'!$J$4:$J$146) -> 22.8 | G15: =SUMIF('Sub-Recipe'!$D$4:$D$67,A15,'Sub-Recipe'!$N$4:$N$67) -> 0 | H15: =F15+G15 -> 22.8 | I15: =H15*E15 -> 2736 | J15: ='Store Issue'!P16 -> 18 | K15: =J15*E15 -> 2160 | L15: =J15-H15 -> -4.8 | M15: =K15-I15 -> -576 | N15: =IFERROR(L15/H15,0) -> -0.21052632
A16: FD012 | B16: Tortilla Wrap | C16: Bakery & Dry Goods | D16: Pcs | E16: ='Store Inventory'!F16 -> 15 | F16: =SUMIF('Recipe Master'!$D$4:$D$146,A16,'Recipe Master'!$J$4:$J$146) -> 109 | G16: =SUMIF('Sub-Recipe'!$D$4:$D$67,A16,'Sub-Recipe'!$N$4:$N$67) -> 0 | H16: =F16+G16 -> 109 | I16: =H16*E16 -> 1635 | J16: ='Store Issue'!P17 -> 55 | K16: =J16*E16 -> 825 | L16: =J16-H16 -> -54 | M16: =K16-I16 -> -810 | N16: =IFERROR(L16/H16,0) -> -0.49541284
... A19: FD015 | B19: Mozzarella Cheese | C19: Dairy | D19: Kg | E19: ='Store Inventory'!F19 -> 620 | F19: =SUMIF('Recipe Master'!$D$4:$D$146,A19,'Recipe Master'!$J$4:$J$146) -> 15.97 | G19: =SUMIF('Sub-Recipe'!$D$4:$D$67,A19,'Sub-Recipe'!$N$4:$N$67) -> 2.12 | H19: =F19+G19 -> 18.09 | I19: =H19*E19 -> 11215.8 | J19: ='Store Issue'!P20 -> 15 | K19: =J19*E19 -> 9300 | L19: =J19-H19 -> -3.09 | M19: =K19-I19 -> -1915.8 | N19: =IFERROR(L19/H19,0) -> -0.1708126
A20: BEVERAGE
A21: BV001 | B21: Coffee Beans (Roasted) | C21: Coffee & Tea | D21: Kg | E21: ='Store Inventory'!F21 -> 900 | F21: =SUMIF('Recipe Master'!$D$4:$D$146,A21,'Recipe Master'!$J$4:$J$146) -> 5.292 | G21: =SUMIF('Sub-Recipe'!$D$4:$D$67,A21,'Sub-Recipe'!$N$4:$N$67) -> 0 | H21: =F21+G21 -> 5.292 | I21: =H21*E21 -> 4762.8 | J21: ='Store Issue'!P22 -> 15 | K21: =J21*E21 -> 13500 | L21: =J21-H21 -> 9.708 | M21: =K21-I21 -> 8737.2 | N21: =IFERROR(L21/H21,0) -> 1.8344671
A22: BV002 | B22: Black Tea Bags | C22: Coffee & Tea | D22: Pcs | E22: ='Store Inventory'!F22 -> 3 | F22: =SUMIF('Recipe Master'!$D$4:$D$146,A22,'Recipe Master'!$J$4:$J$146) -> 74 | G22: =SUMIF('Sub-Recipe'!$D$4:$D$67,A22,'Sub-Recipe'!$N$4:$N$67) -> 0 | H22: =F22+G22 -> 74 | I22: =H22*E22 -> 222 | J22: ='Store Issue'!P23 -> 0 | K22: =J22*E22 -> 0 | L22: =J22-H22 -> -74 | M22: =K22-I22 -> -222 | N22: =IFERROR(L22/H22,0) -> -1
A23: BV003 | B23: Green Tea Bags | C23: Coffee & Tea | D23: Pcs | E23: ='Store Inventory'!F23 -> 4 | F23: =SUMIF('Recipe Master'!$D$4:$D$146,A23,'Recipe Master'!$J$4:$J$146) -> 53 | G23: =SUMIF('Sub-Recipe'!$D$4:$D$67,A23,'Sub-Recipe'!$N$4:$N$67) -> 0 | H23: =F23+G23 -> 53 | I23: =H23*E23 -> 212 | J23: ='Store Issue'!P24 -> 0 | K23: =J23*E23 -> 0 | L23: =J23-H23 -> -53 | M23: =K23-I23 -> -212 | N23: =IFERROR(L23/H23,0) -> -1
A24: BV004 | B24: Fresh Milk | C24: Dairy & Bar | D24: Ltr | E24: ='Store Inventory'!F24 -> 65.461538 | F24: =SUMIF('Recipe Master'!$D$4:$D$146,A24,'Recipe Master'!$J$4:$J$146) -> 42.85 | G24: =SUMIF('Sub-Recipe'!$D$4:$D$67,A24,'Sub-Recipe'!$N$4:$N$67) -> 3 | H24: =F24+G24 -> 45.85 | I24: =H24*E24 -> 3001.4115 | J24: ='Store Issue'!P25 -> 85 | K24: =J24*E24 -> 5564.2308 | L24: =J24-H24 -> 39.15 | M24: =K24-I24 -> 2562.8192 | N24: =IFERROR(L24/H24,0) -> 0.85387132
A25: BV005 | B25: Cocoa Powder | C25: Coffee & Tea | D25: Kg | E25: ='Store Inventory'!F25 -> 350 | F25: =SUMIF('Recipe Master'!$D$4:$D$146,A25,'Recipe Master'!$J$4:$J$146) -> 1.56 | G25: =SUMIF('Sub-Recipe'!$D$4:$D$67,A25,'Sub-Recipe'!$N$4:$N$67) -> 0 | H25: =F25+G25 -> 1.56 | I25: =H25*E25 -> 546 | J25: ='Store Issue'!P26 -> 0 | K25: =J25*E25 -> 0 | L25: =J25-H25 -> -1.56 | M25: =K25-I25 -> -546 | N25: =IFERROR(L25/H25,0) -> -1
A26: BV006 | B26: White Rum | C26: Bar & Spirits | D26: Ltr | E26: ='Store Inventory'!F26 -> 950 | F26: =SUMIF('Recipe Master'!$D$4:$D$146,A26,'Recipe Master'!$J$4:$J$146) -> 5.25 | G26: =SUMIF('Sub-Recipe'!$D$4:$D$67,A26,'Sub-Recipe'!$N$4:$N$67) -> 0 | H26: =F26+G26 -> 5.25 | I26: =H26*E26 -> 4987.5 | J26: ='Store Issue'!P27 -> 6 | K26: =J26*E26 -> 5700 | L26: =J26-H26 -> 0.75 | M26: =K26-I26 -> 712.5 | N26: =IFERROR(L26/H26,0) -> 0.14285714
A27: BV007 | B27: Fresh Mint Leaves | C27: Bar Garnish | D27: Kg | E27: ='Store Inventory'!F27 -> 150 | F27: =SUMIF('Recipe Master'!$D$4:$D$146,A27,'Recipe Master'!$J$4:$J$146) -> 0 | G27: =SUMIF('Sub-Recipe'!$D$4:$D$67,A27,'Sub-Recipe'!$N$4:$N$67) -> 0.525 | H27: =F27+G27 -> 0.525 | I27: =H27*E27 -> 78.75 | J27: ='Store Issue'!P28 -> 0 | K27: =J27*E27 -> 0 | L27: =J27-H27 -> -0.525 | M27: =K27-I27 -> -78.75 | N27: =IFERROR(L27/H27,0) -> -1
A28: BV008 | B28: Fresh Lime | C28: Bar Garnish | D28: Kg | E28: ='Store Inventory'!F28 -> 100 | F28: =SUMIF('Recipe Master'!$D$4:$D$146,A28,'Recipe Master'!$J$4:$J$146) -> 2.3 | G28: =SUMIF('Sub-Recipe'!$D$4:$D$67,A28,'Sub-Recipe'!$N$4:$N$67) -> 2.495 | H28: =F28+G28 -> 4.795 | I28: =H28*E28 -> 479.5 | J28: ='Store Issue'!P29 -> 6 | K28: =J28*E28 -> 600 | L28: =J28-H28 -> 1.205 | M28: =K28-I28 -> 120.5 | N28: =IFERROR(L28/H28,0) -> 0.25130344
A29: BV009 | B29: Fresh Avocado | C29: Fresh Produce | D29: Kg | E29: ='Store Inventory'!F29 -> 90 | F29: =SUMIF('Recipe Master'!$D$4:$D$146,A29,'Recipe Master'!$J$4:$J$146) -> 17.95 | G29: =SUMIF('Sub-Recipe'!$D$4:$D$67,A29,'Sub-Recipe'!$N$4:$N$67) -> 0 | H29: =F29+G29 -> 17.95 | I29: =H29*E29 -> 1615.5 | J29: ='Store Issue'!P30 -> 12 | K29: =J29*E29 -> 1080 | L29: =J29-H29 -> -5.95 | M29: =K29-I29 -> -535.5 | N29: =IFERROR(L29/H29,0) -> -0.33147632
A30: BV010 | B30: Soda Water | C30: Bar & Mixers | D30: Ltr | E30: ='Store Inventory'!F30 -> 45 | F30: =SUMIF('Recipe Master'!$D$4:$D$146,A30,'Recipe Master'!$J$4:$J$146) -> 15.75 | G30: =SUMIF('Sub-Recipe'!$D$4:$D$67,A30,'Sub-Recipe'!$N$4:$N$67) -> 0 | H30: =F30+G30 -> 15.75 | I30: =H30*E30 -> 708.75 | J30: ='Store Issue'!P31 -> 18 | K30: =J30*E30 -> 810 | L30: =J30-H30 -> 2.25 | M30: =K30-I30 -> 101.25 | N30: =IFERROR(L30/H30,0) -> 0.14285714
A31: BV011 | B31: Coca-Cola (330ml Bottle) | C31: Soft Drinks | D31: Bottle | E31: ='Store Inventory'!F31 -> 35 | F31: =SUMIF('Recipe Master'!$D$4:$D$146,A31,'Recipe Master'!$J$4:$J$146) -> 103 | G31: =SUMIF('Sub-Recipe'!$D$4:$D$67,A31,'Sub-Recipe'!$N$4:$N$67) -> 0 | H31: =F31+G31 -> 103 | I31: =H31*E31 -> 3605 | J31: ='Store Issue'!P32 -> 150 | K31: =J31*E31 -> 5250 | L31: =J31-H31 -> 47 | M31: =K31-I31 -> 1645 | N31: =IFERROR(L31/H31,0) -> 0.45631068
A32: OTHERS
A33: OT001 | B33: Burger Takeaway Box | C33: Packaging | D33: Pcs | E33: ='Store Inventory'!F33 -> 8 | F33: =SUMIF('Recipe Master'!$D$4:$D$146,A33,'Recipe Master'!$J$4:$J$146) -> 29 | G33: =SUMIF('Sub-Recipe'!$D$4:$D$67,A33,'Sub-Recipe'!$N$4:$N$67) -> 0 | H33: =F33+G33 -> 29 | I33: =H33*E33 -> 232 | J33: ='Store Issue'!P34 -> 280 | K33: =J33*E33 -> 2240 | L33: =J33-H33 -> 251 | M33: =K33-I33 -> 2008 | N33: =IFERROR(L33/H33,0) -> 8.6551724
A34: OT002 | B34: Pizza Takeaway Box | C34: Packaging | D34: Pcs | E34: ='Store Inventory'!F34 -> 15 | F34: =SUMIF('Recipe Master'!$D$4:$D$146,A34,'Recipe Master'!$J$4:$J$146) -> 24 | G34: =SUMIF('Sub-Recipe'!$D$4:$D$67,A34,'Sub-Recipe'!$N$4:$N$67) -> 0 | H34: =F34+G34 -> 24 | I34: =H34*E34 -> 360 | J34: ='Store Issue'!P35 -> 200 | K34: =J34*E34 -> 3000 | L34: =J34-H34 -> 176 | M34: =K34-I34 -> 2640 | N34: =IFERROR(L34/H34,0) -> 7.3333333
A35: OT003 | B35: Paper Napkins | C35: Consumables | D35: Pcs | E35: ='Store Inventory'!F35 -> 1 | F35: =SUMIF('Recipe Master'!$D$4:$D$146,A35,'Recipe Master'!$J$4:$J$146) -> 0 | G35: =SUMIF('Sub-Recipe'!$D$4:$D$67,A35,'Sub-Recipe'!$N$4:$N$67) -> 0 | H35: =F35+G35 -> 0 | I35: =H35*E35 -> 0 | J35: ='Store Issue'!P36 -> 0 | K35: =J35*E35 -> 0 | L35: =J35-H35 -> 0 | M35: =K35-I35 -> 0 | N35: =IFERROR(L35/H35,0) -> 0
A36: OT004 | B36: Disposable Straws | C36: Consumables | D36: Pcs | E36: ='Store Inventory'!F36 -> 1 | F36: =SUMIF('Recipe Master'!$D$4:$D$146,A36,'Recipe Master'!$J$4:$J$146) -> 0 | G36: =SUMIF('Sub-Recipe'!$D$4:$D$67,A36,'Sub-Recipe'!$N$4:$N$67) -> 0 | H36: =F36+G36 -> 0 | I36: =H36*E36 -> 0 | J36: ='Store Issue'!P37 -> 0 | K36: =J36*E36 -> 0 | L36: =J36-H36 -> 0 | M36: =K36-I36 -> 0 | N36: =IFERROR(L36/H36,0) -> 0
A37: OT005 | B37: White Sugar | C37: Pantry & Dry Goods | D37: Kg | E37: ='Store Inventory'!F37 -> 60 | F37: =SUMIF('Recipe Master'!$D$4:$D$146,A37,'Recipe Master'!$J$4:$J$146) -> 1.04 | G37: =SUMIF('Sub-Recipe'!$D$4:$D$67,A37,'Sub-Recipe'!$N$4:$N$67) -> 4.733 | H37: =F37+G37 -> 5.773 | I37: =H37*E37 -> 346.38 | J37: ='Store Issue'!P38 -> 20 | K37: =J37*E37 -> 1200 | L37: =J37-H37 -> 14.227 | M37: =K37-I37 -> 853.62 | N37: =IFERROR(L37/H37,0) -> 2.4644033
A38: OT006 | B38: Iodized Salt | C38: Pantry & Dry Goods | D38: Kg | E38: ='Store Inventory'!F38 -> 25 | F38: =SUMIF('Recipe Master'!$D$4:$D$146,A38,'Recipe Master'!$J$4:$J$146) -> 0 | G38: =SUMIF('Sub-Recipe'!$D$4:$D$67,A38,'Sub-Recipe'!$N$4:$N$67) -> 0.92 | H38: =F38+G38 -> 0.92 | I38: =H38*E38 -> 23 | J38: ='Store Issue'!P39 -> 0 | K38: =J38*E38 -> 0 | L38: =J38-H38 -> -0.92 | M38: =K38-I38 -> -23 | N38: =IFERROR(L38/H38,0) -> -1
A39: OT007 | B39: Cooking / Vegetable Oil | C39: Pantry & Dry Goods | D39: Ltr | E39: ='Store Inventory'!F39 -> 150 | F39: =SUMIF('Recipe Master'!$D$4:$D$146,A39,'Recipe Master'!$J$4:$J$146) -> 3.56 | G39: =SUMIF('Sub-Recipe'!$D$4:$D$67,A39,'Sub-Recipe'!$N$4:$N$67) -> 1.4785 | H39: =F39+G39 -> 5.0385 | I39: =H39*E39 -> 755.775 | J39: ='Store Issue'!P40 -> 18 | K39: =J39*E39 -> 2700 | L39: =J39-H39 -> 12.9615 | M39: =K39-I39 -> 1944.225 | N39: =IFERROR(L39/H39,0) -> 2.5724918
A40: OT008 | B40: Instant Dry Yeast | C40: Pantry & Dry Goods | D40: Kg | E40: ='Store Inventory'!F40 -> 400 | F40: =SUMIF('Recipe Master'!$D$4:$D$146,A40,'Recipe Master'!$J$4:$J$146) -> 0 | G40: =SUMIF('Sub-Recipe'!$D$4:$D$67,A40,'Sub-Recipe'!$N$4:$N$67) -> 1.012 | H40: =F40+G40 -> 1.012 | I40: =H40*E40 -> 404.8 | J40: ='Store Issue'!P41 -> 8 | K40: =J40*E40 -> 3200 | L40: =J40-H40 -> 6.988 | M40: =K40-I40 -> 2795.2 | N40: =IFERROR(L40/H40,0) -> 6.9051383
A41: OT009 | B41: Black Pepper (Ground) | C41: Pantry & Dry Goods | D41: Kg | E41: ='Store Inventory'!F41 -> 500 | F41: =SUMIF('Recipe Master'!$D$4:$D$146,A41,'Recipe Master'!$J$4:$J$146) -> 0 | G41: =SUMIF('Sub-Recipe'!$D$4:$D$67,A41,'Sub-Recipe'!$N$4:$N$67) -> 0.152 | H41: =F41+G41 -> 0.152 | I41: =H41*E41 -> 76 | J41: ='Store Issue'!P42 -> 0 | K41: =J41*E41 -> 0 | L41: =J41-H41 -> -0.152 | M41: =K41-I41 -> -76 | N41: =IFERROR(L41/H41,0) -> -1

Sheet Inventory Variance
A1: INVENTORY VARIANCE
A2: Perpetual book stock vs physical count at the outlet — where shrinkage hides
A3: ITEM CODE | B3: ITEM NAME | C3: CATEGORY | D3: UOM | E3: AVG. COST | F3: BOOK QTY (Kitchen Expected) | G3: PHYSICAL COUNT (latest, enter below) | H3: QTY VARIANCE | I3: COST VARIANCE | J3: VARIANCE % | K3: STATUS
A4: FOOD
A5: FD001 | B5: Beef Mince (80% Lean) | C5: Meat & Poultry | D5: Kg | E5: ='Store Inventory'!F5 -> 557.35294 | F5: ='Kitchen & Bar Receiving'!P6-'Theoretical Consumption'!H5 -> 1.8 | G5: 6 | H5: =G5-F5 -> 4.2 | I5: =H5*E5 -> 2340.8824 | J5: =IFERROR(H5/F5,0) -> 2.3333333 | K5: =IF(ABS(J5)<=0.03,"OK",IF(ABS(J5)<=0.08,"REVIEW","INVESTIGATE")) -> INVESTIGATE
A6: FD002 | B6: Chicken Breast (Boneless) | C6: Meat & Poultry | D6: Kg | E6: ='Store Inventory'!F6 -> 482.66667 | F6: ='Kitchen & Bar Receiving'!P7-'Theoretical Consumption'!H6 -> -2.23 | G6: 4 | H6: =G6-F6 -> 6.23 | I6: =H6*E6 -> 3007.0133 | J6: =IFERROR(H6/F6,0) -> -2.793722 | K6: =IF(ABS(J6)<=0.03,"OK",IF(ABS(J6)<=0.08,"REVIEW","INVESTIGATE")) -> INVESTIGATE
A7: FD003 | B7: Bacon Strips | C7: Meat & Poultry | D7: Kg | E7: ='Store Inventory'!F7 -> 650 | F7: ='Kitchen & Bar Receiving'!P8-'Theoretical Consumption'!H7 -> 4.46 | G7: 0 | H7: =G7-F7 -> -4.46 | I7: =H7*E7 -> -2899 | J7: =IFERROR(H7/F7,0) -> -1 | K7: =IF(ABS(J7)<=0.03,"OK",IF(ABS(J7)<=0.08,"REVIEW","INVESTIGATE")) -> INVESTIGATE
A8: FD004 | B8: Fresh Lettuce | C8: Fresh Produce | D8: Kg | E8: ='Store Inventory'!F8 -> 60 | F8: ='Kitchen & Bar Receiving'!P9-'Theoretical Consumption'!H8 -> 7.67 | G8: 3 | H8: =G8-F8 -> -4.67 | I8: =H8*E8 -> -280.2 | J8: =IFERROR(H8/F8,0) -> -0.60886571 | K8: =IF(ABS(J8)<=0.03,"OK",IF(ABS(J8)<=0.08,"REVIEW","INVESTIGATE")) -> INVESTIGATE
A9: FD005 | B9: Fresh Tomato | C9: Fresh Produce | D9: Kg | E9: ='Store Inventory'!F9 -> 56 | F9: ='Kitchen & Bar Receiving'!P10-'Theoretical Consumption'!H9 -> 2.545 | G9: 3 | H9: =G9-F9 -> 0.455 | I9: =H9*E9 -> 25.48 | J9: =IFERROR(H9/F9,0) -> 0.17878193 | K9: =IF(ABS(J9)<=0.03,"OK",IF(ABS(J9)<=0.08,"REVIEW","INVESTIGATE")) -> INVESTIGATE
A10: FD006 | B10: Onion | C10: Fresh Produce | D10: Kg | E10: ='Store Inventory'!F10 -> 40 | F10: ='Kitchen & Bar Receiving'!P11-'Theoretical Consumption'!H10 -> 1.425 | G10: 0 | H10: =G10-F10 -> -1.425 | I10: =H10*E10 -> -57 | J10: =IFERROR(H10/F10,0) -> -1 | K10: =IF(ABS(J10)<=0.03,"OK",IF(ABS(J10)<=0.08,"REVIEW","INVESTIGATE")) -> INVESTIGATE
A11: FD007 | B11: Cheddar Cheese Slice | C11: Dairy | D11: Pcs | E11: ='Store Inventory'!F11 -> 12 | F11: ='Kitchen & Bar Receiving'!P12-'Theoretical Consumption'!H11 -> -120 | G11: 0 | H11: =G11-F11 -> 120 | I11: =H11*E11 -> 1440 | J11: =IFERROR(H11/F11,0) -> -1 | K11: =IF(ABS(J11)<=0.03,"OK",IF(ABS(J11)<=0.08,"REVIEW","INVESTIGATE")) -> INVESTIGATE
A12: FD008 | B12: All-Purpose Flour | C12: Bakery & Dry Goods | D12: Kg | E12: ='Store Inventory'!F12 -> 55 | F12: ='Kitchen & Bar Receiving'!P13-'Theoretical Consumption'!H12 -> -24.5 | G12: 0 | H12: =G12-F12 -> 24.5 | I12: =H12*E12 -> 1347.5 | J12: =IFERROR(H12/F12,0) -> -1 | K12: =IF(ABS(J12)<=0.03,"OK",IF(ABS(J12)<=0.08,"REVIEW","INVESTIGATE")) -> INVESTIGATE
A13: FD009 | B13: Butter (Unsalted) | C13: Dairy | D13: Kg | E13: ='Store Inventory'!F13 -> 480 | F13: ='Kitchen & Bar Receiving'!P14-'Theoretical Consumption'!H13 -> -5.278 | G13: 1.5 | H13: =G13-F13 -> 6.778 | I13: =H13*E13 -> 3253.44 | J13: =IFERROR(H13/F13,0) -> -1.2841986 | K13: =IF(ABS(J13)<=0.03,"OK",IF(ABS(J13)<=0.08,"REVIEW","INVESTIGATE")) -> INVESTIGATE
A14: FD010 | B14: Fresh Eggs | C14: Dairy | D14: Pcs | E14: ='Store Inventory'!F14 -> 8 | F14: ='Kitchen & Bar Receiving'!P15-'Theoretical Consumption'!H14 -> -11.6 | G14: 0 | H14: =G14-F14 -> 11.6 | I14: =H14*E14 -> 92.8 | J14: =IFERROR(H14/F14,0) -> -1 | K14: =IF(ABS(J14)<=0.03,"OK",IF(ABS(J14)<=0.08,"REVIEW","INVESTIGATE")) -> INVESTIGATE
A15: FD011 | B15: Spaghetti Pasta | C15: Bakery & Dry Goods | D15: Kg | E15: ='Store Inventory'!F15 -> 120 | F15: ='Kitchen & Bar Receiving'!P16-'Theoretical Consumption'!H15 -> -4.8 | G15: 0 | H15: =G15-F15 -> 4.8 | I15: =H15*E15 -> 576 | J15: =IFERROR(H15/F15,0) -> -1 | K15: =IF(ABS(J15)<=0.03,"OK",IF(ABS(J15)<=0.08,"REVIEW","INVESTIGATE")) -> INVESTIGATE
A16: FD012 | B16: Tortilla Wrap | C16: Bakery & Dry Goods | D16: Pcs | E16: ='Store Inventory'!F16 -> 15 | F16: ='Kitchen & Bar Receiving'!P17-'Theoretical Consumption'!H16 -> -54 | G16: 0 | H16: =G16-F16 -> 54 | I16: =H16*E16 -> 810 | J16: =IFERROR(H16/F16,0) -> -1 | K16: =IF(ABS(J16)<=0.03,"OK",IF(ABS(J16)<=0.08,"REVIEW","INVESTIGATE")) -> INVESTIGATE
... A19: FD015 | B19: Mozzarella Cheese | C19: Dairy | D19: Kg | E19: ='Store Inventory'!F19 -> 620 | F19: ='Kitchen & Bar Receiving'!P20-'Theoretical Consumption'!H19 -> -3.09 | G19: 0 | H19: =G19-F19 -> 3.09 | I19: =H19*E19 -> 1915.8 | J19: =IFERROR(H19/F19,0) -> -1 | K19: =IF(ABS(J19)<=0.03,"OK",IF(ABS(J19)<=0.08,"REVIEW","INVESTIGATE")) -> INVESTIGATE
A20: BEVERAGE
A21: BV001 | B21: Coffee Beans (Roasted) | C21: Coffee & Tea | D21: Kg | E21: ='Store Inventory'!F21 -> 900 | F21: ='Kitchen & Bar Receiving'!P22-'Theoretical Consumption'!H21 -> 9.708 | G21: 0 | H21: =G21-F21 -> -9.708 | I21: =H21*E21 -> -8737.2 | J21: =IFERROR(H21/F21,0) -> -1 | K21: =IF(ABS(J21)<=0.03,"OK",IF(ABS(J21)<=0.08,"REVIEW","INVESTIGATE")) -> INVESTIGATE
A22: BV002 | B22: Black Tea Bags | C22: Coffee & Tea | D22: Pcs | E22: ='Store Inventory'!F22 -> 3 | F22: ='Kitchen & Bar Receiving'!P23-'Theoretical Consumption'!H22 -> -74 | G22: 0 | H22: =G22-F22 -> 74 | I22: =H22*E22 -> 222 | J22: =IFERROR(H22/F22,0) -> -1 | K22: =IF(ABS(J22)<=0.03,"OK",IF(ABS(J22)<=0.08,"REVIEW","INVESTIGATE")) -> INVESTIGATE
A23: BV003 | B23: Green Tea Bags | C23: Coffee & Tea | D23: Pcs | E23: ='Store Inventory'!F23 -> 4 | F23: ='Kitchen & Bar Receiving'!P24-'Theoretical Consumption'!H23 -> -53 | G23: 0 | H23: =G23-F23 -> 53 | I23: =H23*E23 -> 212 | J23: =IFERROR(H23/F23,0) -> -1 | K23: =IF(ABS(J23)<=0.03,"OK",IF(ABS(J23)<=0.08,"REVIEW","INVESTIGATE")) -> INVESTIGATE
A24: BV004 | B24: Fresh Milk | C24: Dairy & Bar | D24: Ltr | E24: ='Store Inventory'!F24 -> 65.461538 | F24: ='Kitchen & Bar Receiving'!P25-'Theoretical Consumption'!H24 -> 39.15 | G24: 9 | H24: =G24-F24 -> -30.15 | I24: =H24*E24 -> -1973.6654 | J24: =IFERROR(H24/F24,0) -> -0.77011494 | K24: =IF(ABS(J24)<=0.03,"OK",IF(ABS(J24)<=0.08,"REVIEW","INVESTIGATE")) -> INVESTIGATE
A25: BV005 | B25: Cocoa Powder | C25: Coffee & Tea | D25: Kg | E25: ='Store Inventory'!F25 -> 350 | F25: ='Kitchen & Bar Receiving'!P26-'Theoretical Consumption'!H25 -> -1.56 | G25: 0 | H25: =G25-F25 -> 1.56 | I25: =H25*E25 -> 546 | J25: =IFERROR(H25/F25,0) -> -1 | K25: =IF(ABS(J25)<=0.03,"OK",IF(ABS(J25)<=0.08,"REVIEW","INVESTIGATE")) -> INVESTIGATE
A26: BV006 | B26: White Rum | C26: Bar & Spirits | D26: Ltr | E26: ='Store Inventory'!F26 -> 950 | F26: ='Kitchen & Bar Receiving'!P27-'Theoretical Consumption'!H26 -> 0.75 | G26: 0 | H26: =G26-F26 -> -0.75 | I26: =H26*E26 -> -712.5 | J26: =IFERROR(H26/F26,0) -> -1 | K26: =IF(ABS(J26)<=0.03,"OK",IF(ABS(J26)<=0.08,"REVIEW","INVESTIGATE")) -> INVESTIGATE
A27: BV007 | B27: Fresh Mint Leaves | C27: Bar Garnish | D27: Kg | E27: ='Store Inventory'!F27 -> 150 | F27: ='Kitchen & Bar Receiving'!P28-'Theoretical Consumption'!H27 -> -0.525 | G27: 0 | H27: =G27-F27 -> 0.525 | I27: =H27*E27 -> 78.75 | J27: =IFERROR(H27/F27,0) -> -1 | K27: =IF(ABS(J27)<=0.03,"OK",IF(ABS(J27)<=0.08,"REVIEW","INVESTIGATE")) -> INVESTIGATE
A28: BV008 | B28: Fresh Lime | C28: Bar Garnish | D28: Kg | E28: ='Store Inventory'!F28 -> 100 | F28: ='Kitchen & Bar Receiving'!P29-'Theoretical Consumption'!H28 -> 1.205 | G28: 0 | H28: =G28-F28 -> -1.205 | I28: =H28*E28 -> -120.5 | J28: =IFERROR(H28/F28,0) -> -1 | K28: =IF(ABS(J28)<=0.03,"OK",IF(ABS(J28)<=0.08,"REVIEW","INVESTIGATE")) -> INVESTIGATE
